Workbook

Sheet final_df
A1: id | B1: interviewer1 | C1: interviewer2 | D1: birth_year | E1: gender | F1: education | G1: housing_type | H1: household_size | I1: num_children | J1: apartment_size | K1: apartment_location | L1: occupation | M1: years_in_district | N1: years_in_apartment | O1: prev_residence | P1: prev_district | Q1: prev_aggr | R1: housing_expenses_total | S1: utilities_cost | T1: rent_cost | U1: mortgage_cost | V1: total_income | W1: expense_coverage | X1: address | Y1: floor | Z1: contact | AA1: apartment_quality | AB1: extra_notes | AC1: interview_length | AD1: other_comments | AE1: elhelyezkedés | AF1: housing_overburden | AG1: lakhatasi_szegeny | AH1: income_per_person | AI1: education_aggr | AJ1: age_group | AK1: housing_type_aggr | AL1: housing_expenses_PP | AM1: category | AN1: f_years_in_apartment_grp | AO1: income_group | AP1: Ideköltözés okai és körülményei - Családi / személyes okok | AQ1: Pozitív / Negatív - Negatív | AR1: Pozitív / Negatív - Pozitív | AS1: Társasházak működése (jelenleg) - Fizikai állapot / karbantartás | AT1: Társasházak működése (jelenleg) - Közös képviselet | AU1: Társasházak működése (jelenleg) - Közös terek használata | AV1: Társasházak működése (jelenleg) - Közösségi élet | AW1: Utca változásai - Fizikai környezet és utcakép változásai | AX1: Utca változásai - Lakossági összetétel / közösségek | AY1: Utca változásai - Üzletek / szolgáltatások / vendéglátás | AZ1: Utcahasználat (jelenleg) - Vásárlás / boltok / szolgáltatások | BA1: Utcán mit változtatna - Közlekedés | BB1: Utcával kapcsolatos attitűdök - Biztonságérzet | BC1: Utcával kapcsolatos attitűdök - Környezeti benyomások (zaj / szmog / más) | BD1: Utcával kapcsolatos attitűdök - Társadalmi sokszínűség (etnikai / osztálybeli / más) | BE1: Önkormányzati szerep - Jelenleg | BF1: Önkormányzati szerep - Jövőre - Utcánál | BG1: Ideköltözés okai és körülményei - Anyagi | BH1: Ideköltözés okai és körülményei - Kulturális | BI1: Izgalmas idézet - Tanulmányba / kiállíásra | BJ1: Jövőkép a társasházról - Lakóközösség cseréje | BK1: Jövőkép a társasházról - Változtatná a társasházon | BL1: Jövőkép a társasházról - Általános jövőkép | BM1: Jövőkép az utcáról - Jövőkép az utcáról | BN1: Lakhatási helyzet - Elhelyezkedés | BO1: Lakhatási helyzet - Komfortszint | BP1: Társasházak működése (jelenleg) - Biztonság | BQ1: Társasházak működése (jelenleg) - Lakóközösség változása | BR1: Utca változásai - Közbiztonság és közterületi viselkedés | BS1: Utcahasználat (jelenleg) - Közlekedési élmények | BT1: Utcahasználat (jelenleg) - Közterület használata | BU1: Utcahasználat (jelenleg) - Közösségi interakciók az utcán | BV1: Utcahasználat (jelenleg) - Szabadidő / szórakozás / vendéglátás | BW1: Utcai fejlesztések értékelése - Blaha Lujza tér | BX1: Utcai fejlesztések értékelése - II. János Pál pápa tér | BY1: Utcai fejlesztések értékelése - Négyes metró | BZ1: Utcai fejlesztések értékelése - Utcai zöldítések | CA1: Utcán mit változtatna - Infrastuktúra | CB1: Utcával kapcsolatos attitűdök - Tisztaság / rendezettség | CC1: Utcával kapcsolatos attitűdök - Érzelmi kötődés | CD1: Utcán mit változtatna - Közbiztonság javítása | CE1: Utcán mit változtatna - Szociális ellátórendszer | CF1: Utcán mit változtatna - Tisztaság / rendezettség javítása | CG1: Ideköltözés okai és körülményei - Munka / közlekedés | CH1: Izgalmas idézet - Csak vicces | CI1: Utcai fejlesztések értékelése - Nincs hatása | CJ1: Utcai fejlesztések értékelése - Teleki tér | CK1: Utcán mit változtatna - Szabadidő / szórakozás / vendéglátás - változtatna | CL1: Utcán mit változtatna - Zöldítés | CM1: Önkormányzati szerep - Jövőre - Társasháznál | CN1: Jövőkép a társasházról - Lakóközösség szerepe | CO1: Utcán mit változtatna - Vásárlás / boltok / szolgáltatások - változtatna | CP1: NA - NA | CQ1: Jövőkép a társasházról - Közös képviselet szerepe
A2: BBGB01 | B2: Bekker Balázs | C2: Gecse Barbara | D2: 1960 | E2: Nő | F2: főiskolai v. egyetemi diploma | G2: saját tulajdon | H2: 2 | I2: 0 | K2: utcai | L2: Óvodavezető | M2: 2015 | N2: 2015 | O2: Budapest | P2: 7 | Q2: Budapest (Pest) | R2: 63000 | S2: 63000 | V2: 450000 | W2: Könnyen | X2: Népszínház 31. | Y2: 2 | AA2: Lakás teljesen rendezett, tiszta. a zunokájával ketten élnek. van egy nyuszi | AB2: pár éve meghalt a lánya és ezért vette az unokáját maga mellé. | AC2: 32 | AE2: Kiss József utca - Nagy Fuvaros utca | AF2: 0.14 | AG2: FALSE | AH2: 225000 | AI2: diploma | AJ2: 50 és 64 év közötti | AK2: tulajdonos | AL2: 31500 | AM2: idős | AN2: 1990 és 2016 között | AO2: Middle | AP2: 1 | AQ2: 2 | AR2: 6 | AS2: 1 | AT2: 4 | AU2: 1 | AV2: 2 | AW2: 2 | AX2: 2 | AY2: 1 | AZ2: 2 | BA2: 2 | BB2: 1 | BC2: 1 | BD2: 2 | BE2: 1 | BF2: 1 | BG2: 0 | BH2: 0 | BI2: 0 | BJ2: 0 | BK2: 0 | BL2: 0 | BM2: 0 | BN2: 0 | BO2: 0 | BP2: 0 | BQ2: 0 | BR2: 0 | BS2: 0 | BT2: 0 | BU2: 0 | BV2: 0 | BW2: 0 | BX2: 0 | BY2: 0 | BZ2: 0 | CA2: 0 | CB2: 0 | CC2: 0 | CD2: 0 | CE2: 0 | CF2: 0 | CG2: 0 | CH2: 0 | CI2: 0 | CJ2: 0 | CK2: 0 | CL2: 0 | CM2: 0 | CN2: 0 | CO2: 0 | CP2: 0 | CQ2: 0
A3: BNGC01 | B3: Baranya Nikoletta | C3: Gregor Csaba | D3: 1971 | E3: Nő | F3: főiskolai v. egyetemi diploma | G3: saját tulajdon | H3: 2 | I3: 0 | J3: 105 | K3: utcai | L3: adatvédelmi szakértő -> 5 hónapja munkanélküli | M3: 2021 | N3: 2021 | O3: Budapest | P3: 2 | Q3: Budapest (Buda) | R3: 352000 | S3: 132000 | U3: 220000 | V3: 1800000 | W3: Viszonylag nehezen | X3: Népszínház 32. | Y3: 4 | AA3: Nagyon értelmiségi lakás, tágas otthonosan limlomos | AB3: Azért jönnek ki viszonylag nehezen a pénzből mert a gyerekek külföldi taníttatására sokat költenek | AC3: 69 | AE3: Nagy Fuvaros utca - Alföldi utca | AF3: 0.19555556 | AG3: FALSE | AH3: 900000 | AI3: diploma | AJ3: 50 és 64 év közötti | AK3: tulajdonos | AL3: 176000 | AM3: fiatal tulajdonos | AN3: 2016 és 2023 között | AO3: High | AP3: 1 | AQ3: 19 | AR3: 12 | AS3: 2 | AT3: 1 | AU3: 3 | AV3: 3 | AW3: 1 | AX3: 3 | AY3: 0 | AZ3: 2 | BA3: 1 | BB3: 3 | BC3: 3 | BD3: 12 | BE3: 5 | BF3: 2 | BG3: 1 | BH3: 1 | BI3: 6 | BJ3: 1 | BK3: 1 | BL3: 1 | BM3: 2 | BN3: 1 | BO3: 1 | BP3: 2 | BQ3: 5 | BR3: 3 | BS3: 1 | BT3: 3 | BU3: 1 | BV3: 3 | BW3: 1 | BX3: 2 | BY3: 1 | BZ3: 1 | CA3: 2 | CB3: 6 | CC3: 1 | CD3: 0 | CE3: 0 | CF3: 0 | CG3: 0 | CH3: 0 | CI3: 0 | CJ3: 0 | CK3: 0 | CL3: 0 | CM3: 0 | CN3: 0 | CO3: 0 | CP3: 0 | CQ3: 0
A4: BNGC02 | B4: Gregor Csaba | C4: Baranya Nikolett | D4: 2004 | E4: Nő | F4: gimnáziumi érettségi | G4: piaci bérlet | H4: 2 | I4: 0 | J4: 50 | K4: udvari | L4: ruházati boltban eladó | M4: 2024 | N4: 2024 | O4: Székesfehérvár | Q4: Dunántúl | R4: 294000 | S4: 99000 | T4: 195000 | V4: 900000 | W4: Viszonylag könnyen | X4: Népszínház 13. | Y4: 3 | AA4: a lakásban nagytakarítás volt, ezért az erkélyen ültünk | AC4: 49 | AE4: József krt. - Kiss József utca | AF4: 0.32666667 | AG4: TRUE | AH4: 450000 | AI4: érettségi | AJ4: 18 és 29 év közötti | AK4: nem tulajdonos | AL4: 147000 | AM4: fiatal bérlő | AN4: utóbbi két évben | AO4: High | AP4: 1 | AQ4: 12 | AR4: 8 | AS4: 1 | AT4: 0 | AU4: 0 | AV4: 2 | AW4: 0 | AX4: 0 | AY4: 0 | AZ4: 3 | BA4: 0 | BB4: 7 | BC4: 2 | BD4: 7 | BE4: 0 | BF4: 0 | BG4: 0 | BH4: 0 | BI4: 2 | BJ4: 0 | BK4: 1 | BL4: 0 | BM4: 3 | BN4: 0 | BO4: 2 | BP4: 2 | BQ4: 2 | BR4: 0 | BS4: 1 | BT4: 0 | BU4: 0 | BV4: 1 | BW4: 0 | BX4: 0 | BY4: 0 | BZ4: 0 | CA4: 1 | CB4: 5 | CC4: 0 | CD4: 3 | CE4: 4 | CF4: 1 | CG4: 0 | CH4: 0 | CI4: 0 | CJ4: 0 | CK4: 0 | CL4: 0 | CM4: 0 | CN4: 0 | CO4: 0 | CP4: 0 | CQ4: 0
A5: BNJR01 | B5: Baranya Nikoletta | C5: Jankó Rebeka | D5: 1996 | E5: Férfi | F5: gimnáziumi érettségi | G5: saját tulajdon | H5: 3 | I5: 0 | J5: 58 | K5: udvari | L5: IT account manager | M5: 2017 | N5: 2018 | O5: Budapest | P5: 8 | Q5: Nyolcadik kerület | R5: 140000 | S5: 75000 | U5: 65000 | V5: 850000 | W5: Viszonylag könnyen | X5: Népszínház 16. | Y5: 0 | AA5: Nem volt jó állapotú, de nem is lepukkant. nem felújított. kvázi a barátnője is itt él. | AC5: 49 | AE5: József krt. - Kiss József utca | AF5: 0.16470588 | AG5: FALSE | AH5: 283333.33 | AI5: érettségi | AJ5: 18 és 29 év közötti | AK5: tulajdonos | AL5: 46666.667 | AM5: fiatal tulajdonos | AN5: 2016 és 2023 között | AO5: Middle | AP5: 0 | AQ5: 15 | AR5: 13 | AS5: 2 | AT5: 2 | AU5: 5 | AV5: 5 | AW5: 1 | AX5: 0 | AY5: 0 | AZ5: 4 | BA5: 2 | BB5: 6 | BC5: 0 | BD5: 8 | BE5: 5 | BF5: 1 | BG5: 1 | BH5: 0 | BI5: 2 | BJ5: 0 | BK5: 2 | BL5: 0 | BM5: 2 | BN5: 0 | BO5: 0 | BP5: 5 | BQ5: 4 | BR5: 1 | BS5: 1 | BT5: 0 | BU5: 0 | BV5: 2 | BW5: 3 | BX5: 2 | BY5: 1 | BZ5: 0 | CA5: 3 | CB5: 1 | CC5: 2 | CD5: 2 | CE5: 0 | CF5: 0 | CG5: 1 | CH5: 3 | CI5: 1 | CJ5: 1 | CK5: 1 | CL5: 3 | CM5: 0 | CN5: 0 | CO5: 0 | CP5: 0 | CQ5: 0
A6: BNPC01 | B6: Baranya Nikoletta | C6: Polyák Csaba | D6: 1979 | E6: Férfi | F6: főiskolai v. egyetemi diploma | G6: saját tulajdon | H6: 1 | I6: 0 | J6: 54 | K6: udvari | L6: masszőr, szocmunkás | M6: 2014 | N6: 2014 | O6: Budapest | P6: 7 | Q6: Budapest (Pest) | R6: 200000 | S6: 100000 | U6: 100000 | V6: 575000 | W6: Nehezen | X6: Népszínház 13. | Y6: 2 | AA6: kulturált, tenni akaró ember, nagyon szép hippi lakás, zöld | AB6: "nem az számít, milyen üzletre van szükség még, azt a piac kitermeli. az a fontos, hogy ne menjenek el, pl. gyógyszertár elment" | AC6: 75 | AE6: József krt. - Kiss József utca | AF6: 0.34782609 | AG6: TRUE | AH6: 575000 | AI6: diploma | AJ6: 30 és 49 év közötti | AK6: tulajdonos | AL6: 200000 | AM6: fiatal tulajdonos | AN6: 1990 és 2016 között | AO6: High | AP6: 0 | AQ6: 29 | AR6: 4 | AS6: 4 | AT6: 2 | AU6: 3 | AV6: 3 | AW6: 3 | AX6: 2 | AY6: 1 | AZ6: 2 | BA6: 3 | BB6: 5 | BC6: 1 | BD6: 7 | BE6: 17 | BF6: 3 | BG6: 1 | BH6: 0 | BI6: 3 | BJ6: 2 | BK6: 1 | BL6: 3 | BM6: 3 | BN6: 0 | BO6: 0 | BP6: 4 | BQ6: 7 | BR6: 2 | BS6: 0 | BT6: 1 | BU6: 0 | BV6: 1 | BW6: 0 | BX6: 2 | BY6: 0 | BZ6: 1 | CA6: 5 | CB6: 9 | CC6: 0 | CD6: 2 | CE6: 3 | CF6: 5 | CG6: 0 | CH6: 0 | CI6: 0 | CJ6: 0 | CK6: 0 | CL6: 2 | CM6: 3 | CN6: 0 | CO6: 0 | CP6: 0 | CQ6: 0
A7: DBLJ01 | B7: Lökkös Júlia | C7: Dancs Balázs | D7: 1949 | E7: Nő | F7: főiskolai v. egyetemi diploma | G7: saját tulajdon | H7: 1 | I7: 0 | J7: 75 | K7: utcai | L7: tolmács, fordító egyéni vállalkozóként | M7: 2012 | N7: 2012 | O7: Budapest | P7: 7 | Q7: Budapest (Pest) | R7: 50000 | S7: 28000 | V7: 127000 | W7: Nehezen | X7: Népszínház 31. | Y7: 5 | AA7: tágas, rendezett, jó körülmények | AB7: idős értelmiségi, zsidó, valószínűleg gyakorló, van egy lánya, elvált és özvegy | AC7: 33 | AE7: Kiss József utca - Nagy Fuvaros utca | AF7: 0.39370079 | AG7: TRUE | AH7: 127000 | AI7: diploma | AJ7: 65 év feletti | AK7: tulajdonos | AL7: 50000 | AM7: idős | AN7: 1990 és 2016 között | AO7: Low | AP7: 1 | AQ7: 0 | AR7: 6 | AS7: 2 | AT7: 1 | AU7: 0 | AV7: 0 | AW7: 0 | AX7: 0 | AY7: 0 | AZ7: 1 | BA7: 0 | BB7: 1 | BC7: 0 | BD7: 0 | BE7: 1 | BF7: 0 | BG7: 1 | BH7: 0 | BI7: 1 | BJ7: 1 | BK7: 1 | BL7: 0 | BM7: 0 | BN7: 0 | BO7: 1 | BP7: 0 | BQ7: 4 | BR7: 0 | BS7: 1 | BT7: 0 | BU7: 0 | BV7: 0 | BW7: 1 | BX7: 1 | BY7: 1 | BZ7: 0 | CA7: 1 | CB7: 1 | CC7: 1 | CD7: 0 | CE7: 0 | CF7: 0 | CG7: 1 | CH7: 2 | CI7: 0 | CJ7: 0 | CK7: 0 | CL7: 0 | CM7: 1 | CN7: 0 | CO7: 0 | CP7: 0 | CQ7: 0
A8: DBLJ02 | B8: Lökkös Júlia | C8: Dancs Balázs | D8: 1958 | E8: Férfi | F8: főiskolai v. egyetemi diploma | G8: saját tulajdon | H8: 2 | I8: 0 | J8: 100 | K8: utcai | L8: földmérő, nyugdíjas | M8: 1990 | N8: 1990 | O8: Budapest | P8: 3 | Q8: Budapest (Buda) | R8: 100000 | V8: 400000 | W8: Viszonylag könnyen | X8: Népszínház 31. | Y8: 3 | AA8: tágas, nagypolgári lakás, rendezett, jó lakáskörülmények | AC8: 40 | AE8: Kiss József utca - Nagy Fuvaros utca | AF8: 0.25 | AG8: FALSE | AH8: 200000 | AI8: diploma | AJ8: 65 év feletti | AK8: tulajdonos | AL8: 50000 | AM8: idős | AN8: 1990 előtt | AO8: Low | AP8: 0 | AQ8: 10 | AR8: 9 | AS8: 1 | AT8: 1 | AU8: 0 | AV8: 4 | AW8: 0 | AX8: 0 | AY8: 1 | AZ8: 2 | BA8: 0 | BB8: 2 | BC8: 0 | BD8: 2 | BE8: 1 | BF8: 0 | BG8: 1 | BH8: 0 | BI8: 1 | BJ8: 2 | BK8: 1 | BL8: 1 | BM8: 0 | BN8: 1 | BO8: 1 | BP8: 0 | BQ8: 7 | BR8: 0 | BS8: 0 | BT8: 1 | BU8: 0 | BV8: 2 | BW8: 1 | BX8: 0 | BY8: 1 | BZ8: 3 | CA8: 0 | CB8: 0 | CC8: 2 | CD8: 0 | CE8: 0 | CF8: 0 | CG8: 1 | CH8: 0 | CI8: 0 | CJ8: 1 | CK8: 0 | CL8: 0 | CM8: 0 | CN8: 0 | CO8: 0 | CP8: 0 | CQ8: 0
A9: DBLJ03 | B9: Dancs Balázs | C9: Lökkös Júlia | D9: 1948 | E9: Nő | F9: gimnáziumi érettségi | G9: saját tulajdon | H9: 2 | I9: 0 | J9: 78 | K9: utcai | L9: nyugdíjas, könyvesbolt-vezető | M9: 1948 | N9: 1948 | Q9: Ide született | R9: 75000 | S9: 75000 | V9: 340000 | W9: Viszonylag könnyen | X9: Bauer Sándor utca 19. | Y9: 1 | AA9: jó életkörülmények, régies tárgyak | AB9: a lánya éjszakai műszakban dolgozik egy benzinkúton | AC9: 28 | AE9: Alföldi utca - Teleki tér | AF9: 0.22058824 | AG9: FALSE | AH9: 170000 | AI9: érettségi | AJ9: 65 év feletti | AK9: tulajdonos | AL9: 37500 | AM9: idős | AN9: 1990 előtt | AO9: Low | AP9: 0 | AQ9: 6 | AR9: 5 | AS9: 1 | AT9: 0 | AU9: 0 | AV9: 0 | AW9: 1 | AX9: 2 | AY9: 2 | AZ9: 2 | BA9: 0 | BB9: 1 | BC9: 1 | BD9: 1 | BE9: 0 | BF9: 0 | BG9: 0 | BH9: 0 | BI9: 2 | BJ9: 0 | BK9: 0 | BL9: 0 | BM9: 0 | BN9: 0 | BO9: 0 | BP9: 0 | BQ9: 1 | BR9: 0 | BS9: 1 | BT9: 0 | BU9: 0 | BV9: 0 | BW9: 1 | BX9: 1 | BY9: 0 | BZ9: 2 | CA9: 0 | CB9: 1 | CC9: 1 | CD9: 0 | CE9: 0 | CF9: 0 | CG9: 0 | CH9: 0 | CI9: 1 | CJ9: 1 | CK9: 0 | CL9: 0 | CM9: 0 | CN9: 0 | CO9: 0 | CP9: 0 | CQ9: 0
A10: DBSA01 | B10: Dancs Balázs | C10: Szakály Abigél Noémi | D10: 1986 | E10: Férfi | F10: főiskolai v. egyetemi diploma | G10: saját tulajdon | H10: 4 | I10: 2 | J10: 84 | K10: utcai | L10: építész | M10: 2016 | N10: 2016 | O10: Budapest | P10: 7 | Q10: Budapest (Pest) | R10: 75000 | S10: 75000 | V10: 1600000 | W10: Viszonylag könnyen | X10: Népszínház 31. | Y10: 4 | AA10: nagyon szép fényes, tágas, felújított | AB10: nagyon jó körülmények között élnek, háztartást a feleség vezeti, adatokra nagyon szenzitív, kormányellenes, a kormányváltástól sokat vár | AC10: 37 | AE10: Kiss József utca - Nagy Fuvaros utca | AF10: 0.046875 | AG10: FALSE | AH10: 400000 | AI10: diploma | AJ10: 30 és 49 év közötti | AK10: tulajdonos | AL10: 18750 | AM10: fiatal tulajdonos | AN10: 1990 és 2016 között | AO10: High | AP10: 0 | AQ10: 2 | AR10: 8 | AS10: 0 | AT10: 0 | AU10: 1 | AV10: 0 | AW10: 1 | AX10: 0 | AY10: 1 | AZ10: 2 | BA10: 5 | BB10: 1 | BC10: 0 | BD10: 2 | BE10: 0 | BF10: 1 | BG10: 1 | BH10: 0 | BI10: 1 | BJ10: 2 | BK10: 2 | BL10: 0 | BM10: 0 | BN10: 0 | BO10: 0 | BP10: 2 | BQ10: 3 | BR10: 1 | BS10: 1 | BT10: 0 | BU10: 0 | BV10: 0 | BW10: 2 | BX10: 0 | BY10: 0 | BZ10: 0 | CA10: 7 | CB10: 0 | CC10: 0 | CD10: 1 | CE10: 0 | CF10: 4 | CG10: 0 | CH10: 0 | CI10: 0 | CJ10: 0 | CK10: 2 | CL10: 4 | CM10: 0 | CN10: 1 | CO10: 3 | CP10: 0 | CQ10: 0
A11: DEDB01 | B11: Dányi Emese | C11: Dancs Balázs | D11: 1947 | E11: Férfi | F11: szakmunkásképző | G11: szívességi használat | H11: 1 | I11: 0 | J11: 54 | K11: utcai | L11: villanyszerelő a vidámparkban | M11: 2014 | N11: 2014 | O11: Budapest | P11: 11 | Q11: Budapest (Buda) | R11: 80000 | S11: 80000 | W11: Viszonylag könnyen | X11: Népszínház 13. | Y11: 1 | AA11: régi berendezések, zsúfolt de rendezett, nem túl tiszta | AC11: 34 | AE11: József krt. - Kiss József utca | AI11: érettségi alatt | AJ11: 65 év feletti | AK11: nem tulajdonos | AL11: 80000 | AM11: idős | AN11: 1990 és 2016 között | AP11: 1 | AQ11: 7 | AR11: 3 | AS11: 1 | AT11: 1 | AU11: 0 | AV11: 0 | AW11: 1 | AX11: 1 | AY11: 2 | AZ11: 1 | BA11: 0 | BB11: 0 | BC11: 2 | BD11: 0 | BE11: 0 | BF11: 0 | BG11: 0 | BH11: 0 | BI11: 0 | BJ11: 0 | BK11: 1 | BL11: 1 | BM11: 0 | BN11: 0 | BO11: 0 | BP11: 0 | BQ11: 1 | BR11: 2 | BS11: 0 | BT11: 1 | BU11: 0 | BV11: 0 | BW11: 1 | BX11: 1 | BY11: 0 | BZ11: 0 | CA11: 1 | CB11: 1 | CC11: 0 | CD11: 0 | CE11: 0 | CF11: 2 | CG11: 0 | CH11: 0 | CI11: 0 | CJ11: 0 | CK11: 0 | CL11: 0 | CM11: 0 | CN11: 0 | CO11: 0 | CP11: 0 | CQ11: 0
A12: DEDB02 | B12: Dányi Emese | C12: Dancs Balázs | D12: 1974 | E12: Nő | F12: befejezett 8 osztály | G12: piaci bérlet | H12: 2 | I12: 0 | J12: 90 | K12: utcai | L12: takarító | M12: 2000 | N12: 2025 | O12: Budapest | P12: 8 | Q12: Nyolcadik kerület | R12: 330000 | S12: 120000 | T12: 210000 | V12: 560000 | W12: Nehezen | X12: Népszínház 13. | Y12: 3 | AA12: régies, muslicák voltak, zene és tv ment, unokák vendégségben voltak, a férje rokkant. a győgyszereket drágának tartja, gondban van velük | AC12: 33 | AD12: stílusos berendezés | AE12: József krt. - Kiss József utca | AF12: 0.58928571 | AG12: TRUE | AH12: 280000 | AI12: érettségi alatt | AJ12: 50 és 64 év közötti | AK12: nem tulajdonos | AL12: 165000 | AM12: fiatal bérlő | AN12: utóbbi két évben | AO12: Middle | AP12: 2 | AQ12: 2 | AR12: 4 | AS12: 0 | AT12: 0 | AU12: 0 | AV12: 0 | AW12: 0 | AX12: 0 | AY12: 0 | AZ12: 2 | BA12: 0 | BB12: 0 | BC12: 0 | BD12: 0 | BE12: 1 | BF12: 0 | BG12: 1 | BH12: 0 | BI12: 0 | BJ12: 0 | BK12: 0 | BL12: 0 | BM12: 1 | BN12: 1 | BO12: 1 | BP12: 0 | BQ12: 1 | BR12: 1 | BS12: 0 | BT12: 1 | BU12: 0 | BV12: 1 | BW12: 1 | BX12: 0 | BY12: 0 | BZ12: 0 | CA12: 0 | CB12: 0 | CC12: 0 | CD12: 0 | CE12: 1 | CF12: 2 | CG12: 1 | CH12: 0 | CI12: 0 | CJ12: 1 | CK12: 0 | CL12: 1 | CM12: 0 | CN12: 0 | CO12: 0 | CP12: 0 | CQ12: 0
A13: DEKR01 | B13: Kisházi Réka | C13: Dányi Emese | D13: 2005 | E13: Férfi | F13: szakközépiskolai érettségi | G13: piaci bérlet | H13: 1 | I13: 0 | J13: 18 | K13: udvari | L13: vendéglátó | M13: 2023 | N13: 2025 | O13: Budapest | P13: 4 | Q13: Budapest (Pest) | R13: 152000 | S13: 18000 | T13: 134000 | V13: 600000 | W13: Könnyen | X13: Népszínház 32. | Y13: 0 | AA13: kicsi, de rendezett, nem rég költözött | AB13: bicskei gyermekotthonos, a barátnője is, aki még ott lakik | AC13: 37 | AD13: most költözött, a wc ajtót nem lehet becsukni, kb. nincs is ajtó | AE13: Nagy Fuvaros utca - Alföldi utca | AF13: 0.25333333 | AG13: FALSE | AH13: 600000 | AI13: érettségi | AJ13: 18 és 29 év közötti | AK13: nem tulajdonos | AL13: 152000 | AM13: fiatal bérlő | AN13: utóbbi két évben | AO13: High | AP13: 0 | AQ13: 6 | AR13: 7 | AS13: 5 | AT13: 0 | AU13: 1 | AV13: 1 | AW13: 0 | AX13: 0 | AY13: 0 | AZ13: 1 | BA13: 2 | BB13: 2 | BC13: 0 | BD13: 4 | BE13: 0 | BF13: 0 | BG13: 1 | BH13: 0 | BI13: 0 | BJ13: 0 | BK13: 2 | BL13: 0 | BM13: 0 | BN13: 3 | BO13: 0 | BP13: 0 | BQ13: 0 | BR13: 0 | BS13: 1 | BT13: 0 | BU13: 0 | BV13: 0 | BW13: 0 | BX13: 0 | BY13: 0 | BZ13: 0 | CA13: 0 | CB13: 2 | CC13: 1 | CD13: 0 | CE13: 0 | CF13: 0 | CG13: 0 | CH13: 0 | CI13: 0 | CJ13: 1 | CK13: 0 | CL13: 0 | CM13: 0 | CN13: 0 | CO13: 1 | CP13: 0 | CQ13: 0
A14: DEKR02 | B14: Dányi Emese | C14: Kisházi Réka | D14: 1997 | E14: Férfi | F14: főiskolai v. egyetemi diploma | G14: piaci bérlet | H14: 2 | I14: 0 | J14: 62 | K14: udvari | L14: szoftverfejlesztő | M14: 2016 | N14: 2019 | O14: Budapest | P14: 8 | Q14: Nyolcadik kerület | R14: 200000 | S14: 40000 | T14: 160000 | V14: 650000 | W14: Könnyen | X14: Népszínház 16. | Y14: 2 | AA14: a ház rossz állapotú, omladozik, de a lakás szép. meleg volt, volt cica meg robotporszívó. nagy tv, sok dolog, rendetlenség, nem főznek. | AC14: 44 | AE14: József krt. - Kiss József utca | AF14: 0.30769231 | AG14: TRUE | AH14: 325000 | AI14: diploma | AJ14: 18 és 29 év közötti | AK14: nem tulajdonos | AL14: 100000 | AM14: fiatal bérlő | AN14: 2016 és 2023 között | AO14: Middle | AP14: 1 | AQ14: 10 | AR14: 3 | AS14: 2 | AT14: 2 | AU14: 2 | AV14: 0 | AW14: 1 | AX14: 3 | AY14: 1 | AZ14: 1 | BA14: 0 | BB14: 5 | BC14: 0 | BD14: 3 | BE14: 0 | BF14: 1 | BG14: 0 | BH14: 0 | BI14: 0 | BJ14: 2 | BK14: 1 | BL14: 0 | BM14: 1 | BN14: 0 | BO14: 2 | BP14: 2 | BQ14: 5 | BR14: 3 | BS14: 1 | BT14: 0 | BU14: 0 | BV14: 0 | BW14: 0 | BX14: 0 | BY14: 1 | BZ14: 1 | CA14: 2 | CB14: 0 | CC14: 0 | CD14: 0 | CE14: 0 | CF14: 0 | CG14: 0 | CH14: 0 | CI14: 0 | CJ14: 0 | CK14: 0 | CL14: 0 | CM14: 0 | CN14: 0 | CO14: 2 | CP14: 0 | CQ14: 0
A15: HCSL01 | B15: Hajdu Csilla | C15: Szöllősi Luca | D15: 2000 | E15: Férfi | F15: gimnáziumi érettségi | G15: saját tulajdon | H15: 1 | I15: 0 | J15: 35 | K15: udvari | L15: gyorséttermi dolgozó | M15: 2020 | N15: 2020 | O15: Budapest | P15: 2 | Q15: Budapest (Buda) | R15: 30000 | S15: 30000 | V15: 310000 | W15: Viszonylag könnyen | X15: Népszínház 19. | Y15: 0 | AA15: kupi volt nála, úgyhogy a belső udvaron interjúztunk | AC15: 30 | AD15: régebben voltak falikutak a falon, amibe virágokat ültettek (mostanra leszedték a falikutakat) | AE15: József krt. - Kiss József utca | AF15: 0.096774194 | AG15: FALSE | AH15: 310000 | AI15: érettségi | AJ15: 18 és 29 év közötti | AK15: tulajdonos | AL15: 30000 | AM15: fiatal tulajdonos | AN15: 2016 és 2023 között | AO15: Middle | AP15: 1 | AQ15: 4 | AR15: 6 | AS15: 3 | AT15: 1 | AU15: 0 | AV15: 1 | AW15: 1 | AX15: 0 | AY15: 1 | AZ15: 1 | BA15: 0 | BB15: 1 | BC15: 0 | BD15: 1 | BE15: 0 | BF15: 0 | BG15: 0 | BH15: 0 | BI15: 1 | BJ15: 0 | BK15: 1 | BL15: 0 | BM15: 0 | BN15: 0 | BO15: 0 | BP15: 0 | BQ15: 1 | BR15: 0 | BS15: 0 | BT15: 1 | BU15: 0 | BV15: 1 | BW15: 1 | BX15: 0 | BY15: 0 | BZ15: 0 | CA15: 0 | CB15: 0 | CC15: 0 | CD15: 0 | CE15: 1 | CF15: 0 | CG15: 0 | CH15: 3 | CI15: 1 | CJ15: 0 | CK15: 0 | CL15: 1 | CM15: 0 | CN15: 0 | CO15: 1 | CP15: 0 | CQ15: 0
A16: JRDE01 | B16: Jankó Rebeka | C16: Dányi Emese | D16: 1990 | E16: Nő | F16: főiskolai v. egyetemi diploma | G16: saját tulajdon | H16: 2 | I16: 0 | J16: 61 | K16: udvari | L16: szülésznő | M16: 2014 | N16: 2014 | O16: Pilisszentiván | Q16: Pest megye | R16: 60000 | S16: 60000 | W16: Könnyen | X16: Népszínház 16. | Y16: 2 | AA16: Otthonos, van cica, nem zsúfolt, konyha régi, de le akarja cserélni. Amikor ide költözött mindent fel kellett újítani. Saját lakása előtt is rendbetartja a környezetetét. | AC16: 53 | AE16: József krt. - Kiss József utca | AI16: diploma | AJ16: 30 és 49 év közötti | AK16: tulajdonos | AL16: 30000 | AM16: fiatal tulajdonos | AN16: 1990 és 2016 között | AP16: 0 | AQ16: 8 | AR16: 26 | AS16: 2 | AT16: 2 | AU16: 0 | AV16: 4 | AW16: 2 | AX16: 1 | AY16: 2 | AZ16: 2 | BA16: 1 | BB16: 2 | BC16: 1 | BD16: 3 | BE16: 0 | BF16: 0 | BG16: 0 | BH16: 0 | BI16: 8 | BJ16: 0 | BK16: 4 | BL16: 0 | BM16: 2 | BN16: 3 | BO16: 1 | BP16: 1 | BQ16: 1 | BR16: 0 | BS16: 0 | BT16: 0 | BU16: 0 | BV16: 4 | BW16: 5 | BX16: 4 | BY16: 2 | BZ16: 2 | CA16: 1 | CB16: 3 | CC16: 3 | CD16: 0 | CE16: 0 | CF16: 0 | CG16: 2 | CH16: 5 | CI16: 0 | CJ16: 0 | CK16: 1 | CL16: 0 | CM16: 0 | CN16: 0 | CO16: 0 | CP16: 0 | CQ16: 0
A17: JRDE02 | B17: Jankó Rebeka | C17: Dányi Emese | D17: 1947 | E17: Nő | F17: szakközépiskolai érettségi | G17: szívességi használat | H17: 1 | I17: 0 | J17: 96 | K17: utcai | L17: gyengeárammal kapcsolatos technikus | M17: 1986 | N17: 1989 | O17: Nagykovácsi | Q17: Pest megye | R17: 80000 | S17: 80000 | V17: 210000 | W17: Viszonylag könnyen | X17: Népszínház 19. | Y17: 4 | AC17: 74 | AE17: József krt. - Kiss József utca | AF17: 0.38095238 | AG17: TRUE | AH17: 210000 | AI17: érettségi | AJ17: 65 év feletti | AK17: nem tulajdonos | AL17: 80000 | AM17: idős | AN17: 1990 előtt | AO17: Middle | AP17: 0 | AQ17: 18 | AR17: 6 | AS17: 4 | AT17: 2 | AU17: 0 | AV17: 0 | AW17: 0 | AX17: 1 | AY17: 0 | AZ17: 2 | BA17: 2 | BB17: 3 | BC17: 2 | BD17: 6 | BE17: 1 | BF17: 2 | BG17: 0 | BH17: 0 | BI17: 1 | BJ17: 0 | BK17: 0 | BL17: 0 | BM17: 0 | BN17: 0 | BO17: 0 | BP17: 3 | BQ17: 2 | BR17: 0 | BS17: 1 | BT17: 0 | BU17: 0 | BV17: 0 | BW17: 1 | BX17: 2 | BY17: 1 | BZ17: 0 | CA17: 1 | CB17: 2 | CC17: 0 | CD17: 0 | CE17: 2 | CF17: 1 | CG17: 0 | CH17: 0 | CI17: 0 | CJ17: 2 | CK17: 0 | CL17: 0 | CM17: 0 | CN17: 0 | CO17: 0 | CP17: 0 | CQ17: 0
A18: JRGC01 | B18: Gregor Csaba | C18: Jankó Rebeka | D18: 2004 | E18: Nő | F18: gimnáziumi érettségi | G18: piaci bérlet | H18: 1 | I18: 0 | K18: udvari | L18: egyetemista | M18: 2024 | N18: 2024 | O18: Kisbér | Q18: Dunántúl | R18: 258000 | S18: 30000 | T18: 228000 | V18: 300000 | W18: Viszonylag nehezen | X18: Népszínház 16. | Y18: 2 | AC18: 38 | AD18: társbérlet | AE18: József krt. - Kiss József utca | AF18: 0.86 | AG18: TRUE | AH18: 300000 | AI18: érettségi | AJ18: 18 és 29 év közötti | AK18: nem tulajdonos | AL18: 258000 | AM18: fiatal bérlő | AN18: utóbbi két évben | AO18: Middle | AP18: 1 | AQ18: 3 | AR18: 7 | AS18: 1 | AT18: 0 | AU18: 0 | AV18: 1 | AW18: 0 | AX18: 0 | AY18: 0 | AZ18: 1 | BA18: 0 | BB18: 1 | BC18: 1 | BD18: 1 | BE18: 1 | BF18: 0 | BG18: 0 | BH18: 0 | BI18: 2 | BJ18: 0 | BK18: 1 | BL18: 0 | BM18: 1 | BN18: 0 | BO18: 0 | BP18: 0 | BQ18: 1 | BR18: 0 | BS18: 1 | BT18: 0 | BU18: 1 | BV18: 3 | BW18: 1 | BX18: 1 | BY18: 1 | BZ18: 1 | CA18: 0 | CB18: 1 | CC18: 0 | CD18: 0 | CE18: 0 | CF18: 0 | CG18: 0 | CH18: 0 | CI18: 1 | CJ18: 0 | CK18: 0 | CL18: 0 | CM18: 0 | CN18: 0 | CO18: 0 | CP18: 0 | CQ18: 0
A19: KROD01 | B19: Kisházi Réka | C19: Osvay Dorottya | D19: 2001 | E19: Férfi | F19: főiskolai v. egyetemi diploma | G19: piaci bérlet | H19: 1 | I19: 0 | J19: 80 | K19: udvari | L19: gépészmérnök | M19: 2025 | N19: 2025 | O19: Budapest, Norvégia | P19: 9 | Q19: Budapest (Pest) | R19: 110000 | W19: Nem tudja | X19: Népszínház 36. | Y19: 3 | AA19: 6-an laknak együtt, mind külföldiek | AB19: palesztin férfi, jól tud magyarul | AC19: 36 | AD19: társbérlet | AE19: Nagy Fuvaros utca - Alföldi utca | AI19: diploma | AJ19: 18 és 29 év közötti | AK19: nem tulajdonos | AL19: 110000 | AM19: fiatal bérlő | AN19: utóbbi két évben | AP19: 0 | AQ19: 4 | AR19: 1 | AS19: 0 | AT19: 0 | AU19: 0 | AV19: 0 | AW19: 0 | AX19: 0 | AY19: 0 | AZ19: 1 | BA19: 0 | BB19: 2 | BC19: 1 | BD19: 2 | BE19: 0 | BF19: 0 | BG19: 1 | BH19: 0 | BI19: 0 | BJ19: 0 | BK19: 1 | BL19: 0 | BM19: 0 | BN19: 0 | BO19: 0 | BP19: 0 | BQ19: 0 | BR19: 0 | BS19: 0 | BT19: 0 | BU19: 0 | BV19: 1 | BW19: 1 | BX19: 1 | BY19: 0 | BZ19: 0 | CA19: 0 | CB19: 0 | CC19: 0 | CD19: 0 | CE19: 0 | CF19: 0 | CG19: 0 | CH19: 0 | CI19: 0 | CJ19: 0 | CK19: 0 | CL19: 0 | CM19: 0 | CN19: 0 | CO19: 0 | CP19: 0 | CQ19: 0
A20: KROD02 | B20: Kisházi Réka | C20: Osvay Dorottya | D20: 1995 | E20: Férfi | F20: főiskolai v. egyetemi diploma | G20: saját tulajdon | H20: 1 | I20: 0 | J20: 60 | K20: utcai | L20: közgazdász | M20: 2025 | N20: 2025 | O20: Budapest | P20: 9 | Q20: Budapest (Pest) | V20: 300000 | W20: Viszonylag könnyen | X20: Népszínház 22. | Y20: 1 | AA20: A lakás felújítás alatt áll még, de jól szituáltnak tűnik | AC20: 31 | AE20: József krt. - Kiss József utca | AH20: 300000 | AI20: diploma | AJ20: 18 és 29 év közötti | AK20: tulajdonos | AM20: fiatal tulajdonos | AN20: utóbbi két évben | AO20: Middle | AP20: 0 | AQ20: 8 | AR20: 3 | AS20: 2 | AT20: 2 | AU20: 0 | AV20: 6 | AW20: 1 | AX20: 0 | AY20: 0 | AZ20: 1 | BA20: 0 | BB20: 7 | BC20: 0 | BD20: 5 | BE20: 0 | BF20: 2 | BG20: 1 | BH20: 0 | BI20: 0 | BJ20: 0 | BK20: 2 | BL20: 1 | BM20: 1 | BN20: 0 | BO20: 0 | BP20: 2 | BQ20: 0 | BR20: 0 | BS20: 0 | BT20: 0 | BU20: 0 | BV20: 0 | BW20: 1 | BX20: 0 | BY20: 0 | BZ20: 0 | CA20: 1 | CB20: 1 | CC20: 0 | CD20: 4 | CE20: 0 | CF20: 0 | CG20: 1 | CH20: 0 | CI20: 0 | CJ20: 0 | CK20: 0 | CL20: 0 | CM20: 0 | CN20: 0 | CO20: 0 | CP20: 0 | CQ20: 0
A21: KROD03 | B21: Kisházi Réka | C21: Osvay Dorottya | D21: 1979 | E21: Férfi | F21: főiskolai v. egyetemi diploma | G21: saját tulajdon | H21: 4 | I21: 2 | J21: 62 | K21: udvari | L21: térképész | M21: 2000 | N21: 2000 | O21: Barcs | Q21: Dunántúl | R21: 50000 | S21: 50000 | V21: 900000 | W21: Könnyen | X21: Népszínház 36. | Y21: 3 | AA21: jól szituált, felesége festőművész és a füvészkertben dolgozik, diplomás házaspár gyerekekkel, feleség festményeivel van kidekrálva mind a gang mind a lakás | AC21: 51 | AE21: Nagy Fuvaros utca - Alföldi utca | AF21: 0.055555556 | AG21: FALSE | AH21: 225000 | AI21: diploma | AJ21: 30 és 49 év közötti | AK21: tulajdonos | AL21: 12500 | AM21: fiatal tulajdonos | AN21: 1990 és 2016 között | AO21: Middle | AP21: 1 | AQ21: 4 | AR21: 8 | AS21: 2 | AT21: 0 | AU21: 0 | AV21: 0 | AW21: 0 | AX21: 0 | AY21: 1 | AZ21: 2 | BA21: 5 | BB21: 0 | BC21: 1 | BD21: 5 | BE21: 1 | BF21: 1 | BG21: 2 | BH21: 0 | BI21: 2 | BJ21: 0 | BK21: 0 | BL21: 0 | BM21: 0 | BN21: 0 | BO21: 2 | BP21: 1 | BQ21: 4 | BR21: 0 | BS21: 2 | BT21: 0 | BU21: 0 | BV21: 0 | BW21: 1 | BX21: 1 | BY21: 2 | BZ21: 1 | CA21: 0 | CB21: 0 | CC21: 0 | CD21: 0 | CE21: 0 | CF21: 0 | CG21: 1 | CH21: 5 | CI21: 1 | CJ21: 1 | CK21: 1 | CL21: 3 | CM21: 0 | CN21: 0 | CO21: 0 | CP21: 2 | CQ21: 0
A22: KROD04 | B22: Kisházi Réka | C22: Osvay Dorottya | D22: 1957 | E22: Nő | F22: főiskolai v. egyetemi diploma | G22: saját tulajdon | H22: 1 | I22: 0 | J22: 64 | K22: utcai | L22: Nyugdíjfolyósító Igazgatóságnál | M22: 1975 | N22: 1975 | O22: Budapest | P22: 8 | Q22: Nyolcadik kerület | R22: 58000 | S22: 58000 | V22: 300000 | W22: Nehezen | X22: Alföldi utca 2. | Y22: 3 | AA22: állítása szerint küzködik anyagilag. a lakása jól szituált | AC22: 41 | AE22: Nagy Fuvaros utca - Alföldi utca | AF22: 0.19333333 | AG22: FALSE | AH22: 300000 | AI22: diploma | AJ22: 65 év feletti | AK22: tulajdonos | AL22: 58000 | AM22: idős | AN22: 1990 előtt | AO22: Middle | AP22: 1 | AQ22: 1 | AR22: 7 | AS22: 1 | AT22: 0 | AU22: 0 | AV22: 1 | AW22: 0 | AX22: 0 | AY22: 0 | AZ22: 1 | BA22: 0 | BB22: 2 | BC22: 0 | BD22: 2 | BE22: 1 | BF22: 0 | BG22: 0 | BH22: 0 | BI22: 0 | BJ22: 0 | BK22: 1 | BL22: 0 | BM22: 0 | BN22: 0 | BO22: 0 | BP22: 0 | BQ22: 1 | BR22: 0 | BS22: 0 | BT22: 0 | BU22: 0 | BV22: 0 | BW22: 0 | BX22: 1 | BY22: 1 | BZ22: 0 | CA22: 0 | CB22: 1 | CC22: 0 | CD22: 0 | CE22: 1 | CF22: 0 | CG22: 0 | CH22: 0 | CI22: 0 | CJ22: 1 | CK22: 0 | CL22: 0 | CM22: 0 | CN22: 0 | CO22: 0 | CP22: 0 | CQ22: 0
A23: KROD05 | B23: Kisházi Réka | C23: Osvay Dorottya | D23: 2000 | E23: Férfi | F23: főiskolai v. egyetemi diploma | G23: saját tulajdon | H23: 2 | I23: 0 | J23: 70 | K23: utcai | L23: hűtés-fűtés tech értékesítő | M23: 2018 | N23: 2018 | O23: Szarvas | Q23: Észak és Alföld | R23: 45000 | S23: 45000 | V23: 600000 | W23: Könnyen | X23: Alföldi utca 2. | Y23: 1 | AA23: rendezett, jól szituált tiszta lakás | AC23: 33 | AE23: Nagy Fuvaros utca - Alföldi utca | AF23: 0.075 | AG23: FALSE | AH23: 300000 | AI23: diploma | AJ23: 18 és 29 év közötti | AK23: tulajdonos | AL23: 22500 | AM23: fiatal tulajdonos | AN23: 2016 és 2023 között | AO23: Middle | AP23: 0 | AQ23: 3 | AR23: 3 | AS23: 1 | AT23: 1 | AU23: 0 | AV23: 0 | AW23: 0 | AX23: 0 | AY23: 0 | AZ23: 2 | BA23: 0 | BB23: 0 | BC23: 1 | BD23: 0 | BE23: 0 | BF23: 0 | BG23: 1 | BH23: 0 | BI23: 2 | BJ23: 0 | BK23: 1 | BL23: 0 | BM23: 0 | BN23: 0 | BO23: 0 | BP23: 1 | BQ23: 0 | BR23: 0 | BS23: 0 | BT23: 1 | BU23: 0 | BV23: 1 | BW23: 0 | BX23: 1 | BY23: 0 | BZ23: 1 | CA23: 0 | CB23: 0 | CC23: 0 | CD23: 0 | CE23: 0 | CF23: 1 | CG23: 0 | CH23: 1 | CI23: 0 | CJ23: 0 | CK23: 0 | CL23: 0 | CM23: 0 | CN23: 0 | CO23: 0 | CP23: 0 | CQ23: 0
A24: KROD06 | B24: Kisházi Réka | C24: Osvay Dorottya | D24: 1988 | E24: Nő | F24: szakközépiskolai érettségi | G24: szívességi használat | H24: 3 | I24: 2 | J24: 24 | K24: udvari | L24: kereskedelmi menedzser, most gyereket nevel | M24: 2025 | N24: 2025 | O24: Budapest | P24: 7 | Q24: Budapest (Pest) | R24: 200000 | S24: 55000 | T24: 145000 | V24: 500000 | W24: Könnyen | X24: Népszínház 57. | Y24: 2 | AA24: zsúfolt, rendezett lakás | AB24: A házban vannak kinti wc-k, amit mások használnak is. | AC24: 33 | AD24: a népszínház utcában nőtt fel, 7 hónapot élt Egyiptomban, 4 évet a 7 kerben, de azon kívül egész életében népszi és diószegi | AE24: Alföldi utca - Teleki tér | AF24: 0.4 | AG24: TRUE | AH24: 166666.67 | AI24: érettségi | AJ24: 30 és 49 év közötti | AK24: nem tulajdonos | AL24: 66666.667 | AM24: fiatal bérlő | AN24: utóbbi két évben | AO24: Low | AP24: 1 | AQ24: 9 | AR24: 5 | AS24: 2 | AT24: 0 | AU24: 1 | AV24: 2 | AW24: 0 | AX24: 1 | AY24: 1 | AZ24: 1 | BA24: 0 | BB24: 1 | BC24: 0 | BD24: 1 | BE24: 0 | BF24: 0 | BG24: 0 | BH24: 0 | BI24: 0 | BJ24: 0 | BK24: 2 | BL24: 0 | BM24: 0 | BN24: 0 | BO24: 1 | BP24: 0 | BQ24: 0 | BR24: 0 | BS24: 1 | BT24: 0 | BU24: 0 | BV24: 1 | BW24: 1 | BX24: 0 | BY24: 0 | BZ24: 2 | CA24: 0 | CB24: 4 | CC24: 0 | CD24: 1 | CE24: 0 | CF24: 0 | CG24: 0 | CH24: 3 | CI24: 2 | CJ24: 1 | CK24: 0 | CL24: 0 | CM24: 0 | CN24: 0 | CO24: 0 | CP24: 0 | CQ24: 0
A25: KRTB01 | B25: Kisházi Réka | C25: Tömösvári Barnabás | D25: 1998 | E25: Férfi | F25: főiskolai v. egyetemi diploma | G25: piaci bérlet | H25: 2 | I25: 0 | J25: 46 | K25: udvari | L25: diák, weblaptervező | M25: 2019 | N25: 2025 | O25: Budapest | P25: 11 | Q25: Budapest (Buda) | R25: 190000 | S25: 19000 | T25: 170000 | V25: 450000 | W25: Nagyon könnyen | X25: Népszínház 42-44. | Y25: 0 | AA25: értelmiségi, diáklakás, pride zászló, rendezett, tiszta | AC25: 48 | AE25: Alföldi utca - Teleki tér | AF25: 0.42222222 | AG25: TRUE | AH25: 225000 | AI25: diploma | AJ25: 18 és 29 év közötti | AK25: nem tulajdonos | AL25: 95000 | AM25: fiatal bérlő | AN25: utóbbi két évben | AO25: Middle | AP25: 1 | AQ25: 2 | AR25: 12 | AS25: 2 | AT25: 0 | AU25: 1 | AV25: 2 | AW25: 0 | AX25: 0 | AY25: 0 | AZ25: 3 | BA25: 6 | BB25: 0 | BC25: 0 | BD25: 3 | BE25: 1 | BF25: 0 | BG25: 1 | BH25: 0 | BI25: 1 | BJ25: 0 | BK25: 0 | BL25: 0 | BM25: 2 | BN25: 0 | BO25: 2 | BP25: 0 | BQ25: 0 | BR25: 0 | BS25: 1 | BT25: 2 | BU25: 0 | BV25: 2 | BW25: 2 | BX25: 1 | BY25: 1 | BZ25: 1 | CA25: 1 | CB25: 0 | CC25: 1 | CD25: 0 | CE25: 1 | CF25: 0 | CG25: 0 | CH25: 0 | CI25: 0 | CJ25: 0 | CK25: 0 | CL25: 3 | CM25: 1 | CN25: 0 | CO25: 2 | CP25: 0 | CQ25: 0
A26: KRTB02 | B26: Kisházi Réka | C26: Tömösvári Barnabás | D26: 1981 | E26: Nő | F26: főiskolai v. egyetemi diploma | G26: saját tulajdon | H26: 3 | I26: 1 | J26: 55 | K26: udvari | L26: mentális közérzetjavítás, ékszeres vállalkozás | M26: 2006 | N26: 2025 | O26: Budapest | P26: 11 | Q26: Budapest (Buda) | R26: 173000 | S26: 73000 | U26: 100000 | V26: 200000 | W26: Viszonylag könnyen | X26: Népszínház 14. | Y26: 0 | AA26: most költözött, zsúfolt, de rendezett - sűrűn dekorált. keresztény és keleti-spirituális jelképek, díszek, stb. | AB26: nemrég veszítette el az állását, egy hónapja költözött, válófélben van. úgy tűnik, most a tartalékaiból él, ez egy újonnan kialakult helyzet | AC26: 50 | AE26: József krt. - Kiss József utca | AF26: 0.865 | AG26: TRUE | AH26: 66666.667 | AI26: diploma | AJ26: 30 és 49 év közötti | AK26: tulajdonos | AL26: 57666.667 | AM26: fiatal tulajdonos | AN26: utóbbi két évben | AO26: Low | AP26: 0 | AQ26: 6 | AR26: 7 | AS26: 1 | AT26: 0 | AU26: 0 | AV26: 2 | AW26: 0 | AX26: 0 | AY26: 0 | AZ26: 2 | BA26: 2 | BB26: 2 | BC26: 0 | BD26: 3 | BE26: 0 | BF26: 0 | BG26: 1 | BH26: 1 | BI26: 2 | BJ26: 0 | BK26: 0 | BL26: 0 | BM26: 2 | BN26: 0 | BO26: 0 | BP26: 1 | BQ26: 1 | BR26: 0 | BS26: 1 | BT26: 0 | BU26: 0 | BV26: 0 | BW26: 1 | BX26: 1 | BY26: 0 | BZ26: 0 | CA26: 5 | CB26: 4 | CC26: 1 | CD26: 2 | CE26: 0 | CF26: 3 | CG26: 1 | CH26: 2 | CI26: 0 | CJ26: 0 | CK26: 2 | CL26: 2 | CM26: 0 | CN26: 0 | CO26: 0 | CP26: 0 | CQ26: 0
A27: KRTB03 | B27: Kisházi Réka | C27: Tömösvári Barnabás | D27: 2002 | E27: Férfi | F27: gimnáziumi érettségi | G27: saját tulajdon | H27: 1 | I27: 0 | J27: 32 | K27: udvari | L27: barber | M27: 2018 | N27: 2023 | O27: Budapest | P27: 10 | Q27: Budapest (Pest) | R27: 70000 | S27: 70000 | V27: 600000 | W27: Könnyen | X27: Népszínház 49. | Y27: 2 | AB27: mikor a barátnője apja megtudta, hogy itt lakik, nem akarta, hogy találkozzanak, mert "itt csak romák laknak". úgy érzi, hogy az, hogy itt lakik, sokszor negatív előítéletekkel jár, megbélyegzéssel találkozik | AC27: 64 | AE27: Alföldi utca - Teleki tér | AF27: 0.11666667 | AG27: FALSE | AH27: 600000 | AI27: érettségi | AJ27: 18 és 29 év közötti | AK27: tulajdonos | AL27: 70000 | AM27: fiatal tulajdonos | AN27: 2016 és 2023 között | AO27: High | AP27: 1 | AQ27: 11 | AR27: 9 | AS27: 1 | AT27: 0 | AU27: 0 | AV27: 2 | AW27: 0 | AX27: 0 | AY27: 1 | AZ27: 2 | BA27: 0 | BB27: 5 | BC27: 0 | BD27: 9 | BE27: 0 | BF27: 0 | BG27: 0 | BH27: 0 | BI27: 2 | BJ27: 1 | BK27: 0 | BL27: 0 | BM27: 2 | BN27: 0 | BO27: 0 | BP27: 0 | BQ27: 1 | BR27: 0 | BS27: 1 | BT27: 0 | BU27: 0 | BV27: 1 | BW27: 0 | BX27: 0 | BY27: 1 | BZ27: 0 | CA27: 1 | CB27: 2 | CC27: 2 | CD27: 4 | CE27: 6 | CF27: 3 | CG27: 0 | CH27: 0 | CI27: 0 | CJ27: 0 | CK27: 3 | CL27: 3 | CM27: 0 | CN27: 0 | CO27: 2 | CP27: 0 | CQ27: 0
A28: LJBN01 | B28: Lökkös Júlia | C28: Baranya Nikolett | D28: 1989 | E28: Nő | F28: gimnáziumi érettségi | G28: piaci bérlet | H28: 2 | I28: 0 | J28: 110 | K28: utcai | L28: munkanélküli, egyetemista, korábban dolgozott könyvkötőműhelyben | M28: 2016 | N28: 2016 | O28: Budapest | P28: 6 | Q28: Budapest (Pest) | R28: 213000 | S28: 48000 | T28: 165000 | V28: 580000 | W28: Nagyon könnyen | X28: Népszínház 22. | Y28: 4 | AA28: tágas, világos, szépen berendezett, elég felső-közés életkörülmények, füstölő a wc-ben | AB28: zajos a lakás az utca miatt | AC28: 51 | AE28: József krt. - Kiss József utca | AF28: 0.36724138 | AG28: TRUE | AH28: 290000 | AI28: érettségi | AJ28: 30 és 49 év közötti | AK28: nem tulajdonos | AL28: 106500 | AM28: fiatal bérlő | AN28: 1990 és 2016 között | AO28: Middle | AP28: 1 | AQ28: 7 | AR28: 16 | AS28: 0 | AT28: 3 | AU28: 0 | AV28: 6 | AW28: 2 | AX28: 0 | AY28: 0 | AZ28: 3 | BA28: 1 | BB28: 2 | BC28: 2 | BD28: 1 | BE28: 0 | BF28: 0 | BG28: 1 | BH28: 0 | BI28: 3 | BJ28: 1 | BK28: 2 | BL28: 0 | BM28: 2 | BN28: 0 | BO28: 0 | BP28: 1 | BQ28: 1 | BR28: 0 | BS28: 0 | BT28: 0 | BU28: 0 | BV28: 2 | BW28: 1 | BX28: 3 | BY28: 1 | BZ28: 2 | CA28: 0 | CB28: 2 | CC28: 2 | CD28: 0 | CE28: 0 | CF28: 0 | CG28: 0 | CH28: 3 | CI28: 0 | CJ28: 1 | CK28: 0 | CL28: 3 | CM28: 0 | CN28: 0 | CO28: 1 | CP28: 0 | CQ28: 0
A29: LJSA01 | B29: Lökkös Júlia | C29: Szakály Abigél Noémi | D29: 1958 | E29: Nő | F29: szakközépiskolai érettségi | G29: szívességi használat | H29: 2 | I29: 0 | J29: 40 | K29: utcai | L29: villamosvezető | M29: 2024 | N29: 2024 | O29: Budapest | P29: 6 | Q29: Budapest (Pest) | R29: 65000 | S29: 65000 | V29: 450000 | W29: Könnyen | X29: Népszínház 57. | Y29: 0 | AA29: fényes, dohányszag, de rendezett, szocialista bútorok, két nyugdíjas | AB29: barátnője háza, akit gondoz, ingyen él ott | AC29: 33 | AE29: Alföldi utca - Teleki tér | AF29: 0.14444444 | AG29: FALSE | AH29: 225000 | AI29: érettségi | AJ29: 65 év feletti | AK29: nem tulajdonos | AL29: 32500 | AM29: idős | AN29: utóbbi két évben | AO29: Middle | AP29: 2 | AQ29: 11 | AR29: 6 | AS29: 2 | AT29: 3 | AU29: 0 | AV29: 1 | AW29: 1 | AX29: 2 | AY29: 2 | AZ29: 2 | BA29: 2 | BB29: 2 | BC29: 1 | BD29: 3 | BE29: 3 | BF29: 2 | BG29: 0 | BH29: 0 | BI29: 1 | BJ29: 0 | BK29: 3 | BL29: 1 | BM29: 1 | BN29: 0 | BO29: 0 | BP29: 3 | BQ29: 0 | BR29: 1 | BS29: 0 | BT29: 0 | BU29: 0 | BV29: 0 | BW29: 0 | BX29: 1 | BY29: 0 | BZ29: 0 | CA29: 0 | CB29: 3 | CC29: 0 | CD29: 2 | CE29: 1 | CF29: 0 | CG29: 0 | CH29: 0 | CI29: 0 | CJ29: 0 | CK29: 0 | CL29: 2 | CM29: 1 | CN29: 1 | CO29: 1 | CP29: 1 | CQ29: 1
A30: LJSA02 | B30: Lökkös Júlia | C30: Szakály Abigél Noémi | D30: 1937 | E30: Nő | F30: befejezett 8 osztály | G30: saját tulajdon | H30: 1 | I30: 0 | J30: 34 | K30: udvari | L30: műszaki rajz szerkesztő, rajzoló | M30: 1965 | N30: 1985 | O30: Budapest | P30: 8 | Q30: Nyolcadik kerület | R30: 42000 | S30: 42000 | V30: 250000 | W30: Viszonylag könnyen | X30: Népszínház 26. | Y30: 2 | AA30: szűkös nagymama lakás | AB30: kis üzletek, cipőbolt, posta hiányoznak neki. sok változáson ment át ő is, az utca is, siratta a múltat | AC30: 39 | AE30: Kiss József utca - Nagy Fuvaros utca | AF30: 0.168 | AG30: FALSE | AH30: 250000 | AI30: érettségi alatt | AJ30: 65 év feletti | AK30: tulajdonos | AL30: 42000 | AM30: idős | AN30: 1990 előtt | AO30: Middle | AP30: 2 | AQ30: 15 | AR30: 2 | AS30: 2 | AT30: 2 | AU30: 4 | AV30: 1 | AW30: 0 | AX30: 2 | AY30: 2 | AZ30: 2 | BA30: 0 | BB30: 2 | BC30: 0 | BD30: 6 | BE30: 0 | BF30: 0 | BG30: 0 | BH30: 0 | BI30: 0 | BJ30: 0 | BK30: 0 | BL30: 1 | BM30: 1 | BN30: 0 | BO30: 1 | BP30: 2 | BQ30: 4 | BR30: 1 | BS30: 2 | BT30: 1 | BU30: 0 | BV30: 0 | BW30: 1 | BX30: 0 | BY30: 0 | BZ30: 0 | CA30: 0 | CB30: 4 | CC30: 0 | CD30: 0 | CE30: 0 | CF30: 2 | CG30: 0 | CH30: 1 | CI30: 1 | CJ30: 0 | CK30: 0 | CL30: 0 | CM30: 0 | CN30: 0 | CO30: 1 | CP30: 0 | CQ30: 0
A31: LJSA03 | B31: Lökkös Júlia | C31: Szakály Abigél Noémi | D31: 1979 | E31: Nő | F31: gimnáziumi érettségi | G31: saját tulajdon | H31: 1 | I31: 0 | J31: 64 | K31: utcai | L31: masszőr | M31: 1979 | N31: 1979 | Q31: Ide született | R31: 55000 | S31: 55000 | W31: Könnyen | X31: Népszínház 34. | Y31: 2 | AA31: egyszerű rendezett lakás 2 kutyával | AC31: 25 | AE31: Nagy Fuvaros utca - Alföldi utca | AI31: érettségi | AJ31: 30 és 49 év közötti | AK31: tulajdonos | AL31: 55000 | AM31: fiatal tulajdonos | AN31: 1990 előtt | AP31: 0 | AQ31: 8 | AR31: 10 | AS31: 1 | AT31: 1 | AU31: 0 | AV31: 2 | AW31: 0 | AX31: 1 | AY31: 1 | AZ31: 1 | BA31: 1 | BB31: 1 | BC31: 2 | BD31: 2 | BE31: 0 | BF31: 0 | BG31: 0 | BH31: 0 | BI31: 0 | BJ31: 1 | BK31: 1 | BL31: 0 | BM31: 1 | BN31: 2 | BO31: 1 | BP31: 0 | BQ31: 1 | BR31: 0 | BS31: 2 | BT31: 0 | BU31: 2 | BV31: 1 | BW31: 0 | BX31: 1 | BY31: 1 | BZ31: 1 | CA31: 0 | CB31: 1 | CC31: 0 | CD31: 1 | CE31: 1 | CF31: 0 | CG31: 0 | CH31: 0 | CI31: 1 | CJ31: 0 | CK31: 1 | CL31: 1 | CM31: 0 | CN31: 0 | CO31: 0 | CP31: 0 | CQ31: 1
A32: LJSA04 | B32: Lökkös Júlia | C32: Szakály Abigél Noémi | D32: 2004 | E32: Férfi | F32: gimnáziumi érettségi | G32: piaci bérlet | H32: 2 | I32: 0 | J32: 53 | K32: utcai | L32: egyetemista | M32: 2023 | N32: 2023 | O32: Császár | Q32: Dunántúl | R32: 105000 | S32: 15000 | T32: 90000 | V32: 500000 | W32: Viszonylag könnyen | X32: Népszínház 34. | Y32: 2 | AC32: 28 | AE32: Nagy Fuvaros utca - Alföldi utca | AF32: 0.21 | AG32: FALSE | AH32: 250000 | AI32: érettségi | AJ32: 18 és 29 év közötti | AK32: nem tulajdonos | AL32: 52500 | AM32: fiatal bérlő | AN32: 2016 és 2023 között | AO32: Middle | AP32: 0 | AQ32: 3 | AR32: 13 | AS32: 1 | AT32: 0 | AU32: 1 | AV32: 2 | AW32: 1 | AX32: 1 | AY32: 0 | AZ32: 2 | BA32: 2 | BB32: 2 | BC32: 1 | BD32: 1 | BE32: 0 | BF32: 0 | BG32: 1 | BH32: 0 | BI32: 4 | BJ32: 1 | BK32: 3 | BL32: 0 | BM32: 1 | BN32: 2 | BO32: 1 | BP32: 1 | BQ32: 0 | BR32: 0 | BS32: 3 | BT32: 0 | BU32: 1 | BV32: 4 | BW32: 1 | BX32: 1 | BY32: 1 | BZ32: 0 | CA32: 3 | CB32: 1 | CC32: 0 | CD32: 0 | CE32: 0 | CF32: 0 | CG32: 1 | CH32: 3 | CI32: 0 | CJ32: 0 | CK32: 1 | CL32: 2 | CM32: 0 | CN32: 1 | CO32: 0 | CP32: 0 | CQ32: 0
A33: LJSA05 | B33: Lökkös Júlia | C33: Szakály Abigél Noémi | D33: 1999 | E33: Nő | F33: befejezett 8 osztály | G33: piaci bérlet | H33: 2 | I33: 0 | J33: 35 | K33: udvari | L33: takarító | M33: 2023 | N33: 2023 | O33: Budapest | P33: 6 | Q33: Budapest (Pest) | R33: 300000 | S33: 30000 | T33: 220000 | V33: 400000 | W33: Nehezen | X33: Népszínház 34. | Y33: 3 | AA33: a férje munkanélküli, egyszerű letisztult, kicsi lakás | AC33: 18 | AE33: Nagy Fuvaros utca - Alföldi utca | AF33: 0.75 | AG33: TRUE | AH33: 200000 | AI33: érettségi alatt | AJ33: 18 és 29 év közötti | AK33: nem tulajdonos | AL33: 150000 | AM33: fiatal bérlő | AN33: 2016 és 2023 között | AO33: Low | AP33: 1 | AQ33: 6 | AR33: 5 | AS33: 2 | AT33: 1 | AU33: 0 | AV33: 2 | AW33: 2 | AX33: 1 | AY33: 1 | AZ33: 2 | BA33: 0 | BB33: 1 | BC33: 0 | BD33: 0 | BE33: 1 | BF33: 0 | BG33: 0 | BH33: 0 | BI33: 2 | BJ33: 0 | BK33: 0 | BL33: 0 | BM33: 1 | BN33: 0 | BO33: 0 | BP33: 0 | BQ33: 0 | BR33: 1 | BS33: 0 | BT33: 1 | BU33: 1 | BV33: 2 | BW33: 0 | BX33: 0 | BY33: 0 | BZ33: 0 | CA33: 0 | CB33: 1 | CC33: 0 | CD33: 0 | CE33: 0 | CF33: 0 | CG33: 0 | CH33: 0 | CI33: 0 | CJ33: 1 | CK33: 0 | CL33: 0 | CM33: 0 | CN33: 0 | CO33: 0 | CP33: 0 | CQ33: 0
A34: MZGC01 | B34: Major Zsuzsanna | C34: Gregor Csaba | D34: 1960 | E34: Nő | F34: szakközépiskolai érettségi | G34: önkormányzati bérlet | H34: 3 | I34: 1 | J34: 40 | K34: utcai | L34: nyugdíjas, ápoló | M34: 1999 | N34: 2021 | O34: Budapest | P34: 14 | Q34: Budapest (Pest) | R34: 106000 | S34: 85000 | T34: 21000 | V34: 330000 | W34: Viszonylag könnyen | X34: Népszínház 57. | Y34: 2 | AA34: összeszedett, rendezett lakás, családias | AC34: 25 | AE34: Alföldi utca - Teleki tér | AF34: 0.32121212 | AG34: TRUE | AH34: 110000 | AI34: érettségi | AJ34: 50 és 64 év közötti | AK34: nem tulajdonos | AL34: 35333.333 | AM34: idős | AN34: 2016 és 2023 között | AO34: Low | AP34: 1 | AQ34: 6 | AR34: 9 | AS34: 0 | AT34: 0 | AU34: 0 | AV34: 1 | AW34: 1 | AX34: 0 | AY34: 0 | AZ34: 2 | BA34: 2 | BB34: 2 | BC34: 0 | BD34: 1 | BE34: 0 | BF34: 1 | BG34: 0 | BH34: 0 | BI34: 0 | BJ34: 0 | BK34: 0 | BL34: 2 | BM34: 1 | BN34: 0 | BO34: 4 | BP34: 0 | BQ34: 0 | BR34: 1 | BS34: 0 | BT34: 0 | BU34: 0 | BV34: 1 | BW34: 0 | BX34: 1 | BY34: 0 | BZ34: 0 | CA34: 0 | CB34: 4 | CC34: 1 | CD34: 0 | CE34: 0 | CF34: 0 | CG34: 0 | CH34: 1 | CI34: 0 | CJ34: 2 | CK34: 0 | CL34: 0 | CM34: 0 | CN34: 0 | CO34: 0 | CP34: 0 | CQ34: 0
A35: MZGC02 | B35: Major Zsuzsanna | C35: Gregor Csaba | D35: 2000 | E35: Férfi | F35: főiskolai v. egyetemi diploma | G35: saját tulajdon | H35: 3 | I35: 0 | J35: 51 | K35: udvari | L35: könyvelő | M35: 2022 | N35: 2022 | O35: Budapest | P35: 3 | Q35: Budapest (Buda) | R35: 325000 | S35: 25000 | U35: 300000 | W35: Viszonylag könnyen | X35: Népszínház 16. | Y35: 0 | AC35: 28 | AE35: József krt. - Kiss József utca | AI35: diploma | AJ35: 18 és 29 év közötti | AK35: tulajdonos | AL35: 108333.33 | AM35: fiatal tulajdonos | AN35: 2016 és 2023 között | AP35: 0 | AQ35: 4 | AR35: 10 | AS35: 1 | AT35: 2 | AU35: 0 | AV35: 2 | AW35: 1 | AX35: 0 | AY35: 0 | AZ35: 1 | BA35: 0 | BB35: 1 | BC35: 0 | BD35: 0 | BE35: 0 | BF35: 0 | BG35: 1 | BH35: 0 | BI35: 1 | BJ35: 1 | BK35: 0 | BL35: 0 | BM35: 1 | BN35: 0 | BO35: 3 | BP35: 0 | BQ35: 1 | BR35: 0 | BS35: 1 | BT35: 0 | BU35: 1 | BV35: 3 | BW35: 1 | BX35: 0 | BY35: 0 | BZ35: 0 | CA35: 0 | CB35: 2 | CC35: 0 | CD35: 0 | CE35: 1 | CF35: 0 | CG35: 1 | CH35: 2 | CI35: 0 | CJ35: 0 | CK35: 0 | CL35: 0 | CM35: 0 | CN35: 0 | CO35: 0 | CP35: 0 | CQ35: 0
A36: ODGB01 | B36: Osvay Dorottya | C36: Gecse Barbara | D36: 1991 | E36: Férfi | F36: gimnáziumi érettségi | G36: saját tulajdon | H36: 1 | I36: 0 | J36: 57 | K36: utcai | L36: operatőr | M36: 2023 | N36: 2023 | O36: Budapest | P36: 7 | Q36: Budapest (Pest) | R36: 40000 | S36: 40000 | W36: Viszonylag könnyen | X36: Népszínház 14. | Y36: 3 | AA36: felújított, alter, fife, plakátok, növények mac képernyő | AB36: nagyon érdeklődött a kutatás iránt, barátkozó volt | AC36: 33 | AE36: József krt. - Kiss József utca | AI36: érettségi | AJ36: 30 és 49 év közötti | AK36: tulajdonos | AL36: 40000 | AM36: fiatal tulajdonos | AN36: 2016 és 2023 között | AP36: 0 | AQ36: 3 | AR36: 6 | AS36: 0 | AT36: 1 | AU36: 1 | AV36: 1 | AW36: 0 | AX36: 1 | AY36: 0 | AZ36: 1 | BA36: 2 | BB36: 0 | BC36: 1 | BD36: 1 | BE36: 0 | BF36: 0 | BG36: 1 | BH36: 1 | BI36: 3 | BJ36: 1 | BK36: 1 | BL36: 0 | BM36: 1 | BN36: 0 | BO36: 0 | BP36: 0 | BQ36: 2 | BR36: 1 | BS36: 0 | BT36: 0 | BU36: 1 | BV36: 2 | BW36: 1 | BX36: 1 | BY36: 0 | BZ36: 1 | CA36: 0 | CB36: 0 | CC36: 0 | CD36: 0 | CE36: 1 | CF36: 0 | CG36: 0 | CH36: 2 | CI36: 2 | CJ36: 0 | CK36: 0 | CL36: 0 | CM36: 0 | CN36: 0 | CO36: 0 | CP36: 0 | CQ36: 0
A37: OMDB01 | B37: Óvári Márton | C37: Dancs Balázs | D37: 1992 | E37: Nő | F37: gimnáziumi érettségi | G37: piaci bérlet | H37: 2 | I37: 0 | J37: 68 | K37: utcai | L37: szocmunkás | M37: 2019 | N37: 2021 | O37: Budapest | P37: 8 | Q37: Nyolcadik kerület | R37: 210000 | S37: 40000 | T37: 168000 | V37: 730000 | W37: Viszonylag könnyen | X37: Népszínház 31. | Y37: 1 | AA37: tiszta, rendezett lakás, gyakran használt eszközök újak. | AB37: van egy macskája | AE37: Kiss József utca - Nagy Fuvaros utca | AF37: 0.28767123 | AG37: FALSE | AH37: 365000 | AI37: érettségi | AJ37: 30 és 49 év közötti | AK37: nem tulajdonos | AL37: 105000 | AM37: fiatal bérlő | AN37: 2016 és 2023 között | AO37: High | AP37: 0 | AQ37: 5 | AR37: 18 | AS37: 0 | AT37: 1 | AU37: 0 | AV37: 0 | AW37: 3 | AX37: 1 | AY37: 2 | AZ37: 2 | BA37: 0 | BB37: 2 | BC37: 0 | BD37: 5 | BE37: 0 | BF37: 1 | BG37: 0 | BH37: 0 | BI37: 1 | BJ37: 0 | BK37: 1 | BL37: 0 | BM37: 1 | BN37: 2 | BO37: 1 | BP37: 0 | BQ37: 0 | BR37: 1 | BS37: 0 | BT37: 1 | BU37: 0 | BV37: 1 | BW37: 1 | BX37: 0 | BY37: 0 | BZ37: 1 | CA37: 0 | CB37: 3 | CC37: 2 | CD37: 0 | CE37: 0 | CF37: 0 | CG37: 1 | CH37: 2 | CI37: 0 | CJ37: 1 | CK37: 0 | CL37: 3 | CM37: 0 | CN37: 0 | CO37: 0 | CP37: 0 | CQ37: 0
A38: OMDE01 | B38: Óvári Márton | C38: Dányi Emese | D38: 2005 | E38: Férfi | F38: gimnáziumi érettségi | G38: önkormányzati bérlet | H38: 4 | I38: 2 | J38: 50 | K38: utcai | L38: egyetemista | M38: 2016 | N38: 2024 | O38: Budapest | P38: 8 | Q38: Nyolcadik kerület | R38: 95000 | S38: 50000 | T38: 90000 | V38: 500000 | W38: Viszonylag nehezen | X38: Népszínház 57. | Y38: 3 | AA38: kaotikus (sokan laknak kis helyen: 4 ember, 3 fiatal és 1 keresű korú) | AC38: 24 | AD38: rezsi 50e kb. (VI) | AE38: Alföldi utca - Teleki tér | AF38: 0.19 | AG38: FALSE | AH38: 125000 | AI38: érettségi | AJ38: 18 és 29 év közötti | AK38: nem tulajdonos | AL38: 23750 | AM38: fiatal bérlő | AN38: utóbbi két évben | AO38: Low | AP38: 0 | AQ38: 3 | AR38: 3 | AS38: 0 | AT38: 0 | AU38: 0 | AV38: 0 | AW38: 0 | AX38: 0 | AY38: 0 | AZ38: 1 | BA38: 0 | BB38: 1 | BC38: 1 | BD38: 0 | BE38: 0 | BF38: 0 | BG38: 0 | BH38: 0 | BI38: 0 | BJ38: 0 | BK38: 0 | BL38: 0 | BM38: 1 | BN38: 0 | BO38: 1 | BP38: 0 | BQ38: 0 | BR38: 1 | BS38: 0 | BT38: 0 | BU38: 0 | BV38: 0 | BW38: 1 | BX38: 0 | BY38: 0 | BZ38: 0 | CA38: 0 | CB38: 1 | CC38: 0 | CD38: 0 | CE38: 0 | CF38: 0 | CG38: 1 | CH38: 0 | CI38: 0 | CJ38: 0 | CK38: 0 | CL38: 1 | CM38: 0 | CN38: 0 | CO38: 0 | CP38: 1 | CQ38: 0
A39: OMDE02 | B39: Óvári Márton | C39: Dányi Emese | D39: 1946 | E39: Nő | F39: főiskolai v. egyetemi diploma | G39: saját tulajdon | H39: 1 | I39: 0 | J39: 75 | K39: utcai | L39: tolmács, idegenvezető, külker üzletkötő | M39: 1990 | N39: 1990 | O39: Szófia | Q39: Külföld | R39: 50000 | S39: 13000 | V39: 150000 | W39: Viszonylag nehezen | X39: Népszínház 19. | Y39: 3 | AC39: 85 | AE39: József krt. - Kiss József utca | AF39: 0.33333333 | AG39: TRUE | AH39: 150000 | AI39: diploma | AJ39: 65 év feletti | AK39: tulajdonos | AL39: 50000 | AM39: idős | AN39: 1990 előtt | AO39: Low | AP39: 1 | AQ39: 12 | AR39: 5 | AS39: 2 | AT39: 0 | AU39: 0 | AV39: 1 | AW39: 0 | AX39: 1 | AY39: 3 | AZ39: 1 | BA39: 0 | BB39: 1 | BC39: 2 | BD39: 4 | BE39: 2 | BF39: 0 | BG39: 0 | BH39: 0 | BI39: 1 | BJ39: 1 | BK39: 0 | BL39: 0 | BM39: 0 | BN39: 0 | BO39: 0 | BP39: 1 | BQ39: 0 | BR39: 1 | BS39: 0 | BT39: 0 | BU39: 0 | BV39: 1 | BW39: 0 | BX39: 0 | BY39: 0 | BZ39: 1 | CA39: 0 | CB39: 1 | CC39: 0 | CD39: 0 | CE39: 0 | CF39: 0 | CG39: 0 | CH39: 1 | CI39: 0 | CJ39: 0 | CK39: 0 | CL39: 0 | CM39: 0 | CN39: 0 | CO39: 1 | CP39: 0 | CQ39: 0
A40: OMLJ01 | B40: Óvári Márton | C40: Lökkös Júlia | D40: 1956 | E40: Férfi | F40: szakmunkásképző | G40: saját tulajdon | H40: 2 | I40: 0 | J40: 80 | K40: utcai | L40: kórházi gondnok | M40: 1989 | N40: 1989 | O40: Budapest | P40: 5 | Q40: Pest megye | R40: 70000 | S40: 70000 | W40: Könnyen | X40: Népszínház 11. | Y40: 2 | AA40: jó életkörülmények, nagypolgári lakás | AD40: a felesége a közös képviselő | AE40: József krt. - Kiss József utca | AI40: érettségi alatt | AJ40: 65 év feletti | AK40: tulajdonos | AL40: 35000 | AM40: idős | AN40: 1990 előtt | AP40: 0 | AQ40: 5 | AR40: 5 | AS40: 1 | AT40: 0 | AU40: 0 | AV40: 0 | AW40: 1 | AX40: 1 | AY40: 0 | AZ40: 1 | BA40: 0 | BB40: 1 | BC40: 1 | BD40: 1 | BE40: 0 | BF40: 1 | BG40: 0 | BH40: 0 | BI40: 3 | BJ40: 0 | BK40: 2 | BL40: 0 | BM40: 0 | BN40: 0 | BO40: 0 | BP40: 0 | BQ40: 1 | BR40: 0 | BS40: 1 | BT40: 2 | BU40: 0 | BV40: 2 | BW40: 1 | BX40: 1 | BY40: 0 | BZ40: 1 | CA40: 2 | CB40: 1 | CC40: 0 | CD40: 0 | CE40: 0 | CF40: 0 | CG40: 1 | CH40: 1 | CI40: 0 | CJ40: 2 | CK40: 0 | CL40: 0 | CM40: 0 | CN40: 0 | CO40: 0 | CP40: 0 | CQ40: 0
A41: OMLJ02 | B41: Óvári Márton | C41: Lökkös Júlia | D41: 1990 | E41: Férfi | F41: főiskolai v. egyetemi diploma | G41: saját tulajdon | H41: 2 | I41: 0 | J41: 27 | K41: udvari | L41: Közalkalmazott, egyetemen tanul | M41: 2017 | N41: 2018 | O41: Kecskemét | Q41: Észak és Alföld | R41: 40000 | S41: 25000 | W41: Viszonylag könnyen | X41: Bauer Sándor utca 19. | Y41: 4 | Z41: kovacsmilan90@gmail.com | AA41: nem engedett be a lakásba, az interjú a gangon készült | AE41: Alföldi utca - Teleki tér | AI41: diploma | AJ41: 30 és 49 év közötti | AK41: tulajdonos | AL41: 20000 | AM41: fiatal tulajdonos | AN41: 2016 és 2023 között | AP41: 0 | AQ41: 5 | AR41: 7 | AS41: 0 | AT41: 1 | AU41: 0 | AV41: 1 | AW41: 1 | AX41: 3 | AY41: 1 | AZ41: 1 | BA41: 1 | BB41: 1 | BC41: 0 | BD41: 1 | BE41: 1 | BF41: 0 | BG41: 1 | BH41: 0 | BI41: 2 | BJ41: 0 | BK41: 0 | BL41: 0 | BM41: 1 | BN41: 1 | BO41: 0 | BP41: 0 | BQ41: 1 | BR41: 1 | BS41: 1 | BT41: 0 | BU41: 0 | BV41: 1 | BW41: 0 | BX41: 0 | BY41: 1 | BZ41: 1 | CA41: 0 | CB41: 0 | CC41: 1 | CD41: 0 | CE41: 0 | CF41: 0 | CG41: 1 | CH41: 0 | CI41: 0 | CJ41: 0 | CK41: 0 | CL41: 1 | CM41: 0 | CN41: 0 | CO41: 1 | CP41: 0 | CQ41: 0
A42: OMMZ01 | B42: Óvári Márton | C42: Major Zsuzsi | D42: 1999 | E42: Nő | F42: főiskolai v. egyetemi diploma | G42: piaci bérlet | H42: 1 | I42: 0 | J42: 36 | K42: udvari | L42: vendéglátó | M42: 2025 | N42: 2025 | O42: Budapest | P42: 9 | Q42: Budapest (Pest) | R42: 240000 | S42: 20000 | T42: 220000 | W42: Viszonylag könnyen | X42: Népszínház 49. | Y42: 5 | AC42: 28 | AD42: 17:38- nál azt mondja, hogy nincs utcai ablaka (VI) JAVÍTVA | AE42: Alföldi utca - Teleki tér | AI42: diploma | AJ42: 18 és 29 év közötti | AK42: nem tulajdonos | AL42: 240000 | AM42: fiatal bérlő | AN42: utóbbi két évben | AP42: 1 | AQ42: 0 | AR42: 4 | AS42: 1 | AT42: 0 | AU42: 0 | AV42: 1 | AW42: 0 | AX42: 0 | AY42: 0 | AZ42: 1 | BA42: 2 | BB42: 1 | BC42: 1 | BD42: 0 | BE42: 0 | BF42: 0 | BG42: 1 | BH42: 0 | BI42: 0 | BJ42: 0 | BK42: 0 | BL42: 0 | BM42: 1 | BN42: 0 | BO42: 0 | BP42: 1 | BQ42: 0 | BR42: 0 | BS42: 0 | BT42: 0 | BU42: 0 | BV42: 1 | BW42: 0 | BX42: 0 | BY42: 0 | BZ42: 0 | CA42: 0 | CB42: 0 | CC42: 0 | CD42: 0 | CE42: 0 | CF42: 0 | CG42: 1 | CH42: 2 | CI42: 0 | CJ42: 0 | CK42: 0 | CL42: 0 | CM42: 0 | CN42: 0 | CO42: 0 | CP42: 0 | CQ42: 0
A43: OMMZ02 | B43: Óvári Márton | C43: Major Zsuzsi | D43: 1957 | E43: Nő | F43: gimnáziumi érettségi | G43: saját tulajdon | H43: 3 | I43: 0 | J43: 56 | K43: utcai | L43: optikus üzletvezető, államigazgatás | M43: 1982 | N43: 1982 | O43: Budapest | P43: 22 | Q43: Budapest (Buda) | R43: 75000 | S43: 75000 | V43: 300000 | W43: Viszonylag könnyen | X43: Népszínház 49. | Y43: 5 | AC43: 35 | AD43: Azt mondja, hogy nem probléma a lakhatási kiadások fedezése (VI) (JAVÍTVA) | AE43: Alföldi utca - Teleki tér | AF43: 0.25 | AG43: FALSE | AH43: 100000 | AI43: érettségi | AJ43: 65 év feletti | AK43: tulajdonos | AL43: 25000 | AM43: idős | AN43: 1990 előtt | AO43: Low | AP43: 1 | AQ43: 9 | AR43: 3 | AS43: 0 | AT43: 0 | AU43: 0 | AV43: 2 | AW43: 1 | AX43: 1 | AY43: 1 | AZ43: 1 | BA43: 0 | BB43: 1 | BC43: 3 | BD43: 1 | BE43: 1 | BF43: 0 | BG43: 0 | BH43: 0 | BI43: 3 | BJ43: 1 | BK43: 1 | BL43: 0 | BM43: 2 | BN43: 0 | BO43: 0 | BP43: 0 | BQ43: 1 | BR43: 1 | BS43: 1 | BT43: 1 | BU43: 0 | BV43: 1 | BW43: 0 | BX43: 0 | BY43: 0 | BZ43: 0 | CA43: 1 | CB43: 2 | CC43: 0 | CD43: 0 | CE43: 0 | CF43: 1 | CG43: 0 | CH43: 2 | CI43: 0 | CJ43: 0 | CK43: 0 | CL43: 0 | CM43: 0 | CN43: 0 | CO43: 0 | CP43: 0 | CQ43: 0
A44: PCDB01 | B44: Polyák Csaba | C44: Dancs Balázs | D44: 1970 | E44: Nő | F44: főiskolai v. egyetemi diploma | G44: saját tulajdon | H44: 3 | I44: 1 | J44: 53 | K44: udvari | L44: szociális munkás | M44: 2003 | N44: 2003 | O44: Budapest | P44: 11 | Q44: Budapest (Buda) | R44: 188000 | S44: 150000 | U44: 38000 | V44: 650000 | W44: Nehezen | X44: Bauer Sándor utca 19. | Y44: 3 | AA44: zsúfolt, tele kacattal, régies konyha | AB44: elvált nehezen jön ki a pénzéből | AC44: 53 | AE44: Alföldi utca - Teleki tér | AF44: 0.28923077 | AG44: FALSE | AH44: 216666.67 | AI44: diploma | AJ44: 50 és 64 év közötti | AK44: tulajdonos | AL44: 62666.667 | AM44: fiatal tulajdonos | AN44: 1990 és 2016 között | AO44: Middle | AP44: 0 | AQ44: 8 | AR44: 17 | AS44: 0 | AT44: 1 | AU44: 0 | AV44: 3 | AW44: 2 | AX44: 3 | AY44: 2 | AZ44: 1 | BA44: 1 | BB44: 2 | BC44: 0 | BD44: 8 | BE44: 1 | BF44: 0 | BG44: 1 | BH44: 0 | BI44: 1 | BJ44: 0 | BK44: 0 | BL44: 1 | BM44: 1 | BN44: 0 | BO44: 0 | BP44: 1 | BQ44: 1 | BR44: 0 | BS44: 2 | BT44: 0 | BU44: 0 | BV44: 0 | BW44: 0 | BX44: 1 | BY44: 0 | BZ44: 0 | CA44: 0 | CB44: 1 | CC44: 1 | CD44: 0 | CE44: 1 | CF44: 0 | CG44: 0 | CH44: 2 | CI44: 0 | CJ44: 2 | CK44: 0 | CL44: 1 | CM44: 0 | CN44: 1 | CO44: 0 | CP44: 0 | CQ44: 0
A45: PCGB01 | B45: Polyák Csaba | C45: Gecse Barbara | D45: 1997 | E45: Férfi | F45: főiskolai v. egyetemi diploma | G45: piaci bérlet | H45: 2 | I45: 0 | J45: 80 | K45: utcai | L45: szoftverfejlesztő | M45: 2023 | N45: 2023 | O45: Budapest | P45: 12 | Q45: Budapest (Buda) | R45: 150000 | S45: 30000 | T45: 120000 | V45: 800000 | W45: Viszonylag könnyen | X45: Népszínház 26. | Y45: 2 | AA45: a postán interjúztunk | AC45: 45 | AD45: valszeg kettős származás, tökéletesen beszél magyarul, de a neve és sok angol szó használata, illetve a kiejtése is utal arra, hogy nem csak a magyar az elsődleges nyelve | AE45: Kiss József utca - Nagy Fuvaros utca | AF45: 0.1875 | AG45: FALSE | AH45: 400000 | AI45: diploma | AJ45: 18 és 29 év közötti | AK45: nem tulajdonos | AL45: 75000 | AM45: fiatal bérlő | AN45: 2016 és 2023 között | AO45: High | AP45: 0 | AQ45: 4 | AR45: 5 | AS45: 2 | AT45: 0 | AU45: 0 | AV45: 0 | AW45: 0 | AX45: 0 | AY45: 0 | AZ45: 0 | BA45: 0 | BB45: 1 | BC45: 1 | BD45: 0 | BE45: 0 | BF45: 0 | BG45: 1 | BH45: 0 | BI45: 1 | BJ45: 0 | BK45: 0 | BL45: 0 | BM45: 0 | BN45: 0 | BO45: 0 | BP45: 0 | BQ45: 0 | BR45: 0 | BS45: 0 | BT45: 1 | BU45: 0 | BV45: 1 | BW45: 1 | BX45: 1 | BY45: 0 | BZ45: 1 | CA45: 1 | CB45: 0 | CC45: 1 | CD45: 0 | CE45: 0 | CF45: 0 | CG45: 0 | CH45: 2 | CI45: 1 | CJ45: 0 | CK45: 1 | CL45: 0 | CM45: 0 | CN45: 1 | CO45: 0 | CP45: 0 | CQ45: 0
A46: PCMZ01 | B46: Polyák Csaba | C46: Major Zsuzsi | D46: 1979 | E46: Férfi | F46: főiskolai v. egyetemi diploma | G46: saját tulajdon | H46: 2 | I46: 0 | J46: 99 | K46: utcai | L46: táncművész | M46: 1999 | N46: 1999 | O46: Budapest | P46: 6 | Q46: Budapest (Pest) | R46: 90000 | S46: 45000 | V46: 700000 | W46: Viszonylag könnyen | X46: Népszínház 19. | Y46: 3 | Z46: csanad.kovats@gmail.com | AA46: rendezett környezet, az anyjával él, kulturális életet él, nyitottak | AC46: 40 | AE46: József krt. - Kiss József utca | AF46: 0.12857143 | AG46: FALSE | AH46: 350000 | AI46: diploma | AJ46: 30 és 49 év közötti | AK46: tulajdonos | AL46: 45000 | AM46: fiatal tulajdonos | AN46: 1990 és 2016 között | AO46: Middle | AP46: 0 | AQ46: 0 | AR46: 0 | AS46: 0 | AT46: 0 | AU46: 0 | AV46: 0 | AW46: 0 | AX46: 0 | AY46: 0 | AZ46: 0 | BA46: 0 | BB46: 0 | BC46: 0 | BD46: 0 | BE46: 0 | BF46: 0 | BG46: 0 | BH46: 0 | BI46: 0 | BJ46: 0 | BK46: 0 | BL46: 0 | BM46: 0 | BN46: 0 | BO46: 0 | BP46: 0 | BQ46: 0 | BR46: 0 | BS46: 0 | BT46: 0 | BU46: 0 | BV46: 0 | BW46: 0 | BX46: 0 | BY46: 0 | BZ46: 0 | CA46: 0 | CB46: 0 | CC46: 0 | CD46: 0 | CE46: 0 | CF46: 0 | CG46: 0 | CH46: 1 | CI46: 0 | CJ46: 0 | CK46: 0 | CL46: 0 | CM46: 0 | CN46: 0 | CO46: 0 | CP46: 0 | CQ46: 0
A47: PCMZ02 | B47: Polyák Csaba | C47: Major Zsuzsi | D47: 1952 | E47: Férfi | F47: befejezett 8 osztály | G47: saját tulajdon | H47: 2 | I47: 0 | J47: 78 | K47: udvari | L47: előadóművész | M47: 2013 | N47: 2013 | O47: Budapest | P47: 9 | Q47: Budapest (Pest) | R47: 90000 | S47: 90000 | V47: 500000 | W47: Viszonylag könnyen | X47: Népszínház 26. | Y47: 2 | Z47: csaba.derby@gmail.com | AA47: kulturált lakás, ritkán használja az utcát | AC47: 46 | AE47: Kiss József utca - Nagy Fuvaros utca | AF47: 0.18 | AG47: FALSE | AH47: 250000 | AI47: érettségi alatt | AJ47: 65 év feletti | AK47: tulajdonos | AL47: 45000 | AM47: idős | AN47: 1990 és 2016 között | AO47: Middle | AP47: 0 | AQ47: 5 | AR47: 4 | AS47: 2 | AT47: 0 | AU47: 1 | AV47: 0 | AW47: 1 | AX47: 1 | AY47: 0 | AZ47: 2 | BA47: 1 | BB47: 1 | BC47: 1 | BD47: 0 | BE47: 0 | BF47: 0 | BG47: 0 | BH47: 0 | BI47: 0 | BJ47: 0 | BK47: 1 | BL47: 0 | BM47: 0 | BN47: 0 | BO47: 0 | BP47: 1 | BQ47: 0 | BR47: 0 | BS47: 1 | BT47: 0 | BU47: 1 | BV47: 0 | BW47: 1 | BX47: 1 | BY47: 0 | BZ47: 1 | CA47: 1 | CB47: 0 | CC47: 0 | CD47: 1 | CE47: 1 | CF47: 2 | CG47: 0 | CH47: 2 | CI47: 1 | CJ47: 1 | CK47: 0 | CL47: 0 | CM47: 0 | CN47: 1 | CO47: 0 | CP47: 0 | CQ47: 1
A48: PCSA01 | B48: Polyák Csaba | C48: Szakály Abigél Noémi | D48: 1952 | E48: Férfi | F48: befejezett 8 osztály | G48: önkormányzati bérlet | H48: 1 | I48: 0 | J48: 30 | K48: udvari | L48: targoncás, kereskedelem | M48: 2000 | N48: 2000 | O48: Budapest | P48: 15 | Q48: Budapest (Pest) | R48: 50000 | S48: 29000 | T48: 19000 | V48: 298000 | W48: Viszonylag könnyen | X48: Népszínház 26. | Y48: 2 | AC48: 43 | AD48: Nyitott új dolgokra, jól megél. 1952 és 76 között a 8. kerületben élt (itt született) majd elköltözött és aztán visszaköltözött a kerületbe 2000ben | AE48: Kiss József utca - Nagy Fuvaros utca | AF48: 0.16778523 | AG48: FALSE | AH48: 298000 | AI48: érettségi alatt | AJ48: 65 év feletti | AK48: nem tulajdonos | AL48: 50000 | AM48: idős | AN48: 1990 és 2016 között | AO48: Middle | AP48: 1 | AQ48: 6 | AR48: 4 | AS48: 1 | AT48: 0 | AU48: 0 | AV48: 1 | AW48: 0 | AX48: 0 | AY48: 0 | AZ48: 1 | BA48: 1 | BB48: 1 | BC48: 1 | BD48: 0 | BE48: 1 | BF48: 0 | BG48: 0 | BH48: 0 | BI48: 1 | BJ48: 0 | BK48: 0 | BL48: 1 | BM48: 1 | BN48: 0 | BO48: 0 | BP48: 0 | BQ48: 3 | BR48: 0 | BS48: 0 | BT48: 0 | BU48: 0 | BV48: 0 | BW48: 1 | BX48: 0 | BY48: 1 | BZ48: 1 | CA48: 1 | CB48: 1 | CC48: 0 | CD48: 1 | CE48: 0 | CF48: 0 | CG48: 0 | CH48: 1 | CI48: 0 | CJ48: 1 | CK48: 0 | CL48: 0 | CM48: 0 | CN48: 0 | CO48: 0 | CP48: 0 | CQ48: 0
A49: PCSA02 | B49: Polyák Csaba | C49: Szakály Abigél Noémi | D49: 1975 | E49: Férfi | F49: gimnáziumi érettségi | G49: szívességi használat | H49: 1 | I49: 0 | J49: 30 | K49: udvari | L49: vállalkozó, kávézó | M49: 2022 | N49: 2022 | O49: Vác | Q49: Pest megye | R49: 140000 | S49: 40000 | T49: 100000 | V49: 600000 | W49: Nagyon könnyen | X49: Népszínház 57. | Y49: 0 | AA49: zsúfolt lakás, de jó körülmények | AC49: 43 | AE49: Alföldi utca - Teleki tér | AF49: 0.23333333 | AG49: FALSE | AH49: 600000 | AI49: érettségi | AJ49: 30 és 49 év közötti | AK49: nem tulajdonos | AL49: 140000 | AM49: fiatal bérlő | AN49: 2016 és 2023 között | AO49: High | AP49: 0 | AQ49: 5 | AR49: 6 | AS49: 1 | AT49: 1 | AU49: 0 | AV49: 2 | AW49: 1 | AX49: 0 | AY49: 0 | AZ49: 0 | BA49: 0 | BB49: 1 | BC49: 0 | BD49: 0 | BE49: 0 | BF49: 0 | BG49: 0 | BH49: 1 | BI49: 2 | BJ49: 1 | BK49: 2 | BL49: 0 | BM49: 1 | BN49: 0 | BO49: 0 | BP49: 0 | BQ49: 0 | BR49: 0 | BS49: 0 | BT49: 1 | BU49: 1 | BV49: 2 | BW49: 1 | BX49: 1 | BY49: 0 | BZ49: 1 | CA49: 1 | CB49: 1 | CC49: 0 | CD49: 0 | CE49: 0 | CF49: 1 | CG49: 0 | CH49: 0 | CI49: 1 | CJ49: 1 | CK49: 1 | CL49: 0 | CM49: 0 | CN49: 1 | CO49: 0 | CP49: 0 | CQ49: 0
A50: SL01 | B50: Szöllősi Luca | D50: 1946 | E50: Nő | F50: főiskolai v. egyetemi diploma | G50: saját tulajdon | H50: 1 | I50: 0 | J50: 69 | K50: utcai | L50: nyugdíjas, főkönyvelő | M50: 1946 | N50: 1946 | Q50: Ide született | R50: 65000 | S50: 65000 | V50: 300000 | W50: Viszonylag könnyen | X50: Népszínház 42-44. | Y50: 3 | AB50: Van egy fényképe, ami 1916-ban készült a házról és látszódik rajta, hogy a homlokzaton 4 oszlop van, ami a 4 évszakot ábrázolja. 1957-ben felújították a házat, és leverték a szobrokat. A hozzá legközelebb lévő szobrot azért döntötték le, mert a bal térdkalácsába befészkelt egy galamb, és ahelyett, hogy kijavították volna, ledöntötték az egészet. | AC50: 53 | AE50: Alföldi utca - Teleki tér | AF50: 0.21666667 | AG50: FALSE | AH50: 300000 | AI50: diploma | AJ50: 65 év feletti | AK50: tulajdonos | AL50: 65000 | AM50: idős | AN50: 1990 előtt | AO50: Middle | AP50: 0 | AQ50: 3 | AR50: 9 | AS50: 1 | AT50: 2 | AU50: 2 | AV50: 4 | AW50: 0 | AX50: 0 | AY50: 0 | AZ50: 1 | BA50: 0 | BB50: 2 | BC50: 0 | BD50: 2 | BE50: 0 | BF50: 0 | BG50: 0 | BH50: 0 | BI50: 7 | BJ50: 0 | BK50: 0 | BL50: 0 | BM50: 0 | BN50: 1 | BO50: 0 | BP50: 0 | BQ50: 0 | BR50: 0 | BS50: 2 | BT50: 0 | BU50: 0 | BV50: 0 | BW50: 0 | BX50: 0 | BY50: 0 | BZ50: 1 | CA50: 0 | CB50: 0 | CC50: 1 | CD50: 0 | CE50: 1 | CF50: 0 | CG50: 0 | CH50: 0 | CI50: 0 | CJ50: 0 | CK50: 0 | CL50: 0 | CM50: 0 | CN50: 0 | CO50: 0 | CP50: 0 | CQ50: 0
A51: SLOD01 | B51: Szöllősi Luca | C51: Osvay Dorottya | D51: 1989 | E51: Férfi | F51: gimnáziumi érettségi | G51: saját tulajdon | H51: 2 | J51: 60 | K51: utcai | L51: vendéglátó | M51: 2024 | N51: 2024 | O51: Budapest | P51: 9 | Q51: Budapest (Pest) | R51: 60000 | V51: 1000000 | W51: Viszonylag könnyen | X51: Népszínház 47. | Y51: 0 | AA51: jól szituált, rendezett, tiszta lakás, cuki fehér cica | AC51: 25 | AE51: Nagy Fuvaros utca - Alföldi utca | AF51: 0.06 | AG51: FALSE | AH51: 500000 | AI51: érettségi | AJ51: 30 és 49 év közötti | AK51: tulajdonos | AL51: 30000 | AM51: fiatal tulajdonos | AN51: utóbbi két évben | AO51: High | AP51: 1 | AQ51: 5 | AR51: 3 | AS51: 1 | AT51: 0 | AU51: 0 | AV51: 0 | AW51: 0 | AX51: 0 | AY51: 0 | AZ51: 1 | BA51: 0 | BB51: 1 | BC51: 2 | BD51: 0 | BE51: 0 | BF51: 0 | BG51: 0 | BH51: 0 | BI51: 0 | BJ51: 0 | BK51: 0 | BL51: 1 | BM51: 0 | BN51: 0 | BO51: 0 | BP51: 1 | BQ51: 0 | BR51: 0 | BS51: 0 | BT51: 0 | BU51: 1 | BV51: 0 | BW51: 0 | BX51: 0 | BY51: 0 | BZ51: 2 | CA51: 0 | CB51: 0 | CC51: 0 | CD51: 1 | CE51: 0 | CF51: 0 | CG51: 0 | CH51: 2 | CI51: 0 | CJ51: 0 | CK51: 0 | CL51: 0 | CM51: 0 | CN51: 0 | CO51: 0 | CP51: 0 | CQ51: 0
A52: SLOD02 | B52: Szöllősi Luca | C52: Osvay Dorottya | D52: 1994 | E52: Nő | F52: kevesebb, mint 8 osztály | G52: piaci bérlet | H52: 4 | I52: 2 | J52: 80 | K52: udvari | L52: takarító | N52: 2020 | O52: Budapest | P52: 8 | Q52: Nyolcadik kerület | W52: Nagyon nehezen | X52: Népszínház 47. | Y52: 2 | AC52: 16 | AD52: a párja intézte a lakást, ő gazdálkodik a jövedelmükkel | AE52: Nagy Fuvaros utca - Alföldi utca | AI52: érettségi alatt | AJ52: 30 és 49 év közötti | AK52: nem tulajdonos | AM52: fiatal bérlő | AN52: 2016 és 2023 között | AP52: 1 | AQ52: 1 | AR52: 4 | AS52: 1 | AT52: 0 | AU52: 0 | AV52: 1 | AW52: 0 | AX52: 0 | AY52: 0 | AZ52: 1 | BA52: 0 | BB52: 1 | BC52: 0 | BD52: 0 | BE52: 0 | BF52: 0 | BG52: 0 | BH52: 0 | BI52: 0 | BJ52: 0 | BK52: 0 | BL52: 0 | BM52: 0 | BN52: 0 | BO52: 0 | BP52: 0 | BQ52: 0 | BR52: 0 | BS52: 0 | BT52: 0 | BU52: 0 | BV52: 1 | BW52: 0 | BX52: 0 | BY52: 0 | BZ52: 0 | CA52: 1 | CB52: 0 | CC52: 1 | CD52: 0 | CE52: 1 | CF52: 0 | CG52: 0 | CH52: 0 | CI52: 0 | CJ52: 0 | CK52: 0 | CL52: 0 | CM52: 0 | CN52: 0 | CO52: 0 | CP52: 1 | CQ52: 0
A53: TBJR01 | B53: Tömösvári Barnabás | C53: Jankó Rebeka | D53: 1957 | E53: Férfi | F53: befejezett 8 osztály | G53: saját tulajdon | H53: 2 | I53: 0 | J53: 90 | K53: utcai | L53: kerékpárszerelő | M53: 2015 | N53: 2015 | O53: Budapest | P53: 7 | Q53: Budapest (Pest) | R53: 50000 | S53: 50000 | V53: 200000 | W53: Nehezen | X53: Népszínház 22. | Y53: 2 | AA53: rendezett, jó állapotú gépesített (mosogatógép), sok könyv | AB53: feketén is dolgozik jövedelemkiegészítésként, ezt vsz nem számolta bele a 13. kérdésnél | AC53: 53 | AD53: mikor a végzettséget kérdeztük, somlyogva válaszolt, illetve a volt foglalkozására irányuló kérdésnél is | AE53: József krt. - Kiss József utca | AF53: 0.25 | AG53: FALSE | AH53: 100000 | AI53: érettségi alatt | AJ53: 65 év feletti | AK53: tulajdonos | AL53: 25000 | AM53: idős | AN53: 1990 és 2016 között | AO53: Low | AP53: 0 | AQ53: 3 | AR53: 5 | AS53: 1 | AT53: 1 | AU53: 0 | AV53: 2 | AW53: 0 | AX53: 0 | AY53: 0 | AZ53: 1 | BA53: 1 | BB53: 1 | BC53: 0 | BD53: 1 | BE53: 0 | BF53: 0 | BG53: 1 | BH53: 0 | BI53: 3 | BJ53: 0 | BK53: 0 | BL53: 0 | BM53: 0 | BN53: 0 | BO53: 0 | BP53: 0 | BQ53: 1 | BR53: 0 | BS53: 0 | BT53: 1 | BU53: 0 | BV53: 2 | BW53: 1 | BX53: 0 | BY53: 0 | BZ53: 1 | CA53: 3 | CB53: 1 | CC53: 0 | CD53: 0 | CE53: 0 | CF53: 0 | CG53: 0 | CH53: 4 | CI53: 1 | CJ53: 0 | CK53: 0 | CL53: 0 | CM53: 0 | CN53: 0 | CO53: 0 | CP53: 0 | CQ53: 0
A54: TBOD01 | B54: Tömösvári Barnabás | C54: Osvay Dorottya | D54: 1969 | E54: Férfi | F54: főiskolai v. egyetemi diploma | G54: piaci bérlet | H54: 1 | I54: 0 | J54: 35 | K54: udvari | L54: egyéni vállalkozóként családfakutató, korábban levéltáros, szabadúszó várostörténész | M54: 2024 | N54: 2025 | O54: Budapest | P54: 8 | Q54: Nyolcadik kerület | R54: 200000 | S54: 40000 | T54: 160000 | V54: 400000 | W54: Nehezen | X54: Népszínház 26. | Y54: 0 | AA54: nem voltak a lakásban, állatíólag 4000 könyve van, pici a lakása, nagyon zsúfolt, azért nem ott nem interjúztak mert nem tudta volna őket leültetni mert nincs hely, lexikon az ember, nem hagy helyet interakciónak, nem veled hanem "rád" beszél | AC54: 85 | AE54: Kiss József utca - Nagy Fuvaros utca | AF54: 0.5 | AG54: TRUE | AH54: 400000 | AI54: diploma | AJ54: 50 és 64 év közötti | AK54: nem tulajdonos | AL54: 200000 | AM54: fiatal bérlő | AN54: utóbbi két évben | AO54: High | AP54: 0 | AQ54: 7 | AR54: 0 | AS54: 0 | AT54: 0 | AU54: 1 | AV54: 1 | AW54: 0 | AX54: 0 | AY54: 0 | AZ54: 3 | BA54: 0 | BB54: 2 | BC54: 0 | BD54: 2 | BE54: 0 | BF54: 0 | BG54: 0 | BH54: 0 | BI54: 0 | BJ54: 0 | BK54: 0 | BL54: 1 | BM54: 2 | BN54: 0 | BO54: 1 | BP54: 1 | BQ54: 1 | BR54: 0 | BS54: 2 | BT54: 1 | BU54: 0 | BV54: 1 | BW54: 0 | BX54: 0 | BY54: 0 | BZ54: 0 | CA54: 0 | CB54: 0 | CC54: 0 | CD54: 0 | CE54: 0 | CF54: 0 | CG54: 0 | CH54: 1 | CI54: 0 | CJ54: 0 | CK54: 1 | CL54: 0 | CM54: 0 | CN54: 0 | CO54: 1 | CP54: 0 | CQ54: 0
A55: TBSA01 | B55: Tömösvári Barnabás | C55: Szakály Abigél Noémi | D55: 1981 | E55: Nő | F55: főiskolai v. egyetemi diploma | G55: piaci bérlet | H55: 1 | I55: 0 | J55: 55 | K55: udvari | L55: reptéri dolgozó | M55: 2022 | N55: 2025 | O55: Budapest | P55: 8 | Q55: Nyolcadik kerület | R55: 230000 | S55: 60000 | T55: 170000 | V55: 450000 | W55: Könnyen | X55: Népszínház 42-44. | Y55: 0 | AA55: nemrég költözött (1 hónapja), ennek a nyomai látszódtak, rendezetlen | AC55: 65 | AE55: Alföldi utca - Teleki tér | AF55: 0.51111111 | AG55: TRUE | AH55: 450000 | AI55: diploma | AJ55: 30 és 49 év közötti | AK55: nem tulajdonos | AL55: 230000 | AM55: fiatal bérlő | AN55: utóbbi két évben | AO55: High | AP55: 1 | AQ55: 3 | AR55: 11 | AS55: 0 | AT55: 0 | AU55: 0 | AV55: 2 | AW55: 0 | AX55: 0 | AY55: 0 | AZ55: 2 | BA55: 0 | BB55: 2 | BC55: 1 | BD55: 2 | BE55: 0 | BF55: 0 | BG55: 0 | BH55: 0 | BI55: 2 | BJ55: 0 | BK55: 1 | BL55: 0 | BM55: 0 | BN55: 0 | BO55: 0 | BP55: 1 | BQ55: 0 | BR55: 0 | BS55: 2 | BT55: 1 | BU55: 1 | BV55: 1 | BW55: 1 | BX55: 0 | BY55: 1 | BZ55: 0 | CA55: 1 | CB55: 2 | CC55: 0 | CD55: 0 | CE55: 0 | CF55: 2 | CG55: 0 | CH55: 4 | CI55: 1 | CJ55: 1 | CK55: 2 | CL55: 0 | CM55: 0 | CN55: 1 | CO55: 1 | CP55: 0 | CQ55: 0
A56: TBSA02 | B56: Tömösvári Barnabás | C56: Szakály Abigél Noémi | D56: 1982 | E56: Nő | F56: főiskolai v. egyetemi diploma | G56: saját tulajdon | H56: 1 | I56: 0 | J56: 49 | K56: udvari | L56: biztonsági vezető | M56: 2008 | N56: 2008 | R56: 25000 | S56: 25000 | V56: 850000 | W56: Viszonylag könnyen | X56: Népszínház 42-44. | Y56: 2 | AA56: rendezett, szép lakás, modern berendezés, kutyával | AC56: 21 | AE56: Alföldi utca - Teleki tér | AF56: 0.029411765 | AG56: FALSE | AH56: 850000 | AI56: diploma | AJ56: 30 és 49 év közötti | AK56: tulajdonos | AL56: 25000 | AM56: fiatal tulajdonos | AN56: 1990 és 2016 között | AO56: High | AP56: 1 | AQ56: 5 | AR56: 13 | AS56: 1 | AT56: 1 | AU56: 0 | AV56: 1 | AW56: 0 | AX56: 1 | AY56: 4 | AZ56: 3 | BA56: 0 | BB56: 1 | BC56: 0 | BD56: 0 | BE56: 1 | BF56: 1 | BG56: 0 | BH56: 0 | BI56: 0 | BJ56: 0 | BK56: 0 | BL56: 2 | BM56: 1 | BN56: 0 | BO56: 1 | BP56: 1 | BQ56: 0 | BR56: 0 | BS56: 1 | BT56: 0 | BU56: 1 | BV56: 1 | BW56: 1 | BX56: 0 | BY56: 1 | BZ56: 2 | CA56: 2 | CB56: 3 | CC56: 0 | CD56: 0 | CE56: 0 | CF56: 0 | CG56: 0 | CH56: 1 | CI56: 1 | CJ56: 0 | CK56: 2 | CL56: 0 | CM56: 0 | CN56: 0 | CO56: 0 | CP56: 1 | CQ56: 1
A57: TBSA03 | B57: Tömösvári Barnabás | C57: Szakály Abigél Noémi | D57: 1959 | E57: Nő | F57: szakmunkásképző | G57: saját tulajdon | H57: 2 | I57: 0 | J57: 40 | K57: udvari | L57: cipész | M57: 1993 | N57: 1993 | O57: Budapest | P57: 13 | Q57: Budapest (Pest) | R57: 50000 | S57: 30000 | V57: 250000 | W57: Viszonylag könnyen | X57: Alföldi utca 2. | Y57: 2 | AA57: rendezett, sötét | AB57: a fia nemrég odaköltözött hozzá | AC57: 46 | AE57: Nagy Fuvaros utca - Alföldi utca | AF57: 0.2 | AG57: FALSE | AH57: 125000 | AI57: érettségi alatt | AJ57: 65 év feletti | AK57: tulajdonos | AL57: 25000 | AM57: idős | AN57: 1990 és 2016 között | AO57: Low | AP57: 1 | AQ57: 12 | AR57: 5 | AS57: 2 | AT57: 3 | AU57: 0 | AV57: 2 | AW57: 1 | AX57: 0 | AY57: 2 | AZ57: 2 | BA57: 0 | BB57: 5 | BC57: 0 | BD57: 5 | BE57: 3 | BF57: 0 | BG57: 0 | BH57: 0 | BI57: 1 | BJ57: 0 | BK57: 0 | BL57: 1 | BM57: 0 | BN57: 0 | BO57: 0 | BP57: 1 | BQ57: 4 | BR57: 2 | BS57: 1 | BT57: 1 | BU57: 0 | BV57: 2 | BW57: 2 | BX57: 1 | BY57: 1 | BZ57: 1 | CA57: 0 | CB57: 2 | CC57: 0 | CD57: 0 | CE57: 0 | CF57: 0 | CG57: 0 | CH57: 0 | CI57: 0 | CJ57: 1 | CK57: 0 | CL57: 2 | CM57: 0 | CN57: 0 | CO57: 0 | CP57: 0 | CQ57: 1

Sheet final_df_sentiment
A1: id | B1: interviewer1 | C1: interviewer2 | D1: birth_year | E1: gender | F1: education | G1: housing_type | H1: household_size | I1: num_children | J1: apartment_size | K1: apartment_location | L1: occupation | M1: years_in_district | N1: years_in_apartment | O1: prev_residence | P1: prev_district | Q1: prev_aggr | R1: housing_expenses_total | S1: utilities_cost | T1: rent_cost | U1: mortgage_cost | V1: total_income | W1: expense_coverage | X1: address | Y1: floor | Z1: contact | AA1: apartment_quality | AB1: extra_notes | AC1: interview_length | AD1: other_comments | AE1: elhelyezkedés | AF1: housing_overburden | AG1: lakhatasi_szegeny | AH1: income_per_person | AI1: education_aggr | AJ1: age_group | AK1: housing_type_aggr | AL1: housing_expenses_PP | AM1: category | AN1: f_years_in_apartment_grp | AO1: income_group | AP1: Társasházak működése (jelenleg) - Fizikai állapot / karbantartás | AQ1: Társasházak működése (jelenleg) - Közös képviselet | AR1: Társasházak működése (jelenleg) - Közösségi élet | AS1: Utca változásai - Fizikai környezet és utcakép változásai | AT1: Utcával kapcsolatos attitűdök - Biztonságérzet | AU1: Utcával kapcsolatos attitűdök - Környezeti benyomások (zaj / szmog / más) | AV1: Utcával kapcsolatos attitűdök - Társadalmi sokszínűség (etnikai / osztálybeli / más) | AW1: Önkormányzati szerep - Jelenleg | AX1: Önkormányzati szerep - Jövőre - Utcánál | AY1: Izgalmas idézet - Tanulmányba / kiállíásra | AZ1: Jövőkép a társasházról - Lakóközösség cseréje | BA1: Jövőkép a társasházról - Általános jövőkép | BB1: Jövőkép az utcáról - Jövőkép az utcáról | BC1: Lakhatási helyzet - Elhelyezkedés | BD1: Lakhatási helyzet - Komfortszint | BE1: Társasházak működése (jelenleg) - Biztonság | BF1: Társasházak működése (jelenleg) - Közös terek használata | BG1: Társasházak működése (jelenleg) - Lakóközösség változása | BH1: Utca változásai - Közbiztonság és közterületi viselkedés | BI1: Utca változásai - Lakossági összetétel / közösségek | BJ1: Utcahasználat (jelenleg) - Közlekedési élmények | BK1: Utcahasználat (jelenleg) - Közterület használata | BL1: Utcahasználat (jelenleg) - Közösségi interakciók az utcán | BM1: Utcahasználat (jelenleg) - Szabadidő / szórakozás / vendéglátás | BN1: Utcai fejlesztések értékelése - Blaha Lujza tér | BO1: Utcai fejlesztések értékelése - II. János Pál pápa tér | BP1: Utcai fejlesztések értékelése - Négyes metró | BQ1: Utcai fejlesztések értékelése - Utcai zöldítések | BR1: Utcával kapcsolatos attitűdök - Tisztaság / rendezettség | BS1: Utcával kapcsolatos attitűdök - Érzelmi kötődés | BT1: Utcahasználat (jelenleg) - Vásárlás / boltok / szolgáltatások | BU1: Utcán mit változtatna - Infrastuktúra | BV1: Utcán mit változtatna - Közbiztonság javítása | BW1: Utcán mit változtatna - Szociális ellátórendszer | BX1: Utcán mit változtatna - Tisztaság / rendezettség javítása | BY1: Izgalmas idézet - Csak vicces | BZ1: Utcai fejlesztések értékelése - Nincs hatása | CA1: Utcai fejlesztések értékelése - Teleki tér | CB1: Utcán mit változtatna - Zöldítés | CC1: Önkormányzati szerep - Jövőre - Társasháznál | CD1: Ideköltözés okai és körülményei - Munka / közlekedés | CE1: Jövőkép a társasházról - Változtatná a társasházon | CF1: Utca változásai - Üzletek / szolgáltatások / vendéglátás | CG1: Utcán mit változtatna - Vásárlás / boltok / szolgáltatások - változtatna | CH1: Utcán mit változtatna - Közlekedés | CI1: Jövőkép a társasházról - Közös képviselet szerepe | CJ1: Jövőkép a társasházról - Lakóközösség szerepe | CK1: Ideköltözés okai és körülményei - Családi / személyes okok
A2: BBGB01 | B2: Bekker Balázs | C2: Gecse Barbara | D2: 1960 | E2: Nő | F2: főiskolai v. egyetemi diploma | G2: saját tulajdon | H2: 2 | I2: 0 | K2: utcai | L2: Óvodavezető | M2: 2015 | N2: 2015 | O2: Budapest | P2: 7 | Q2: Budapest (Pest) | R2: 63000 | S2: 63000 | V2: 450000 | W2: Könnyen | X2: Népszínház 31. | Y2: 2 | AA2: Lakás teljesen rendezett, tiszta. a zunokájával ketten élnek. van egy nyuszi | AB2: pár éve meghalt a lánya és ezért vette az unokáját maga mellé. | AC2: 32 | AE2: Kiss József utca - Nagy Fuvaros utca | AF2: 0.14 | AG2: FALSE | AH2: 225000 | AI2: diploma | AJ2: 50 és 64 év közötti | AK2: tulajdonos | AL2: 31500 | AM2: idős | AN2: 1990 és 2016 között | AO2: Middle | AP2: 1 | AQ2: 1 | AR2: 1 | AS2: 1 | AT2: 1 | AU2: 0 | AV2: 0 | AW2: 1 | AX2: 1
A3: BNGC01 | B3: Baranya Nikoletta | C3: Gregor Csaba | D3: 1971 | E3: Nő | F3: főiskolai v. egyetemi diploma | G3: saját tulajdon | H3: 2 | I3: 0 | J3: 105 | K3: utcai | L3: adatvédelmi szakértő -> 5 hónapja munkanélküli | M3: 2021 | N3: 2021 | O3: Budapest | P3: 2 | Q3: Budapest (Buda) | R3: 352000 | S3: 132000 | U3: 220000 | V3: 1800000 | W3: Viszonylag nehezen | X3: Népszínház 32. | Y3: 4 | AA3: Nagyon értelmiségi lakás, tágas otthonosan limlomos | AB3: Azért jönnek ki viszonylag nehezen a pénzből mert a gyerekek külföldi taníttatására sokat költenek | AC3: 69 | AE3: Nagy Fuvaros utca - Alföldi utca | AF3: 0.19555556 | AG3: FALSE | AH3: 900000 | AI3: diploma | AJ3: 50 és 64 év közötti | AK3: tulajdonos | AL3: 176000 | AM3: fiatal tulajdonos | AN3: 2016 és 2023 között | AO3: High | AR3: 0 | AS3: 1 | AT3: 0.33333333 | AU3: 0 | AV3: 0.33333333 | AW3: 0.5 | AX3: 0 | AY3: 0.33333333 | AZ3: 0 | BA3: 0 | BB3: 0 | BC3: 1 | BD3: 1 | BE3: 0 | BF3: 0 | BG3: 0 | BH3: 0 | BI3: 0.33333333 | BJ3: 1 | BK3: 1 | BL3: 1 | BM3: 1 | BN3: 0 | BO3: 0.5 | BP3: 1 | BQ3: 1 | BR3: 0.16666667 | BS3: 1
A4: BNGC02 | B4: Gregor Csaba | C4: Baranya Nikolett | D4: 2004 | E4: Nő | F4: gimnáziumi érettségi | G4: piaci bérlet | H4: 2 | I4: 0 | J4: 50 | K4: udvari | L4: ruházati boltban eladó | M4: 2024 | N4: 2024 | O4: Székesfehérvár | Q4: Dunántúl | R4: 294000 | S4: 99000 | T4: 195000 | V4: 900000 | W4: Viszonylag könnyen | X4: Népszínház 13. | Y4: 3 | AA4: a lakásban nagytakarítás volt, ezért az erkélyen ültünk | AC4: 49 | AE4: József krt. - Kiss József utca | AF4: 0.32666667 | AG4: TRUE | AH4: 450000 | AI4: érettségi | AJ4: 18 és 29 év közötti | AK4: nem tulajdonos | AL4: 147000 | AM4: fiatal bérlő | AN4: utóbbi két évben | AO4: High | AT4: 0.33333333 | AU4: 0 | AV4: 0.28571429 | BB4: 0.33333333 | BD4: 1 | BJ4: 1 | BM4: 1 | BR4: 0 | BT4: 1 | BU4: 0 | BV4: 0 | BW4: 0 | BX4: 0
A5: BNJR01 | B5: Baranya Nikoletta | C5: Jankó Rebeka | D5: 1996 | E5: Férfi | F5: gimnáziumi érettségi | G5: saját tulajdon | H5: 3 | I5: 0 | J5: 58 | K5: udvari | L5: IT account manager | M5: 2017 | N5: 2018 | O5: Budapest | P5: 8 | Q5: Nyolcadik kerület | R5: 140000 | S5: 75000 | U5: 65000 | V5: 850000 | W5: Viszonylag könnyen | X5: Népszínház 16. | Y5: 0 | AA5: Nem volt jó állapotú, de nem is lepukkant. nem felújított. kvázi a barátnője is itt él. | AC5: 49 | AE5: József krt. - Kiss József utca | AF5: 0.16470588 | AG5: FALSE | AH5: 283333.33 | AI5: érettségi | AJ5: 18 és 29 év közötti | AK5: tulajdonos | AL5: 46666.667 | AM5: fiatal tulajdonos | AN5: 2016 és 2023 között | AO5: Middle | AQ5: 0 | AR5: 0 | AS5: 1 | AT5: 0 | AV5: 0.57142857 | AW5: 0 | AX5: 0 | BB5: 0.5 | BE5: 0 | BF5: 0 | BG5: 0 | BH5: 1 | BJ5: 1 | BN5: 0.5 | BO5: 0.33333333 | BP5: 1 | BS5: 1 | BT5: 1 | BY5: 0.33333333 | BZ5: 0.5 | CA5: 1
A6: BNPC01 | B6: Baranya Nikoletta | C6: Polyák Csaba | D6: 1979 | E6: Férfi | F6: főiskolai v. egyetemi diploma | G6: saját tulajdon | H6: 1 | I6: 0 | J6: 54 | K6: udvari | L6: masszőr, szocmunkás | M6: 2014 | N6: 2014 | O6: Budapest | P6: 7 | Q6: Budapest (Pest) | R6: 200000 | S6: 100000 | U6: 100000 | V6: 575000 | W6: Nehezen | X6: Népszínház 13. | Y6: 2 | AA6: kulturált, tenni akaró ember, nagyon szép hippi lakás, zöld | AB6: "nem az számít, milyen üzletre van szükség még, azt a piac kitermeli. az a fontos, hogy ne menjenek el, pl. gyógyszertár elment" | AC6: 75 | AE6: József krt. - Kiss József utca | AF6: 0.34782609 | AG6: TRUE | AH6: 575000 | AI6: diploma | AJ6: 30 és 49 év közötti | AK6: tulajdonos | AL6: 200000 | AM6: fiatal tulajdonos | AN6: 1990 és 2016 között | AO6: High | AR6: 0 | AS6: 0 | AT6: 0 | AU6: 0 | AV6: 0.16666667 | AW6: 0 | AX6: 0 | AY6: 0 | AZ6: 0 | BA6: 0.33333333 | BB6: 0 | BE6: 0 | BF6: 0 | BG6: 0 | BH6: 0 | BI6: 0 | BO6: 0 | BQ6: 0 | BR6: 0 | BV6: 0 | BW6: 0 | BX6: 0 | CB6: 0 | CC6: 0
A7: DBLJ01 | B7: Lökkös Júlia | C7: Dancs Balázs | D7: 1949 | E7: Nő | F7: főiskolai v. egyetemi diploma | G7: saját tulajdon | H7: 1 | I7: 0 | J7: 75 | K7: utcai | L7: tolmács, fordító egyéni vállalkozóként | M7: 2012 | N7: 2012 | O7: Budapest | P7: 7 | Q7: Budapest (Pest) | R7: 50000 | S7: 28000 | V7: 127000 | W7: Nehezen | X7: Népszínház 31. | Y7: 5 | AA7: tágas, rendezett, jó körülmények | AB7: idős értelmiségi, zsidó, valószínűleg gyakorló, van egy lánya, elvált és özvegy | AC7: 33 | AE7: Kiss József utca - Nagy Fuvaros utca | AF7: 0.39370079 | AG7: TRUE | AH7: 127000 | AI7: diploma | AJ7: 65 év feletti | AK7: tulajdonos | AL7: 50000 | AM7: idős | AN7: 1990 és 2016 között | AO7: Low | AT7: 1 | AW7: 1 | BD7: 1 | BJ7: 1 | BN7: 1 | BO7: 1 | BP7: 1 | BR7: 1 | BS7: 1 | BY7: 1 | CD7: 1
A8: DBLJ02 | B8: Lökkös Júlia | C8: Dancs Balázs | D8: 1958 | E8: Férfi | F8: főiskolai v. egyetemi diploma | G8: saját tulajdon | H8: 2 | I8: 0 | J8: 100 | K8: utcai | L8: földmérő, nyugdíjas | M8: 1990 | N8: 1990 | O8: Budapest | P8: 3 | Q8: Budapest (Buda) | R8: 100000 | V8: 400000 | W8: Viszonylag könnyen | X8: Népszínház 31. | Y8: 3 | AA8: tágas, nagypolgári lakás, rendezett, jó lakáskörülmények | AC8: 40 | AE8: Kiss József utca - Nagy Fuvaros utca | AF8: 0.25 | AG8: FALSE | AH8: 200000 | AI8: diploma | AJ8: 65 év feletti | AK8: tulajdonos | AL8: 50000 | AM8: idős | AN8: 1990 előtt | AO8: Low | AR8: 0.66666667 | AT8: 0.5 | AV8: 0.66666667 | AW8: 1 | AY8: 0.5 | AZ8: 0 | BA8: 0 | BG8: 0 | BN8: 1 | BP8: 1 | BQ8: 0 | BS8: 0.66666667 | CA8: 1 | CE8: 0 | CF8: 0
A9: DBLJ03 | B9: Dancs Balázs | C9: Lökkös Júlia | D9: 1948 | E9: Nő | F9: gimnáziumi érettségi | G9: saját tulajdon | H9: 2 | I9: 0 | J9: 78 | K9: utcai | L9: nyugdíjas, könyvesbolt-vezető | M9: 1948 | N9: 1948 | Q9: Ide született | R9: 75000 | S9: 75000 | V9: 340000 | W9: Viszonylag könnyen | X9: Bauer Sándor utca 19. | Y9: 1 | AA9: jó életkörülmények, régies tárgyak | AB9: a lánya éjszakai műszakban dolgozik egy benzinkúton | AC9: 28 | AE9: Alföldi utca - Teleki tér | AF9: 0.22058824 | AG9: FALSE | AH9: 170000 | AI9: érettségi | AJ9: 65 év feletti | AK9: tulajdonos | AL9: 37500 | AM9: idős | AN9: 1990 előtt | AO9: Low | AT9: 0 | AU9: 1 | AV9: 0 | AY9: 0 | BN9: 0 | BO9: 0 | BQ9: 1 | BR9: 0 | BS9: 1 | BZ9: 0 | CA9: 1 | CF9: 0
A10: DBSA01 | B10: Dancs Balázs | C10: Szakály Abigél Noémi | D10: 1986 | E10: Férfi | F10: főiskolai v. egyetemi diploma | G10: saját tulajdon | H10: 4 | I10: 2 | J10: 84 | K10: utcai | L10: építész | M10: 2016 | N10: 2016 | O10: Budapest | P10: 7 | Q10: Budapest (Pest) | R10: 75000 | S10: 75000 | V10: 1600000 | W10: Viszonylag könnyen | X10: Népszínház 31. | Y10: 4 | AA10: nagyon szép fényes, tágas, felújított | AB10: nagyon jó körülmények között élnek, háztartást a feleség vezeti, adatokra nagyon szenzitív, kormányellenes, a kormányváltástól sokat vár | AC10: 37 | AE10: Kiss József utca - Nagy Fuvaros utca | AF10: 0.046875 | AG10: FALSE | AH10: 400000 | AI10: diploma | AJ10: 30 és 49 év közötti | AK10: tulajdonos | AL10: 18750 | AM10: fiatal tulajdonos | AN10: 1990 és 2016 között | AO10: High | AS10: 1 | AT10: 0 | AV10: 1 | AY10: 1 | BH10: 1 | BN10: 0.66666667 | BT10: 1 | CF10: 1
A11: DEDB01 | B11: Dányi Emese | C11: Dancs Balázs | D11: 1947 | E11: Férfi | F11: szakmunkásképző | G11: szívességi használat | H11: 1 | I11: 0 | J11: 54 | K11: utcai | L11: villanyszerelő a vidámparkban | M11: 2014 | N11: 2014 | O11: Budapest | P11: 11 | Q11: Budapest (Buda) | R11: 80000 | S11: 80000 | W11: Viszonylag könnyen | X11: Népszínház 13. | Y11: 1 | AA11: régi berendezések, zsúfolt de rendezett, nem túl tiszta | AC11: 34 | AE11: József krt. - Kiss József utca | AI11: érettségi alatt | AJ11: 65 év feletti | AK11: nem tulajdonos | AL11: 80000 | AM11: idős | AN11: 1990 és 2016 között | AP11: 0 | AQ11: 0 | AS11: 1 | AU11: 0 | BH11: 0.5 | BN11: 0 | BO11: 1 | BR11: 0 | BX11: 0 | CE11: 0 | CF11: 0.5
A12: DEDB02 | B12: Dányi Emese | C12: Dancs Balázs | D12: 1974 | E12: Nő | F12: befejezett 8 osztály | G12: piaci bérlet | H12: 2 | I12: 0 | J12: 90 | K12: utcai | L12: takarító | M12: 2000 | N12: 2025 | O12: Budapest | P12: 8 | Q12: Nyolcadik kerület | R12: 330000 | S12: 120000 | T12: 210000 | V12: 560000 | W12: Nehezen | X12: Népszínház 13. | Y12: 3 | AA12: régies, muslicák voltak, zene és tv ment, unokák vendégségben voltak, a férje rokkant. a győgyszereket drágának tartja, gondban van velük | AC12: 33 | AD12: stílusos berendezés | AE12: József krt. - Kiss József utca | AF12: 0.58928571 | AG12: TRUE | AH12: 280000 | AI12: érettségi alatt | AJ12: 50 és 64 év közötti | AK12: nem tulajdonos | AL12: 165000 | AM12: fiatal bérlő | AN12: utóbbi két évben | AO12: Middle | AW12: 0 | BB12: 0 | BH12: 1 | BK12: 1 | BN12: 1 | CA12: 1
A13: DEKR01 | B13: Kisházi Réka | C13: Dányi Emese | D13: 2005 | E13: Férfi | F13: szakközépiskolai érettségi | G13: piaci bérlet | H13: 1 | I13: 0 | J13: 18 | K13: udvari | L13: vendéglátó | M13: 2023 | N13: 2025 | O13: Budapest | P13: 4 | Q13: Budapest (Pest) | R13: 152000 | S13: 18000 | T13: 134000 | V13: 600000 | W13: Könnyen | X13: Népszínház 32. | Y13: 0 | AA13: kicsi, de rendezett, nem rég költözött | AB13: bicskei gyermekotthonos, a barátnője is, aki még ott lakik | AC13: 37 | AD13: most költözött, a wc ajtót nem lehet becsukni, kb. nincs is ajtó | AE13: Nagy Fuvaros utca - Alföldi utca | AF13: 0.25333333 | AG13: FALSE | AH13: 600000 | AI13: érettségi | AJ13: 18 és 29 év közötti | AK13: nem tulajdonos | AL13: 152000 | AM13: fiatal bérlő | AN13: utóbbi két évben | AO13: High | AT13: 0.33333333 | AV13: 0.5 | BR13: 0.66666667 | BS13: 1 | CA13: 0
A14: DEKR02 | B14: Dányi Emese | C14: Kisházi Réka | D14: 1997 | E14: Férfi | F14: főiskolai v. egyetemi diploma | G14: piaci bérlet | H14: 2 | I14: 0 | J14: 62 | K14: udvari | L14: szoftverfejlesztő | M14: 2016 | N14: 2019 | O14: Budapest | P14: 8 | Q14: Nyolcadik kerület | R14: 200000 | S14: 40000 | T14: 160000 | V14: 650000 | W14: Könnyen | X14: Népszínház 16. | Y14: 2 | AA14: a ház rossz állapotú, omladozik, de a lakás szép. meleg volt, volt cica meg robotporszívó. nagy tv, sok dolog, rendetlenség, nem főznek. | AC14: 44 | AE14: József krt. - Kiss József utca | AF14: 0.30769231 | AG14: TRUE | AH14: 325000 | AI14: diploma | AJ14: 18 és 29 év közötti | AK14: nem tulajdonos | AL14: 100000 | AM14: fiatal bérlő | AN14: 2016 és 2023 között | AO14: Middle | AS14: 0.5 | AT14: 0.16666667 | AV14: 0 | AX14: 0 | BB14: 0 | BD14: 0 | BE14: 0 | BG14: 0 | BH14: 0.25 | BI14: 0 | BJ14: 1 | BP14: 1 | BQ14: 1 | BT14: 0 | CF14: 0 | CG14: 0
A15: HCSL01 | B15: Hajdu Csilla | C15: Szöllősi Luca | D15: 2000 | E15: Férfi | F15: gimnáziumi érettségi | G15: saját tulajdon | H15: 1 | I15: 0 | J15: 35 | K15: udvari | L15: gyorséttermi dolgozó | M15: 2020 | N15: 2020 | O15: Budapest | P15: 2 | Q15: Budapest (Buda) | R15: 30000 | S15: 30000 | V15: 310000 | W15: Viszonylag könnyen | X15: Népszínház 19. | Y15: 0 | AA15: kupi volt nála, úgyhogy a belső udvaron interjúztunk | AC15: 30 | AD15: régebben voltak falikutak a falon, amibe virágokat ültettek (mostanra leszedték a falikutakat) | AE15: József krt. - Kiss József utca | AF15: 0.096774194 | AG15: FALSE | AH15: 310000 | AI15: érettségi | AJ15: 18 és 29 év közötti | AK15: tulajdonos | AL15: 30000 | AM15: fiatal tulajdonos | AN15: 2016 és 2023 között | AO15: Middle | AP15: 0.66666667 | AQ15: 0 | AR15: 0.5 | AT15: 1 | AV15: 1 | BN15: 0 | BY15: 0 | BZ15: 0 | CF15: 1
A16: JRDE01 | B16: Jankó Rebeka | C16: Dányi Emese | D16: 1990 | E16: Nő | F16: főiskolai v. egyetemi diploma | G16: saját tulajdon | H16: 2 | I16: 0 | J16: 61 | K16: udvari | L16: szülésznő | M16: 2014 | N16: 2014 | O16: Pilisszentiván | Q16: Pest megye | R16: 60000 | S16: 60000 | W16: Könnyen | X16: Népszínház 16. | Y16: 2 | AA16: Otthonos, van cica, nem zsúfolt, konyha régi, de le akarja cserélni. Amikor ide költözött mindent fel kellett újítani. Saját lakása előtt is rendbetartja a környezetetét. | AC16: 53 | AE16: József krt. - Kiss József utca | AI16: diploma | AJ16: 30 és 49 év közötti | AK16: tulajdonos | AL16: 30000 | AM16: fiatal tulajdonos | AN16: 1990 és 2016 között | AS16: 1 | AT16: 0.33333333 | AU16: 0 | AV16: 0.66666667 | AY16: 1 | BB16: 1 | BC16: 1 | BD16: 1 | BI16: 1 | BM16: 1 | BN16: 0.5 | BO16: 1 | BP16: 1 | BQ16: 0.66666667 | BR16: 0 | BS16: 1 | BY16: 1 | CF16: 0
A17: JRDE02 | B17: Jankó Rebeka | C17: Dányi Emese | D17: 1947 | E17: Nő | F17: szakközépiskolai érettségi | G17: szívességi használat | H17: 1 | I17: 0 | J17: 96 | K17: utcai | L17: gyengeárammal kapcsolatos technikus | M17: 1986 | N17: 1989 | O17: Nagykovácsi | Q17: Pest megye | R17: 80000 | S17: 80000 | V17: 210000 | W17: Viszonylag könnyen | X17: Népszínház 19. | Y17: 4 | AC17: 74 | AE17: József krt. - Kiss József utca | AF17: 0.38095238 | AG17: TRUE | AH17: 210000 | AI17: érettségi | AJ17: 65 év feletti | AK17: nem tulajdonos | AL17: 80000 | AM17: idős | AN17: 1990 előtt | AO17: Middle | AP17: 0 | AQ17: 0 | AT17: 0 | AU17: 0 | AV17: 0.2 | AW17: 1 | BE17: 0 | BI17: 0 | BJ17: 1 | BN17: 0 | BO17: 1 | BP17: 1 | BR17: 0 | BT17: 1 | CA17: 0.5
A18: JRGC01 | B18: Gregor Csaba | C18: Jankó Rebeka | D18: 2004 | E18: Nő | F18: gimnáziumi érettségi | G18: piaci bérlet | H18: 1 | I18: 0 | K18: udvari | L18: egyetemista | M18: 2024 | N18: 2024 | O18: Kisbér | Q18: Dunántúl | R18: 258000 | S18: 30000 | T18: 228000 | V18: 300000 | W18: Viszonylag nehezen | X18: Népszínház 16. | Y18: 2 | AC18: 38 | AD18: társbérlet | AE18: József krt. - Kiss József utca | AF18: 0.86 | AG18: TRUE | AH18: 300000 | AI18: érettségi | AJ18: 18 és 29 év közötti | AK18: nem tulajdonos | AL18: 258000 | AM18: fiatal bérlő | AN18: utóbbi két évben | AO18: Middle | AP18: 0 | AT18: 1 | AU18: 0 | AV18: 1 | BB18: 1 | BL18: 1 | BM18: 1 | BN18: 1 | BO18: 1 | BP18: 1 | BR18: 0.5
A19: KROD01 | B19: Kisházi Réka | C19: Osvay Dorottya | D19: 2001 | E19: Férfi | F19: főiskolai v. egyetemi diploma | G19: piaci bérlet | H19: 1 | I19: 0 | J19: 80 | K19: udvari | L19: gépészmérnök | M19: 2025 | N19: 2025 | O19: Budapest, Norvégia | P19: 9 | Q19: Budapest (Pest) | R19: 110000 | W19: Nem tudja | X19: Népszínház 36. | Y19: 3 | AA19: 6-an laknak együtt, mind külföldiek | AB19: palesztin férfi, jól tud magyarul | AC19: 36 | AD19: társbérlet | AE19: Nagy Fuvaros utca - Alföldi utca | AI19: diploma | AJ19: 18 és 29 év közötti | AK19: nem tulajdonos | AL19: 110000 | AM19: fiatal bérlő | AN19: utóbbi két évben | AT19: 0 | AU19: 0 | AV19: 0 | BN19: 0 | BO19: 1
A20: KROD02 | B20: Kisházi Réka | C20: Osvay Dorottya | D20: 1995 | E20: Férfi | F20: főiskolai v. egyetemi diploma | G20: saját tulajdon | H20: 1 | I20: 0 | J20: 60 | K20: utcai | L20: közgazdász | M20: 2025 | N20: 2025 | O20: Budapest | P20: 9 | Q20: Budapest (Pest) | V20: 300000 | W20: Viszonylag könnyen | X20: Népszínház 22. | Y20: 1 | AA20: A lakás felújítás alatt áll még, de jól szituáltnak tűnik | AC20: 31 | AE20: József krt. - Kiss József utca | AH20: 300000 | AI20: diploma | AJ20: 18 és 29 év közötti | AK20: tulajdonos | AM20: fiatal tulajdonos | AN20: utóbbi két évben | AO20: Middle | AT20: 0 | AV20: 0 | BA20: 0 | BB20: 1 | BE20: 0 | BN20: 1 | BR20: 0
A21: KROD03 | B21: Kisházi Réka | C21: Osvay Dorottya | D21: 1979 | E21: Férfi | F21: főiskolai v. egyetemi diploma | G21: saját tulajdon | H21: 4 | I21: 2 | J21: 62 | K21: udvari | L21: térképész | M21: 2000 | N21: 2000 | O21: Barcs | Q21: Dunántúl | R21: 50000 | S21: 50000 | V21: 900000 | W21: Könnyen | X21: Népszínház 36. | Y21: 3 | AA21: jól szituált, felesége festőművész és a füvészkertben dolgozik, diplomás házaspár gyerekekkel, feleség festményeivel van kidekrálva mind a gang mind a lakás | AC21: 51 | AE21: Nagy Fuvaros utca - Alföldi utca | AF21: 0.055555556 | AG21: FALSE | AH21: 225000 | AI21: diploma | AJ21: 30 és 49 év közötti | AK21: tulajdonos | AL21: 12500 | AM21: fiatal tulajdonos | AN21: 1990 és 2016 között | AO21: Middle | AU21: 0 | AV21: 0 | AW21: 0 | AY21: 1 | BD21: 1 | BJ21: 1 | BN21: 1 | BO21: 1 | BP21: 1 | BQ21: 1 | BT21: 0 | BZ21: 1 | CA21: 0 | CF21: 1 | CH21: 0
A22: KROD04 | B22: Kisházi Réka | C22: Osvay Dorottya | D22: 1957 | E22: Nő | F22: főiskolai v. egyetemi diploma | G22: saját tulajdon | H22: 1 | I22: 0 | J22: 64 | K22: utcai | L22: Nyugdíjfolyósító Igazgatóságnál | M22: 1975 | N22: 1975 | O22: Budapest | P22: 8 | Q22: Nyolcadik kerület | R22: 58000 | S22: 58000 | V22: 300000 | W22: Nehezen | X22: Alföldi utca 2. | Y22: 3 | AA22: állítása szerint küzködik anyagilag. a lakása jól szituált | AC22: 41 | AE22: Nagy Fuvaros utca - Alföldi utca | AF22: 0.19333333 | AG22: FALSE | AH22: 300000 | AI22: diploma | AJ22: 65 év feletti | AK22: tulajdonos | AL22: 58000 | AM22: idős | AN22: 1990 előtt | AO22: Middle | AT22: 1 | AV22: 0.5 | AW22: 1 | BO22: 1 | BP22: 1 | BR22: 0 | CA22: 1
A23: KROD05 | B23: Kisházi Réka | C23: Osvay Dorottya | D23: 2000 | E23: Férfi | F23: főiskolai v. egyetemi diploma | G23: saját tulajdon | H23: 2 | I23: 0 | J23: 70 | K23: utcai | L23: hűtés-fűtés tech értékesítő | M23: 2018 | N23: 2018 | O23: Szarvas | Q23: Észak és Alföld | R23: 45000 | S23: 45000 | V23: 600000 | W23: Könnyen | X23: Alföldi utca 2. | Y23: 1 | AA23: rendezett, jól szituált tiszta lakás | AC23: 33 | AE23: Nagy Fuvaros utca - Alföldi utca | AF23: 0.075 | AG23: FALSE | AH23: 300000 | AI23: diploma | AJ23: 18 és 29 év közötti | AK23: tulajdonos | AL23: 22500 | AM23: fiatal tulajdonos | AN23: 2016 és 2023 között | AO23: Middle | AP23: 0 | AQ23: 0 | AU23: 0 | BE23: 1 | BO23: 1 | BQ23: 1
A24: KROD06 | B24: Kisházi Réka | C24: Osvay Dorottya | D24: 1988 | E24: Nő | F24: szakközépiskolai érettségi | G24: szívességi használat | H24: 3 | I24: 2 | J24: 24 | K24: udvari | L24: kereskedelmi menedzser, most gyereket nevel | M24: 2025 | N24: 2025 | O24: Budapest | P24: 7 | Q24: Budapest (Pest) | R24: 200000 | S24: 55000 | T24: 145000 | V24: 500000 | W24: Könnyen | X24: Népszínház 57. | Y24: 2 | AA24: zsúfolt, rendezett lakás | AB24: A házban vannak kinti wc-k, amit mások használnak is. | AC24: 33 | AD24: a népszínház utcában nőtt fel, 7 hónapot élt Egyiptomban, 4 évet a 7 kerben, de azon kívül egész életében népszi és diószegi | AE24: Alföldi utca - Teleki tér | AF24: 0.4 | AG24: TRUE | AH24: 166666.67 | AI24: érettségi | AJ24: 30 és 49 év közötti | AK24: nem tulajdonos | AL24: 66666.667 | AM24: fiatal bérlő | AN24: utóbbi két évben | AO24: Low | AP24: 0.5 | AR24: 0.5 | AT24: 0 | AV24: 0 | BD24: 0 | BF24: 1 | BI24: 0 | BJ24: 1 | BN24: 1 | BR24: 0 | CA24: 1 | CF24: 0
A25: KRTB01 | B25: Kisházi Réka | C25: Tömösvári Barnabás | D25: 1998 | E25: Férfi | F25: főiskolai v. egyetemi diploma | G25: piaci bérlet | H25: 2 | I25: 0 | J25: 46 | K25: udvari | L25: diák, weblaptervező | M25: 2019 | N25: 2025 | O25: Budapest | P25: 11 | Q25: Budapest (Buda) | R25: 190000 | S25: 19000 | T25: 170000 | V25: 450000 | W25: Nagyon könnyen | X25: Népszínház 42-44. | Y25: 0 | AA25: értelmiségi, diáklakás, pride zászló, rendezett, tiszta | AC25: 48 | AE25: Alföldi utca - Teleki tér | AF25: 0.42222222 | AG25: TRUE | AH25: 225000 | AI25: diploma | AJ25: 18 és 29 év közötti | AK25: nem tulajdonos | AL25: 95000 | AM25: fiatal bérlő | AN25: utóbbi két évben | AO25: Middle | AR25: 1 | AV25: 1 | AW25: 1 | BB25: 1 | BD25: 1 | BF25: 1 | BJ25: 1 | BK25: 1 | BN25: 0.5 | BO25: 1 | BP25: 1 | BQ25: 0.5 | BS25: 1 | CB25: 1 | CH25: 1
A26: KRTB02 | B26: Kisházi Réka | C26: Tömösvári Barnabás | D26: 1981 | E26: Nő | F26: főiskolai v. egyetemi diploma | G26: saját tulajdon | H26: 3 | I26: 1 | J26: 55 | K26: udvari | L26: mentális közérzetjavítás, ékszeres vállalkozás | M26: 2006 | N26: 2025 | O26: Budapest | P26: 11 | Q26: Budapest (Buda) | R26: 173000 | S26: 73000 | U26: 100000 | V26: 200000 | W26: Viszonylag könnyen | X26: Népszínház 14. | Y26: 0 | AA26: most költözött, zsúfolt, de rendezett - sűrűn dekorált. keresztény és keleti-spirituális jelképek, díszek, stb. | AB26: nemrég veszítette el az állását, egy hónapja költözött, válófélben van. úgy tűnik, most a tartalékaiból él, ez egy újonnan kialakult helyzet | AC26: 50 | AE26: József krt. - Kiss József utca | AF26: 0.865 | AG26: TRUE | AH26: 66666.667 | AI26: diploma | AJ26: 30 és 49 év közötti | AK26: tulajdonos | AL26: 57666.667 | AM26: fiatal tulajdonos | AN26: utóbbi két évben | AO26: Low | AR26: 1 | AT26: 0.33333333 | AV26: 0.5 | AY26: 1 | BB26: 1 | BE26: 0 | BN26: 1 | BO26: 0.5 | BR26: 0.2 | BS26: 1 | BU26: 0.5 | BV26: 0 | BX26: 0 | CB26: 1 | CH26: 1
A27: KRTB03 | B27: Kisházi Réka | C27: Tömösvári Barnabás | D27: 2002 | E27: Férfi | F27: gimnáziumi érettségi | G27: saját tulajdon | H27: 1 | I27: 0 | J27: 32 | K27: udvari | L27: barber | M27: 2018 | N27: 2023 | O27: Budapest | P27: 10 | Q27: Budapest (Pest) | R27: 70000 | S27: 70000 | V27: 600000 | W27: Könnyen | X27: Népszínház 49. | Y27: 2 | AB27: mikor a barátnője apja megtudta, hogy itt lakik, nem akarta, hogy találkozzanak, mert "itt csak romák laknak". úgy érzi, hogy az, hogy itt lakik, sokszor negatív előítéletekkel jár, megbélyegzéssel találkozik | AC27: 64 | AE27: Alföldi utca - Teleki tér | AF27: 0.11666667 | AG27: FALSE | AH27: 600000 | AI27: érettségi | AJ27: 18 és 29 év közötti | AK27: tulajdonos | AL27: 70000 | AM27: fiatal tulajdonos | AN27: 2016 és 2023 között | AO27: High | AP27: 1 | AT27: 0.2 | AV27: 0.22222222 | AY27: 1 | BB27: 1 | BJ27: 1 | BP27: 1 | BR27: 0 | BS27: 1 | BV27: 0 | BW27: 0 | CF27: 0
A28: LJBN01 | B28: Lökkös Júlia | C28: Baranya Nikolett | D28: 1989 | E28: Nő | F28: gimnáziumi érettségi | G28: piaci bérlet | H28: 2 | I28: 0 | J28: 110 | K28: utcai | L28: munkanélküli, egyetemista, korábban dolgozott könyvkötőműhelyben | M28: 2016 | N28: 2016 | O28: Budapest | P28: 6 | Q28: Budapest (Pest) | R28: 213000 | S28: 48000 | T28: 165000 | V28: 580000 | W28: Nagyon könnyen | X28: Népszínház 22. | Y28: 4 | AA28: tágas, világos, szépen berendezett, elég felső-közés életkörülmények, füstölő a wc-ben | AB28: zajos a lakás az utca miatt | AC28: 51 | AE28: József krt. - Kiss József utca | AF28: 0.36724138 | AG28: TRUE | AH28: 290000 | AI28: érettségi | AJ28: 30 és 49 év közötti | AK28: nem tulajdonos | AL28: 106500 | AM28: fiatal bérlő | AN28: 1990 és 2016 között | AO28: Middle | AR28: 1 | AS28: 1 | AT28: 0.66666667 | AU28: 0.5 | AV28: 1 | AY28: 1 | BB28: 1 | BN28: 0.5 | BO28: 0.5 | BP28: 1 | BQ28: 0.5 | BR28: 0.5 | BS28: 1 | CA28: 0
A29: LJSA01 | B29: Lökkös Júlia | C29: Szakály Abigél Noémi | D29: 1958 | E29: Nő | F29: szakközépiskolai érettségi | G29: szívességi használat | H29: 2 | I29: 0 | J29: 40 | K29: utcai | L29: villamosvezető | M29: 2024 | N29: 2024 | O29: Budapest | P29: 6 | Q29: Budapest (Pest) | R29: 65000 | S29: 65000 | V29: 450000 | W29: Könnyen | X29: Népszínház 57. | Y29: 0 | AA29: fényes, dohányszag, de rendezett, szocialista bútorok, két nyugdíjas | AB29: barátnője háza, akit gondoz, ingyen él ott | AC29: 33 | AE29: Alföldi utca - Teleki tér | AF29: 0.14444444 | AG29: FALSE | AH29: 225000 | AI29: érettségi | AJ29: 65 év feletti | AK29: nem tulajdonos | AL29: 32500 | AM29: idős | AN29: utóbbi két évben | AO29: Middle | AS29: 1 | AT29: 0 | AU29: 0 | AV29: 0 | AW29: 0.33333333 | AX29: 0 | BA29: 0 | BB29: 0 | BE29: 0.66666667 | BH29: 0 | BI29: 0.5 | BO29: 0.5 | BR29: 0.33333333 | CC29: 0 | CE29: 0 | CF29: 0 | CG29: 0 | CI29: 0 | CJ29: 0
A30: LJSA02 | B30: Lökkös Júlia | C30: Szakály Abigél Noémi | D30: 1937 | E30: Nő | F30: befejezett 8 osztály | G30: saját tulajdon | H30: 1 | I30: 0 | J30: 34 | K30: udvari | L30: műszaki rajz szerkesztő, rajzoló | M30: 1965 | N30: 1985 | O30: Budapest | P30: 8 | Q30: Nyolcadik kerület | R30: 42000 | S30: 42000 | V30: 250000 | W30: Viszonylag könnyen | X30: Népszínház 26. | Y30: 2 | AA30: szűkös nagymama lakás | AB30: kis üzletek, cipőbolt, posta hiányoznak neki. sok változáson ment át ő is, az utca is, siratta a múltat | AC30: 39 | AE30: Kiss József utca - Nagy Fuvaros utca | AF30: 0.168 | AG30: FALSE | AH30: 250000 | AI30: érettségi alatt | AJ30: 65 év feletti | AK30: tulajdonos | AL30: 42000 | AM30: idős | AN30: 1990 előtt | AO30: Middle | AP30: 0 | AT30: 0 | AV30: 0 | BA30: 0 | BD30: 0 | BF30: 0 | BG30: 0 | BH30: 0 | BI30: 0 | BJ30: 1 | BN30: 0 | BR30: 0 | BT30: 0 | BZ30: 0 | CF30: 0 | CG30: 0
A31: LJSA03 | B31: Lökkös Júlia | C31: Szakály Abigél Noémi | D31: 1979 | E31: Nő | F31: gimnáziumi érettségi | G31: saját tulajdon | H31: 1 | I31: 0 | J31: 64 | K31: utcai | L31: masszőr | M31: 1979 | N31: 1979 | Q31: Ide született | R31: 55000 | S31: 55000 | W31: Könnyen | X31: Népszínház 34. | Y31: 2 | AA31: egyszerű rendezett lakás 2 kutyával | AC31: 25 | AE31: Nagy Fuvaros utca - Alföldi utca | AI31: érettségi | AJ31: 30 és 49 év közötti | AK31: tulajdonos | AL31: 55000 | AM31: fiatal tulajdonos | AN31: 1990 előtt | AP31: 0 | AQ31: 0 | AR31: 0.5 | AT31: 1 | AU31: 0.5 | AV31: 1 | BB31: 1 | BC31: 0.5 | BD31: 0 | BI31: 1 | BJ31: 1 | BO31: 0 | BP31: 1 | BQ31: 1 | BR31: 0 | BZ31: 0 | CF31: 0
A32: LJSA04 | B32: Lökkös Júlia | C32: Szakály Abigél Noémi | D32: 2004 | E32: Férfi | F32: gimnáziumi érettségi | G32: piaci bérlet | H32: 2 | I32: 0 | J32: 53 | K32: utcai | L32: egyetemista | M32: 2023 | N32: 2023 | O32: Császár | Q32: Dunántúl | R32: 105000 | S32: 15000 | T32: 90000 | V32: 500000 | W32: Viszonylag könnyen | X32: Népszínház 34. | Y32: 2 | AC32: 28 | AE32: Nagy Fuvaros utca - Alföldi utca | AF32: 0.21 | AG32: FALSE | AH32: 250000 | AI32: érettségi | AJ32: 18 és 29 év közötti | AK32: nem tulajdonos | AL32: 52500 | AM32: fiatal bérlő | AN32: 2016 és 2023 között | AO32: Middle | AP32: 0 | AR32: 1 | AS32: 1 | AT32: 0.5 | AU32: 1 | AV32: 1 | AY32: 0.66666667 | BB32: 1 | BC32: 1 | BE32: 0 | BF32: 0 | BJ32: 1 | BN32: 1 | BO32: 1 | BP32: 1 | BR32: 1
A33: LJSA05 | B33: Lökkös Júlia | C33: Szakály Abigél Noémi | D33: 1999 | E33: Nő | F33: befejezett 8 osztály | G33: piaci bérlet | H33: 2 | I33: 0 | J33: 35 | K33: udvari | L33: takarító | M33: 2023 | N33: 2023 | O33: Budapest | P33: 6 | Q33: Budapest (Pest) | R33: 300000 | S33: 30000 | T33: 220000 | V33: 400000 | W33: Nehezen | X33: Népszínház 34. | Y33: 3 | AA33: a férje munkanélküli, egyszerű letisztult, kicsi lakás | AC33: 18 | AE33: Nagy Fuvaros utca - Alföldi utca | AF33: 0.75 | AG33: TRUE | AH33: 200000 | AI33: érettségi alatt | AJ33: 18 és 29 év közötti | AK33: nem tulajdonos | AL33: 150000 | AM33: fiatal bérlő | AN33: 2016 és 2023 között | AO33: Low | AP33: 0 | AQ33: 0 | AR33: 1 | AS33: 1 | AT33: 0 | AY33: 1 | BB33: 1 | BH33: 0 | BI33: 0 | BR33: 0 | BT33: 1 | CA33: 1 | CF33: 1
A34: MZGC01 | B34: Major Zsuzsanna | C34: Gregor Csaba | D34: 1960 | E34: Nő | F34: szakközépiskolai érettségi | G34: önkormányzati bérlet | H34: 3 | I34: 1 | J34: 40 | K34: utcai | L34: nyugdíjas, ápoló | M34: 1999 | N34: 2021 | O34: Budapest | P34: 14 | Q34: Budapest (Pest) | R34: 106000 | S34: 85000 | T34: 21000 | V34: 330000 | W34: Viszonylag könnyen | X34: Népszínház 57. | Y34: 2 | AA34: összeszedett, rendezett lakás, családias | AC34: 25 | AE34: Alföldi utca - Teleki tér | AF34: 0.32121212 | AG34: TRUE | AH34: 110000 | AI34: érettségi | AJ34: 50 és 64 év közötti | AK34: nem tulajdonos | AL34: 35333.333 | AM34: idős | AN34: 2016 és 2023 között | AO34: Low | AS34: 1 | AT34: 0 | AV34: 0 | AX34: 1 | BA34: 0 | BB34: 1 | BD34: 1 | BH34: 0 | BM34: 1 | BO34: 1 | BR34: 0.25 | BS34: 1 | BY34: 0 | CA34: 1
A35: MZGC02 | B35: Major Zsuzsanna | C35: Gregor Csaba | D35: 2000 | E35: Férfi | F35: főiskolai v. egyetemi diploma | G35: saját tulajdon | H35: 3 | I35: 0 | J35: 51 | K35: udvari | L35: könyvelő | M35: 2022 | N35: 2022 | O35: Budapest | P35: 3 | Q35: Budapest (Buda) | R35: 325000 | S35: 25000 | U35: 300000 | W35: Viszonylag könnyen | X35: Népszínház 16. | Y35: 0 | AC35: 28 | AE35: József krt. - Kiss József utca | AI35: diploma | AJ35: 18 és 29 év közötti | AK35: tulajdonos | AL35: 108333.33 | AM35: fiatal tulajdonos | AN35: 2016 és 2023 között | AP35: 0 | AQ35: 1 | AR35: 0 | AS35: 1 | AT35: 1 | BB35: 1 | BD35: 0.66666667 | BJ35: 1 | BN35: 1 | BR35: 0.5 | BY35: 1
A36: ODGB01 | B36: Osvay Dorottya | C36: Gecse Barbara | D36: 1991 | E36: Férfi | F36: gimnáziumi érettségi | G36: saját tulajdon | H36: 1 | I36: 0 | J36: 57 | K36: utcai | L36: operatőr | M36: 2023 | N36: 2023 | O36: Budapest | P36: 7 | Q36: Budapest (Pest) | R36: 40000 | S36: 40000 | W36: Viszonylag könnyen | X36: Népszínház 14. | Y36: 3 | AA36: felújított, alter, fife, plakátok, növények mac képernyő | AB36: nagyon érdeklődött a kutatás iránt, barátkozó volt | AC36: 33 | AE36: József krt. - Kiss József utca | AI36: érettségi | AJ36: 30 és 49 év közötti | AK36: tulajdonos | AL36: 40000 | AM36: fiatal tulajdonos | AN36: 2016 és 2023 között | AQ36: 1 | AR36: 0 | AU36: 0.5 | AV36: 0 | AY36: 0.33333333 | BB36: 1 | BH36: 1 | BO36: 1 | BQ36: 1 | BZ36: 1
A37: OMDB01 | B37: Óvári Márton | C37: Dancs Balázs | D37: 1992 | E37: Nő | F37: gimnáziumi érettségi | G37: piaci bérlet | H37: 2 | I37: 0 | J37: 68 | K37: utcai | L37: szocmunkás | M37: 2019 | N37: 2021 | O37: Budapest | P37: 8 | Q37: Nyolcadik kerület | R37: 210000 | S37: 40000 | T37: 168000 | V37: 730000 | W37: Viszonylag könnyen | X37: Népszínház 31. | Y37: 1 | AA37: tiszta, rendezett lakás, gyakran használt eszközök újak. | AB37: van egy macskája | AE37: Kiss József utca - Nagy Fuvaros utca | AF37: 0.28767123 | AG37: FALSE | AH37: 365000 | AI37: érettségi | AJ37: 30 és 49 év közötti | AK37: nem tulajdonos | AL37: 105000 | AM37: fiatal bérlő | AN37: 2016 és 2023 között | AO37: High | AQ37: 1 | AS37: 1 | AT37: 1 | AV37: 0.66666667 | AX37: 1 | BB37: 1 | BC37: 1 | BD37: 1 | BH37: 1 | BI37: 1 | BN37: 0.5 | BQ37: 1 | BR37: 0 | BS37: 0.66666667 | BT37: 1 | BY37: 1 | CA37: 1 | CB37: 1 | CF37: 1
A38: OMDE01 | B38: Óvári Márton | C38: Dányi Emese | D38: 2005 | E38: Férfi | F38: gimnáziumi érettségi | G38: önkormányzati bérlet | H38: 4 | I38: 2 | J38: 50 | K38: utcai | L38: egyetemista | M38: 2016 | N38: 2024 | O38: Budapest | P38: 8 | Q38: Nyolcadik kerület | R38: 95000 | S38: 50000 | T38: 90000 | V38: 500000 | W38: Viszonylag nehezen | X38: Népszínház 57. | Y38: 3 | AA38: kaotikus (sokan laknak kis helyen: 4 ember, 3 fiatal és 1 keresű korú) | AC38: 24 | AD38: rezsi 50e kb. (VI) | AE38: Alföldi utca - Teleki tér | AF38: 0.19 | AG38: FALSE | AH38: 125000 | AI38: érettségi | AJ38: 18 és 29 év közötti | AK38: nem tulajdonos | AL38: 23750 | AM38: fiatal bérlő | AN38: utóbbi két évben | AO38: Low | AT38: 1 | AU38: 0 | BB38: 1 | BD38: 0 | BH38: 1 | BN38: 1 | BR38: 0
A39: OMDE02 | B39: Óvári Márton | C39: Dányi Emese | D39: 1946 | E39: Nő | F39: főiskolai v. egyetemi diploma | G39: saját tulajdon | H39: 1 | I39: 0 | J39: 75 | K39: utcai | L39: tolmács, idegenvezető, külker üzletkötő | M39: 1990 | N39: 1990 | O39: Szófia | Q39: Külföld | R39: 50000 | S39: 13000 | V39: 150000 | W39: Viszonylag nehezen | X39: Népszínház 19. | Y39: 3 | AC39: 85 | AE39: József krt. - Kiss József utca | AF39: 0.33333333 | AG39: TRUE | AH39: 150000 | AI39: diploma | AJ39: 65 év feletti | AK39: tulajdonos | AL39: 50000 | AM39: idős | AN39: 1990 előtt | AO39: Low | AP39: 0.5 | AR39: 0 | AT39: 1 | AU39: 0 | AV39: 0.4 | AW39: 0 | AY39: 0 | BE39: 0 | BH39: 0 | BQ39: 1 | BR39: 0 | BY39: 1 | CF39: 0.5
A40: OMLJ01 | B40: Óvári Márton | C40: Lökkös Júlia | D40: 1956 | E40: Férfi | F40: szakmunkásképző | G40: saját tulajdon | H40: 2 | I40: 0 | J40: 80 | K40: utcai | L40: kórházi gondnok | M40: 1989 | N40: 1989 | O40: Budapest | P40: 5 | Q40: Pest megye | R40: 70000 | S40: 70000 | W40: Könnyen | X40: Népszínház 11. | Y40: 2 | AA40: jó életkörülmények, nagypolgári lakás | AD40: a felesége a közös képviselő | AE40: József krt. - Kiss József utca | AI40: érettségi alatt | AJ40: 65 év feletti | AK40: tulajdonos | AL40: 35000 | AM40: idős | AN40: 1990 előtt | AP40: 0 | AS40: 1 | AT40: 1 | AU40: 1 | AV40: 1 | AY40: 1 | BI40: 1 | BN40: 1 | BO40: 0 | BQ40: 1 | BR40: 0 | CA40: 0
A41: OMLJ02 | B41: Óvári Márton | C41: Lökkös Júlia | D41: 1990 | E41: Férfi | F41: főiskolai v. egyetemi diploma | G41: saját tulajdon | H41: 2 | I41: 0 | J41: 27 | K41: udvari | L41: Közalkalmazott, egyetemen tanul | M41: 2017 | N41: 2018 | O41: Kecskemét | Q41: Észak és Alföld | R41: 40000 | S41: 25000 | W41: Viszonylag könnyen | X41: Bauer Sándor utca 19. | Y41: 4 | Z41: kovacsmilan90@gmail.com | AA41: nem engedett be a lakásba, az interjú a gangon készült | AE41: Alföldi utca - Teleki tér | AI41: diploma | AJ41: 30 és 49 év közötti | AK41: tulajdonos | AL41: 20000 | AM41: fiatal tulajdonos | AN41: 2016 és 2023 között | AQ41: 0 | AR41: 1 | AS41: 0 | AT41: 1 | AV41: 0 | AW41: 0 | AY41: 1 | BB41: 1 | BC41: 1 | BH41: 0 | BI41: 0.33333333 | BJ41: 1 | BP41: 1 | BQ41: 0 | BS41: 1
A42: OMMZ01 | B42: Óvári Márton | C42: Major Zsuzsi | D42: 1999 | E42: Nő | F42: főiskolai v. egyetemi diploma | G42: piaci bérlet | H42: 1 | I42: 0 | J42: 36 | K42: udvari | L42: vendéglátó | M42: 2025 | N42: 2025 | O42: Budapest | P42: 9 | Q42: Budapest (Pest) | R42: 240000 | S42: 20000 | T42: 220000 | W42: Viszonylag könnyen | X42: Népszínház 49. | Y42: 5 | AC42: 28 | AD42: 17:38- nál azt mondja, hogy nincs utcai ablaka (VI) JAVÍTVA | AE42: Alföldi utca - Teleki tér | AI42: diploma | AJ42: 18 és 29 év közötti | AK42: nem tulajdonos | AL42: 240000 | AM42: fiatal bérlő | AN42: utóbbi két évben | AP42: 1 | AR42: 1 | AT42: 1 | AU42: 1 | BB42: 1 | BE42: 1
A43: OMMZ02 | B43: Óvári Márton | C43: Major Zsuzsi | D43: 1957 | E43: Nő | F43: gimnáziumi érettségi | G43: saját tulajdon | H43: 3 | I43: 0 | J43: 56 | K43: utcai | L43: optikus üzletvezető, államigazgatás | M43: 1982 | N43: 1982 | O43: Budapest | P43: 22 | Q43: Budapest (Buda) | R43: 75000 | S43: 75000 | V43: 300000 | W43: Viszonylag könnyen | X43: Népszínház 49. | Y43: 5 | AC43: 35 | AD43: Azt mondja, hogy nem probléma a lakhatási kiadások fedezése (VI) (JAVÍTVA) | AE43: Alföldi utca - Teleki tér | AF43: 0.25 | AG43: FALSE | AH43: 100000 | AI43: érettségi | AJ43: 65 év feletti | AK43: tulajdonos | AL43: 25000 | AM43: idős | AN43: 1990 előtt | AO43: Low | AR43: 1 | AT43: 1 | AU43: 0 | AV43: 0 | AW43: 0 | AY43: 0 | AZ43: 0 | BB43: 0 | BH43: 0 | BJ43: 1 | BR43: 0 | BY43: 0
A44: PCDB01 | B44: Polyák Csaba | C44: Dancs Balázs | D44: 1970 | E44: Nő | F44: főiskolai v. egyetemi diploma | G44: saját tulajdon | H44: 3 | I44: 1 | J44: 53 | K44: udvari | L44: szociális munkás | M44: 2003 | N44: 2003 | O44: Budapest | P44: 11 | Q44: Budapest (Buda) | R44: 188000 | S44: 150000 | U44: 38000 | V44: 650000 | W44: Nehezen | X44: Bauer Sándor utca 19. | Y44: 3 | AA44: zsúfolt, tele kacattal, régies konyha | AB44: elvált nehezen jön ki a pénzéből | AC44: 53 | AE44: Alföldi utca - Teleki tér | AF44: 0.28923077 | AG44: FALSE | AH44: 216666.67 | AI44: diploma | AJ44: 50 és 64 év közötti | AK44: tulajdonos | AL44: 62666.667 | AM44: fiatal tulajdonos | AN44: 1990 és 2016 között | AO44: Middle | AR44: 1 | AS44: 1 | AT44: 1 | AV44: 0.5 | AW44: 1 | BA44: 1 | BB44: 0 | BE44: 0 | BG44: 1 | BJ44: 1 | BO44: 1 | BR44: 0 | BS44: 1 | CA44: 0.5 | CF44: 1 | CJ44: 1
A45: PCGB01 | B45: Polyák Csaba | C45: Gecse Barbara | D45: 1997 | E45: Férfi | F45: főiskolai v. egyetemi diploma | G45: piaci bérlet | H45: 2 | I45: 0 | J45: 80 | K45: utcai | L45: szoftverfejlesztő | M45: 2023 | N45: 2023 | O45: Budapest | P45: 12 | Q45: Budapest (Buda) | R45: 150000 | S45: 30000 | T45: 120000 | V45: 800000 | W45: Viszonylag könnyen | X45: Népszínház 26. | Y45: 2 | AA45: a postán interjúztunk | AC45: 45 | AD45: valszeg kettős származás, tökéletesen beszél magyarul, de a neve és sok angol szó használata, illetve a kiejtése is utal arra, hogy nem csak a magyar az elsődleges nyelve | AE45: Kiss József utca - Nagy Fuvaros utca | AF45: 0.1875 | AG45: FALSE | AH45: 400000 | AI45: diploma | AJ45: 18 és 29 év közötti | AK45: nem tulajdonos | AL45: 75000 | AM45: fiatal bérlő | AN45: 2016 és 2023 között | AO45: High | AP45: 0 | AT45: 0.5 | AU45: 0 | AY45: 1 | BN45: 1 | BO45: 1 | BQ45: 1 | BS45: 1 | BZ45: 1
A46: PCMZ01 | B46: Polyák Csaba | C46: Major Zsuzsi | D46: 1979 | E46: Férfi | F46: főiskolai v. egyetemi diploma | G46: saját tulajdon | H46: 2 | I46: 0 | J46: 99 | K46: utcai | L46: táncművész | M46: 1999 | N46: 1999 | O46: Budapest | P46: 6 | Q46: Budapest (Pest) | R46: 90000 | S46: 45000 | V46: 700000 | W46: Viszonylag könnyen | X46: Népszínház 19. | Y46: 3 | Z46: csanad.kovats@gmail.com | AA46: rendezett környezet, az anyjával él, kulturális életet él, nyitottak | AC46: 40 | AE46: József krt. - Kiss József utca | AF46: 0.12857143 | AG46: FALSE | AH46: 350000 | AI46: diploma | AJ46: 30 és 49 év közötti | AK46: tulajdonos | AL46: 45000 | AM46: fiatal tulajdonos | AN46: 1990 és 2016 között | AO46: Middle
A47: PCMZ02 | B47: Polyák Csaba | C47: Major Zsuzsi | D47: 1952 | E47: Férfi | F47: befejezett 8 osztály | G47: saját tulajdon | H47: 2 | I47: 0 | J47: 78 | K47: udvari | L47: előadóművész | M47: 2013 | N47: 2013 | O47: Budapest | P47: 9 | Q47: Budapest (Pest) | R47: 90000 | S47: 90000 | V47: 500000 | W47: Viszonylag könnyen | X47: Népszínház 26. | Y47: 2 | Z47: csaba.derby@gmail.com | AA47: kulturált lakás, ritkán használja az utcát | AC47: 46 | AE47: Kiss József utca - Nagy Fuvaros utca | AF47: 0.18 | AG47: FALSE | AH47: 250000 | AI47: érettségi alatt | AJ47: 65 év feletti | AK47: tulajdonos | AL47: 45000 | AM47: idős | AN47: 1990 és 2016 között | AO47: Middle | AP47: 0.5 | AS47: 0 | AT47: 1 | AU47: 0 | BE47: 0 | BF47: 0 | BI47: 1 | BN47: 0 | BQ47: 1 | CA47: 0
A48: PCSA01 | B48: Polyák Csaba | C48: Szakály Abigél Noémi | D48: 1952 | E48: Férfi | F48: befejezett 8 osztály | G48: önkormányzati bérlet | H48: 1 | I48: 0 | J48: 30 | K48: udvari | L48: targoncás, kereskedelem | M48: 2000 | N48: 2000 | O48: Budapest | P48: 15 | Q48: Budapest (Pest) | R48: 50000 | S48: 29000 | T48: 19000 | V48: 298000 | W48: Viszonylag könnyen | X48: Népszínház 26. | Y48: 2 | AC48: 43 | AD48: Nyitott új dolgokra, jól megél. 1952 és 76 között a 8. kerületben élt (itt született) majd elköltözött és aztán visszaköltözött a kerületbe 2000ben | AE48: Kiss József utca - Nagy Fuvaros utca | AF48: 0.16778523 | AG48: FALSE | AH48: 298000 | AI48: érettségi alatt | AJ48: 65 év feletti | AK48: nem tulajdonos | AL48: 50000 | AM48: idős | AN48: 1990 és 2016 között | AO48: Middle | AP48: 0 | AT48: 1 | AU48: 0 | AY48: 1 | BA48: 0 | BG48: 0 | BN48: 1 | BP48: 0 | BQ48: 1 | BR48: 0 | CA48: 1
A49: PCSA02 | B49: Polyák Csaba | C49: Szakály Abigél Noémi | D49: 1975 | E49: Férfi | F49: gimnáziumi érettségi | G49: szívességi használat | H49: 1 | I49: 0 | J49: 30 | K49: udvari | L49: vállalkozó, kávézó | M49: 2022 | N49: 2022 | O49: Vác | Q49: Pest megye | R49: 140000 | S49: 40000 | T49: 100000 | V49: 600000 | W49: Nagyon könnyen | X49: Népszínház 57. | Y49: 0 | AA49: zsúfolt lakás, de jó körülmények | AC49: 43 | AE49: Alföldi utca - Teleki tér | AF49: 0.23333333 | AG49: FALSE | AH49: 600000 | AI49: érettségi | AJ49: 30 és 49 év közötti | AK49: nem tulajdonos | AL49: 140000 | AM49: fiatal bérlő | AN49: 2016 és 2023 között | AO49: High | AP49: 1 | AQ49: 1 | AR49: 0 | AS49: 1 | AT49: 1 | AY49: 0.5 | BB49: 1 | BM49: 1 | BN49: 0 | BO49: 0 | BR49: 0 | CA49: 1
A50: SL01 | B50: Szöllősi Luca | D50: 1946 | E50: Nő | F50: főiskolai v. egyetemi diploma | G50: saját tulajdon | H50: 1 | I50: 0 | J50: 69 | K50: utcai | L50: nyugdíjas, főkönyvelő | M50: 1946 | N50: 1946 | Q50: Ide született | R50: 65000 | S50: 65000 | V50: 300000 | W50: Viszonylag könnyen | X50: Népszínház 42-44. | Y50: 3 | AB50: Van egy fényképe, ami 1916-ban készült a házról és látszódik rajta, hogy a homlokzaton 4 oszlop van, ami a 4 évszakot ábrázolja. 1957-ben felújították a házat, és leverték a szobrokat. A hozzá legközelebb lévő szobrot azért döntötték le, mert a bal térdkalácsába befészkelt egy galamb, és ahelyett, hogy kijavították volna, ledöntötték az egészet. | AC50: 53 | AE50: Alföldi utca - Teleki tér | AF50: 0.21666667 | AG50: FALSE | AH50: 300000 | AI50: diploma | AJ50: 65 év feletti | AK50: tulajdonos | AL50: 65000 | AM50: idős | AN50: 1990 előtt | AO50: Middle | AP50: 1 | AQ50: 0 | AR50: 1 | AT50: 1 | AV50: 1 | AY50: 1 | BC50: 1 | BF50: 1 | BJ50: 0 | BQ50: 1 | BS50: 1
A51: SLOD01 | B51: Szöllősi Luca | C51: Osvay Dorottya | D51: 1989 | E51: Férfi | F51: gimnáziumi érettségi | G51: saját tulajdon | H51: 2 | J51: 60 | K51: utcai | L51: vendéglátó | M51: 2024 | N51: 2024 | O51: Budapest | P51: 9 | Q51: Budapest (Pest) | R51: 60000 | V51: 1000000 | W51: Viszonylag könnyen | X51: Népszínház 47. | Y51: 0 | AA51: jól szituált, rendezett, tiszta lakás, cuki fehér cica | AC51: 25 | AE51: Nagy Fuvaros utca - Alföldi utca | AF51: 0.06 | AG51: FALSE | AH51: 500000 | AI51: érettségi | AJ51: 30 és 49 év közötti | AK51: tulajdonos | AL51: 30000 | AM51: fiatal tulajdonos | AN51: utóbbi két évben | AO51: High | AP51: 0 | AT51: 0.5 | AU51: 0 | BE51: 0 | BQ51: 1 | BY51: 0
A52: SLOD02 | B52: Szöllősi Luca | C52: Osvay Dorottya | D52: 1994 | E52: Nő | F52: kevesebb, mint 8 osztály | G52: piaci bérlet | H52: 4 | I52: 2 | J52: 80 | K52: udvari | L52: takarító | N52: 2020 | O52: Budapest | P52: 8 | Q52: Nyolcadik kerület | W52: Nagyon nehezen | X52: Népszínház 47. | Y52: 2 | AC52: 16 | AD52: a párja intézte a lakást, ő gazdálkodik a jövedelmükkel | AE52: Nagy Fuvaros utca - Alföldi utca | AI52: érettségi alatt | AJ52: 30 és 49 év közötti | AK52: nem tulajdonos | AM52: fiatal bérlő | AN52: 2016 és 2023 között | AP52: 1 | AR52: 1 | AT52: 0.5 | BS52: 1
A53: TBJR01 | B53: Tömösvári Barnabás | C53: Jankó Rebeka | D53: 1957 | E53: Férfi | F53: befejezett 8 osztály | G53: saját tulajdon | H53: 2 | I53: 0 | J53: 90 | K53: utcai | L53: kerékpárszerelő | M53: 2015 | N53: 2015 | O53: Budapest | P53: 7 | Q53: Budapest (Pest) | R53: 50000 | S53: 50000 | V53: 200000 | W53: Nehezen | X53: Népszínház 22. | Y53: 2 | AA53: rendezett, jó állapotú gépesített (mosogatógép), sok könyv | AB53: feketén is dolgozik jövedelemkiegészítésként, ezt vsz nem számolta bele a 13. kérdésnél | AC53: 53 | AD53: mikor a végzettséget kérdeztük, somlyogva válaszolt, illetve a volt foglalkozására irányuló kérdésnél is | AE53: József krt. - Kiss József utca | AF53: 0.25 | AG53: FALSE | AH53: 100000 | AI53: érettségi alatt | AJ53: 65 év feletti | AK53: tulajdonos | AL53: 25000 | AM53: idős | AN53: 1990 és 2016 között | AO53: Low | AP53: 1 | AQ53: 0 | AR53: 0.5 | AT53: 1 | AV53: 1 | AY53: 0.5 | BQ53: 1 | BR53: 0 | BY53: 0.66666667
A54: TBOD01 | B54: Tömösvári Barnabás | C54: Osvay Dorottya | D54: 1969 | E54: Férfi | F54: főiskolai v. egyetemi diploma | G54: piaci bérlet | H54: 1 | I54: 0 | J54: 35 | K54: udvari | L54: egyéni vállalkozóként családfakutató, korábban levéltáros, szabadúszó várostörténész | M54: 2024 | N54: 2025 | O54: Budapest | P54: 8 | Q54: Nyolcadik kerület | R54: 200000 | S54: 40000 | T54: 160000 | V54: 400000 | W54: Nehezen | X54: Népszínház 26. | Y54: 0 | AA54: nem voltak a lakásban, állatíólag 4000 könyve van, pici a lakása, nagyon zsúfolt, azért nem ott nem interjúztak mert nem tudta volna őket leültetni mert nincs hely, lexikon az ember, nem hagy helyet interakciónak, nem veled hanem "rád" beszél | AC54: 85 | AE54: Kiss József utca - Nagy Fuvaros utca | AF54: 0.5 | AG54: TRUE | AH54: 400000 | AI54: diploma | AJ54: 50 és 64 év közötti | AK54: nem tulajdonos | AL54: 200000 | AM54: fiatal bérlő | AN54: utóbbi két évben | AO54: High | AT54: 0 | AV54: 0 | BA54: 0 | BB54: 0 | BE54: 0
A55: TBSA01 | B55: Tömösvári Barnabás | C55: Szakály Abigél Noémi | D55: 1981 | E55: Nő | F55: főiskolai v. egyetemi diploma | G55: piaci bérlet | H55: 1 | I55: 0 | J55: 55 | K55: udvari | L55: reptéri dolgozó | M55: 2022 | N55: 2025 | O55: Budapest | P55: 8 | Q55: Nyolcadik kerület | R55: 230000 | S55: 60000 | T55: 170000 | V55: 450000 | W55: Könnyen | X55: Népszínház 42-44. | Y55: 0 | AA55: nemrég költözött (1 hónapja), ennek a nyomai látszódtak, rendezetlen | AC55: 65 | AE55: Alföldi utca - Teleki tér | AF55: 0.51111111 | AG55: TRUE | AH55: 450000 | AI55: diploma | AJ55: 30 és 49 év közötti | AK55: nem tulajdonos | AL55: 230000 | AM55: fiatal bérlő | AN55: utóbbi két évben | AO55: High | AR55: 1 | AT55: 1 | AU55: 1 | AV55: 1 | AY55: 1 | BE55: 1 | BJ55: 1 | BN55: 0.5 | BP55: 1 | BR55: 0 | BT55: 1 | BY55: 1 | BZ55: 0.5 | CA55: 1
A56: TBSA02 | B56: Tömösvári Barnabás | C56: Szakály Abigél Noémi | D56: 1982 | E56: Nő | F56: főiskolai v. egyetemi diploma | G56: saját tulajdon | H56: 1 | I56: 0 | J56: 49 | K56: udvari | L56: biztonsági vezető | M56: 2008 | N56: 2008 | R56: 25000 | S56: 25000 | V56: 850000 | W56: Viszonylag könnyen | X56: Népszínház 42-44. | Y56: 2 | AA56: rendezett, szép lakás, modern berendezés, kutyával | AC56: 21 | AE56: Alföldi utca - Teleki tér | AF56: 0.029411765 | AG56: FALSE | AH56: 850000 | AI56: diploma | AJ56: 30 és 49 év közötti | AK56: tulajdonos | AL56: 25000 | AM56: fiatal tulajdonos | AN56: 1990 és 2016 között | AO56: High | AP56: 1 | AQ56: 1 | AR56: 1 | AT56: 1 | BA56: 1 | BB56: 0 | BD56: 1 | BE56: 1 | BJ56: 1 | BN56: 1 | BQ56: 1 | BR56: 0 | BT56: 1 | CF56: 0.5 | CI56: 1 | CK56: 1
A57: TBSA03 | B57: Tömösvári Barnabás | C57: Szakály Abigél Noémi | D57: 1959 | E57: Nő | F57: szakmunkásképző | G57: saját tulajdon | H57: 2 | I57: 0 | J57: 40 | K57: udvari | L57: cipész | M57: 1993 | N57: 1993 | O57: Budapest | P57: 13 | Q57: Budapest (Pest) | R57: 50000 | S57: 30000 | V57: 250000 | W57: Viszonylag könnyen | X57: Alföldi utca 2. | Y57: 2 | AA57: rendezett, sötét | AB57: a fia nemrég odaköltözött hozzá | AC57: 46 | AE57: Nagy Fuvaros utca - Alföldi utca | AF57: 0.2 | AG57: FALSE | AH57: 125000 | AI57: érettségi alatt | AJ57: 65 év feletti | AK57: tulajdonos | AL57: 25000 | AM57: idős | AN57: 1990 és 2016 között | AO57: Low | AS57: 0 | AT57: 0 | AV57: 0 | AW57: 0.5 | BA57: 1 | BG57: 0 | BH57: 0 | BJ57: 1 | BN57: 0 | BO57: 0 | BP57: 1 | BQ57: 0 | BR57: 0 | CA57: 0 | CB57: 0.5 | CF57: 0 | CI57: 1

Sheet Elemzés - előfordulás
A1: Kódkategória | B1: Kód | C1: Kód konkrétan | D1: Összesen | E1: Férfi | F1: Nő | G1: idős | H1: fiatal tulajdonos | I1: fiatal bérlő
A2: Ideköltözés okai és körülményei | B2: Anyagi | C2: Ideköltözés okai és körülményei - Anyagi | D2: =SUMPRODUCT((INDEX(final_df!$B$2:$ZZ$100,,MATCH(C2,final_df!$B$1:$ZZ$1,0))>0)*1) -> 23 | E2: =SUMPRODUCT((INDEX(final_df!$B$2:$ZZ$100,,MATCH($C2,final_df!$B$1:$ZZ$1,0))>0)*(final_df!$E$2:$E$100=E$1)) -> 16 | F2: =SUMPRODUCT((INDEX(final_df!$B$2:$ZZ$100,,MATCH($C2,final_df!$B$1:$ZZ$1,0))>0)*(final_df!$E$2:$E$100=F$1)) -> 7 | G2: =SUMPRODUCT((INDEX(final_df!$B$2:$ZZ$100,,MATCH($C2,final_df!$B$1:$ZZ$1,0))>0)*(final_df!$AM$2:$AM$100=G$1)) -> 3 | H2: =SUMPRODUCT((INDEX(final_df!$B$2:$ZZ$100,,MATCH($C2,final_df!$B$1:$ZZ$1,0))>0)*(final_df!$AM$2:$AM$100=H$1)) -> 12 | I2: =SUMPRODUCT((INDEX(final_df!$B$2:$ZZ$100,,MATCH($C2,final_df!$B$1:$ZZ$1,0))>0)*(final_df!$AM$2:$AM$100=I$1)) -> 8
B3: Családi / személyes okok | C3: Ideköltözés okai és körülményei - Családi / személyes okok | D3: =SUMPRODUCT((INDEX(final_df!$B$2:$ZZ$100,,MATCH(C3,final_df!$B$1:$ZZ$1,0))>0)*1) -> 28 | E3: =SUMPRODUCT((INDEX(final_df!$B$2:$ZZ$100,,MATCH($C3,final_df!$B$1:$ZZ$1,0))>0)*(final_df!$E$2:$E$100=E$1)) -> 8 | F3: =SUMPRODUCT((INDEX(final_df!$B$2:$ZZ$100,,MATCH($C3,final_df!$B$1:$ZZ$1,0))>0)*(final_df!$E$2:$E$100=F$1)) -> 20 | G3: =SUMPRODUCT((INDEX(final_df!$B$2:$ZZ$100,,MATCH($C3,final_df!$B$1:$ZZ$1,0))>0)*(final_df!$AM$2:$AM$100=G$1)) -> 11 | H3: =SUMPRODUCT((INDEX(final_df!$B$2:$ZZ$100,,MATCH($C3,final_df!$B$1:$ZZ$1,0))>0)*(final_df!$AM$2:$AM$100=H$1)) -> 6 | I3: =SUMPRODUCT((INDEX(final_df!$B$2:$ZZ$100,,MATCH($C3,final_df!$B$1:$ZZ$1,0))>0)*(final_df!$AM$2:$AM$100=I$1)) -> 11
B4: Kulturális | C4: Ideköltözés okai és körülményei - Kulturális | D4: =SUMPRODUCT((INDEX(final_df!$B$2:$ZZ$100,,MATCH(C4,final_df!$B$1:$ZZ$1,0))>0)*1) -> 4 | E4: =SUMPRODUCT((INDEX(final_df!$B$2:$ZZ$100,,MATCH($C4,final_df!$B$1:$ZZ$1,0))>0)*(final_df!$E$2:$E$100=E$1)) -> 2 | F4: =SUMPRODUCT((INDEX(final_df!$B$2:$ZZ$100,,MATCH($C4,final_df!$B$1:$ZZ$1,0))>0)*(final_df!$E$2:$E$100=F$1)) -> 2 | G4: =SUMPRODUCT((INDEX(final_df!$B$2:$ZZ$100,,MATCH($C4,final_df!$B$1:$ZZ$1,0))>0)*(final_df!$AM$2:$AM$100=G$1)) -> 0 | H4: =SUMPRODUCT((INDEX(final_df!$B$2:$ZZ$100,,MATCH($C4,final_df!$B$1:$ZZ$1,0))>0)*(final_df!$AM$2:$AM$100=H$1)) -> 3 | I4: =SUMPRODUCT((INDEX(final_df!$B$2:$ZZ$100,,MATCH($C4,final_df!$B$1:$ZZ$1,0))>0)*(final_df!$AM$2:$AM$100=I$1)) -> 1
B5: Munka / közlekedés | C5: Ideköltözés okai és körülményei - Munka / közlekedés | D5: =SUMPRODUCT((INDEX(final_df!$B$2:$ZZ$100,,MATCH(C5,final_df!$B$1:$ZZ$1,0))>0)*1) -> 15 | E5: =SUMPRODUCT((INDEX(final_df!$B$2:$ZZ$100,,MATCH($C5,final_df!$B$1:$ZZ$1,0))>0)*(final_df!$E$2:$E$100=E$1)) -> 9 | F5: =SUMPRODUCT((INDEX(final_df!$B$2:$ZZ$100,,MATCH($C5,final_df!$B$1:$ZZ$1,0))>0)*(final_df!$E$2:$E$100=F$1)) -> 6 | G5: =SUMPRODUCT((INDEX(final_df!$B$2:$ZZ$100,,MATCH($C5,final_df!$B$1:$ZZ$1,0))>0)*(final_df!$AM$2:$AM$100=G$1)) -> 3 | H5: =SUMPRODUCT((INDEX(final_df!$B$2:$ZZ$100,,MATCH($C5,final_df!$B$1:$ZZ$1,0))>0)*(final_df!$AM$2:$AM$100=H$1)) -> 7 | I5: =SUMPRODUCT((INDEX(final_df!$B$2:$ZZ$100,,MATCH($C5,final_df!$B$1:$ZZ$1,0))>0)*(final_df!$AM$2:$AM$100=I$1)) -> 5
A6: Izgalmas idézet | B6: Csak vicces | C6: Izgalmas idézet - Csak vicces | D6: =SUMPRODUCT((INDEX(final_df!$B$2:$ZZ$100,,MATCH(C6,final_df!$B$1:$ZZ$1,0))>0)*1) -> 29 | E6: =SUMPRODUCT((INDEX(final_df!$B$2:$ZZ$100,,MATCH($C6,final_df!$B$1:$ZZ$1,0))>0)*(final_df!$E$2:$E$100=E$1)) -> 15 | F6: =SUMPRODUCT((INDEX(final_df!$B$2:$ZZ$100,,MATCH($C6,final_df!$B$1:$ZZ$1,0))>0)*(final_df!$E$2:$E$100=F$1)) -> 14 | G6: =SUMPRODUCT((INDEX(final_df!$B$2:$ZZ$100,,MATCH($C6,final_df!$B$1:$ZZ$1,0))>0)*(final_df!$AM$2:$AM$100=G$1)) -> 9 | H6: =SUMPRODUCT((INDEX(final_df!$B$2:$ZZ$100,,MATCH($C6,final_df!$B$1:$ZZ$1,0))>0)*(final_df!$AM$2:$AM$100=H$1)) -> 12 | I6: =SUMPRODUCT((INDEX(final_df!$B$2:$ZZ$100,,MATCH($C6,final_df!$B$1:$ZZ$1,0))>0)*(final_df!$AM$2:$AM$100=I$1)) -> 8
B7: Tanulmányba / kiállíásra | C7: Izgalmas idézet - Tanulmányba / kiállíásra | D7: =SUMPRODUCT((INDEX(final_df!$B$2:$ZZ$100,,MATCH(C7,final_df!$B$1:$ZZ$1,0))>0)*1) -> 36 | E7: =SUMPRODUCT((INDEX(final_df!$B$2:$ZZ$100,,MATCH($C7,final_df!$B$1:$ZZ$1,0))>0)*(final_df!$E$2:$E$100=E$1)) -> 18 | F7: =SUMPRODUCT((INDEX(final_df!$B$2:$ZZ$100,,MATCH($C7,final_df!$B$1:$ZZ$1,0))>0)*(final_df!$E$2:$E$100=F$1)) -> 18 | G7: =SUMPRODUCT((INDEX(final_df!$B$2:$ZZ$100,,MATCH($C7,final_df!$B$1:$ZZ$1,0))>0)*(final_df!$AM$2:$AM$100=G$1)) -> 12 | H7: =SUMPRODUCT((INDEX(final_df!$B$2:$ZZ$100,,MATCH($C7,final_df!$B$1:$ZZ$1,0))>0)*(final_df!$AM$2:$AM$100=H$1)) -> 14 | I7: =SUMPRODUCT((INDEX(final_df!$B$2:$ZZ$100,,MATCH($C7,final_df!$B$1:$ZZ$1,0))>0)*(final_df!$AM$2:$AM$100=I$1)) -> 10
A8: Jövőkép a társasházról | B8: Általános jövőkép | C8: Jövőkép a társasházról - Általános jövőkép | D8: =SUMPRODUCT((INDEX(final_df!$B$2:$ZZ$100,,MATCH(C8,final_df!$B$1:$ZZ$1,0))>0)*1) -> 14 | E8: =SUMPRODUCT((INDEX(final_df!$B$2:$ZZ$100,,MATCH($C8,final_df!$B$1:$ZZ$1,0))>0)*(final_df!$E$2:$E$100=E$1)) -> 7 | F8: =SUMPRODUCT((INDEX(final_df!$B$2:$ZZ$100,,MATCH($C8,final_df!$B$1:$ZZ$1,0))>0)*(final_df!$E$2:$E$100=F$1)) -> 7 | G8: =SUMPRODUCT((INDEX(final_df!$B$2:$ZZ$100,,MATCH($C8,final_df!$B$1:$ZZ$1,0))>0)*(final_df!$AM$2:$AM$100=G$1)) -> 7 | H8: =SUMPRODUCT((INDEX(final_df!$B$2:$ZZ$100,,MATCH($C8,final_df!$B$1:$ZZ$1,0))>0)*(final_df!$AM$2:$AM$100=H$1)) -> 6 | I8: =SUMPRODUCT((INDEX(final_df!$B$2:$ZZ$100,,MATCH($C8,final_df!$B$1:$ZZ$1,0))>0)*(final_df!$AM$2:$AM$100=I$1)) -> 1
B9: Közös képviselet szerepe | C9: Jövőkép a társasházról - Közös képviselet szerepe | D9: =SUMPRODUCT((INDEX(final_df!$B$2:$ZZ$100,,MATCH(C9,final_df!$B$1:$ZZ$1,0))>0)*1) -> 5 | E9: =SUMPRODUCT((INDEX(final_df!$B$2:$ZZ$100,,MATCH($C9,final_df!$B$1:$ZZ$1,0))>0)*(final_df!$E$2:$E$100=E$1)) -> 1 | F9: =SUMPRODUCT((INDEX(final_df!$B$2:$ZZ$100,,MATCH($C9,final_df!$B$1:$ZZ$1,0))>0)*(final_df!$E$2:$E$100=F$1)) -> 4 | G9: =SUMPRODUCT((INDEX(final_df!$B$2:$ZZ$100,,MATCH($C9,final_df!$B$1:$ZZ$1,0))>0)*(final_df!$AM$2:$AM$100=G$1)) -> 3 | H9: =SUMPRODUCT((INDEX(final_df!$B$2:$ZZ$100,,MATCH($C9,final_df!$B$1:$ZZ$1,0))>0)*(final_df!$AM$2:$AM$100=H$1)) -> 2 | I9: =SUMPRODUCT((INDEX(final_df!$B$2:$ZZ$100,,MATCH($C9,final_df!$B$1:$ZZ$1,0))>0)*(final_df!$AM$2:$AM$100=I$1)) -> 0
B10: Lakóközösség cseréje | C10: Jövőkép a társasházról - Lakóközösség cseréje | D10: =SUMPRODUCT((INDEX(final_df!$B$2:$ZZ$100,,MATCH(C10,final_df!$B$1:$ZZ$1,0))>0)*1) -> 15 | E10: =SUMPRODUCT((INDEX(final_df!$B$2:$ZZ$100,,MATCH($C10,final_df!$B$1:$ZZ$1,0))>0)*(final_df!$E$2:$E$100=E$1)) -> 9 | F10: =SUMPRODUCT((INDEX(final_df!$B$2:$ZZ$100,,MATCH($C10,final_df!$B$1:$ZZ$1,0))>0)*(final_df!$E$2:$E$100=F$1)) -> 6 | G10: =SUMPRODUCT((INDEX(final_df!$B$2:$ZZ$100,,MATCH($C10,final_df!$B$1:$ZZ$1,0))>0)*(final_df!$AM$2:$AM$100=G$1)) -> 4 | H10: =SUMPRODUCT((INDEX(final_df!$B$2:$ZZ$100,,MATCH($C10,final_df!$B$1:$ZZ$1,0))>0)*(final_df!$AM$2:$AM$100=H$1)) -> 7 | I10: =SUMPRODUCT((INDEX(final_df!$B$2:$ZZ$100,,MATCH($C10,final_df!$B$1:$ZZ$1,0))>0)*(final_df!$AM$2:$AM$100=I$1)) -> 4
B11: Lakóközösség szerepe | C11: Jövőkép a társasházról - Lakóközösség szerepe | D11: =SUMPRODUCT((INDEX(final_df!$B$2:$ZZ$100,,MATCH(C11,final_df!$B$1:$ZZ$1,0))>0)*1) -> 8 | E11: =SUMPRODUCT((INDEX(final_df!$B$2:$ZZ$100,,MATCH($C11,final_df!$B$1:$ZZ$1,0))>0)*(final_df!$E$2:$E$100=E$1)) -> 5 | F11: =SUMPRODUCT((INDEX(final_df!$B$2:$ZZ$100,,MATCH($C11,final_df!$B$1:$ZZ$1,0))>0)*(final_df!$E$2:$E$100=F$1)) -> 3 | G11: =SUMPRODUCT((INDEX(final_df!$B$2:$ZZ$100,,MATCH($C11,final_df!$B$1:$ZZ$1,0))>0)*(final_df!$AM$2:$AM$100=G$1)) -> 2 | H11: =SUMPRODUCT((INDEX(final_df!$B$2:$ZZ$100,,MATCH($C11,final_df!$B$1:$ZZ$1,0))>0)*(final_df!$AM$2:$AM$100=H$1)) -> 2 | I11: =SUMPRODUCT((INDEX(final_df!$B$2:$ZZ$100,,MATCH($C11,final_df!$B$1:$ZZ$1,0))>0)*(final_df!$AM$2:$AM$100=I$1)) -> 4
B12: Változtatná a társasházon | C12: Jövőkép a társasházról - Változtatná a társasházon | D12: =SUMPRODUCT((INDEX(final_df!$B$2:$ZZ$100,,MATCH(C12,final_df!$B$1:$ZZ$1,0))>0)*1) -> 29 | E12: =SUMPRODUCT((INDEX(final_df!$B$2:$ZZ$100,,MATCH($C12,final_df!$B$1:$ZZ$1,0))>0)*(final_df!$E$2:$E$100=E$1)) -> 16 | F12: =SUMPRODUCT((INDEX(final_df!$B$2:$ZZ$100,,MATCH($C12,final_df!$B$1:$ZZ$1,0))>0)*(final_df!$E$2:$E$100=F$1)) -> 13 | G12: =SUMPRODUCT((INDEX(final_df!$B$2:$ZZ$100,,MATCH($C12,final_df!$B$1:$ZZ$1,0))>0)*(final_df!$AM$2:$AM$100=G$1)) -> 8 | H12: =SUMPRODUCT((INDEX(final_df!$B$2:$ZZ$100,,MATCH($C12,final_df!$B$1:$ZZ$1,0))>0)*(final_df!$AM$2:$AM$100=H$1)) -> 10 | I12: =SUMPRODUCT((INDEX(final_df!$B$2:$ZZ$100,,MATCH($C12,final_df!$B$1:$ZZ$1,0))>0)*(final_df!$AM$2:$AM$100=I$1)) -> 11
A13: Jövőkép az utcáról | B13: Jövőkép az utcáról | C13: Jövőkép az utcáról - Jövőkép az utcáról | D13: =SUMPRODUCT((INDEX(final_df!$B$2:$ZZ$100,,MATCH(C13,final_df!$B$1:$ZZ$1,0))>0)*1) -> 31 | E13: =SUMPRODUCT((INDEX(final_df!$B$2:$ZZ$100,,MATCH($C13,final_df!$B$1:$ZZ$1,0))>0)*(final_df!$E$2:$E$100=E$1)) -> 14 | F13: =SUMPRODUCT((INDEX(final_df!$B$2:$ZZ$100,,MATCH($C13,final_df!$B$1:$ZZ$1,0))>0)*(final_df!$E$2:$E$100=F$1)) -> 17 | G13: =SUMPRODUCT((INDEX(final_df!$B$2:$ZZ$100,,MATCH($C13,final_df!$B$1:$ZZ$1,0))>0)*(final_df!$AM$2:$AM$100=G$1)) -> 5 | H13: =SUMPRODUCT((INDEX(final_df!$B$2:$ZZ$100,,MATCH($C13,final_df!$B$1:$ZZ$1,0))>0)*(final_df!$AM$2:$AM$100=H$1)) -> 13 | I13: =SUMPRODUCT((INDEX(final_df!$B$2:$ZZ$100,,MATCH($C13,final_df!$B$1:$ZZ$1,0))>0)*(final_df!$AM$2:$AM$100=I$1)) -> 13
A14: Lakhatási helyzet | B14: Elhelyezkedés | C14: Lakhatási helyzet - Elhelyezkedés | D14: =SUMPRODUCT((INDEX(final_df!$B$2:$ZZ$100,,MATCH(C14,final_df!$B$1:$ZZ$1,0))>0)*1) -> 10 | E14: =SUMPRODUCT((INDEX(final_df!$B$2:$ZZ$100,,MATCH($C14,final_df!$B$1:$ZZ$1,0))>0)*(final_df!$E$2:$E$100=E$1)) -> 4 | F14: =SUMPRODUCT((INDEX(final_df!$B$2:$ZZ$100,,MATCH($C14,final_df!$B$1:$ZZ$1,0))>0)*(final_df!$E$2:$E$100=F$1)) -> 6 | G14: =SUMPRODUCT((INDEX(final_df!$B$2:$ZZ$100,,MATCH($C14,final_df!$B$1:$ZZ$1,0))>0)*(final_df!$AM$2:$AM$100=G$1)) -> 2 | H14: =SUMPRODUCT((INDEX(final_df!$B$2:$ZZ$100,,MATCH($C14,final_df!$B$1:$ZZ$1,0))>0)*(final_df!$AM$2:$AM$100=H$1)) -> 4 | I14: =SUMPRODUCT((INDEX(final_df!$B$2:$ZZ$100,,MATCH($C14,final_df!$B$1:$ZZ$1,0))>0)*(final_df!$AM$2:$AM$100=I$1)) -> 4
B15: Komfortszint | C15: Lakhatási helyzet - Komfortszint | D15: =SUMPRODUCT((INDEX(final_df!$B$2:$ZZ$100,,MATCH(C15,final_df!$B$1:$ZZ$1,0))>0)*1) -> 19 | E15: =SUMPRODUCT((INDEX(final_df!$B$2:$ZZ$100,,MATCH($C15,final_df!$B$1:$ZZ$1,0))>0)*(final_df!$E$2:$E$100=E$1)) -> 8 | F15: =SUMPRODUCT((INDEX(final_df!$B$2:$ZZ$100,,MATCH($C15,final_df!$B$1:$ZZ$1,0))>0)*(final_df!$E$2:$E$100=F$1)) -> 11 | G15: =SUMPRODUCT((INDEX(final_df!$B$2:$ZZ$100,,MATCH($C15,final_df!$B$1:$ZZ$1,0))>0)*(final_df!$AM$2:$AM$100=G$1)) -> 4 | H15: =SUMPRODUCT((INDEX(final_df!$B$2:$ZZ$100,,MATCH($C15,final_df!$B$1:$ZZ$1,0))>0)*(final_df!$AM$2:$AM$100=H$1)) -> 6 | I15: =SUMPRODUCT((INDEX(final_df!$B$2:$ZZ$100,,MATCH($C15,final_df!$B$1:$ZZ$1,0))>0)*(final_df!$AM$2:$AM$100=I$1)) -> 9
A16: Önkormányzati szerep | B16: Jelenleg | C16: Önkormányzati szerep - Jelenleg | D16: =SUMPRODUCT((INDEX(final_df!$B$2:$ZZ$100,,MATCH(C16,final_df!$B$1:$ZZ$1,0))>0)*1) -> 21 | E16: =SUMPRODUCT((INDEX(final_df!$B$2:$ZZ$100,,MATCH($C16,final_df!$B$1:$ZZ$1,0))>0)*(final_df!$E$2:$E$100=E$1)) -> 7 | F16: =SUMPRODUCT((INDEX(final_df!$B$2:$ZZ$100,,MATCH($C16,final_df!$B$1:$ZZ$1,0))>0)*(final_df!$E$2:$E$100=F$1)) -> 14 | G16: =SUMPRODUCT((INDEX(final_df!$B$2:$ZZ$100,,MATCH($C16,final_df!$B$1:$ZZ$1,0))>0)*(final_df!$AM$2:$AM$100=G$1)) -> 10 | H16: =SUMPRODUCT((INDEX(final_df!$B$2:$ZZ$100,,MATCH($C16,final_df!$B$1:$ZZ$1,0))>0)*(final_df!$AM$2:$AM$100=H$1)) -> 7 | I16: =SUMPRODUCT((INDEX(final_df!$B$2:$ZZ$100,,MATCH($C16,final_df!$B$1:$ZZ$1,0))>0)*(final_df!$AM$2:$AM$100=I$1)) -> 4
B17: Jövőre - Társasháznál | C17: Önkormányzati szerep - Jövőre - Társasháznál | D17: =SUMPRODUCT((INDEX(final_df!$B$2:$ZZ$100,,MATCH(C17,final_df!$B$1:$ZZ$1,0))>0)*1) -> 4 | E17: =SUMPRODUCT((INDEX(final_df!$B$2:$ZZ$100,,MATCH($C17,final_df!$B$1:$ZZ$1,0))>0)*(final_df!$E$2:$E$100=E$1)) -> 2 | F17: =SUMPRODUCT((INDEX(final_df!$B$2:$ZZ$100,,MATCH($C17,final_df!$B$1:$ZZ$1,0))>0)*(final_df!$E$2:$E$100=F$1)) -> 2 | G17: =SUMPRODUCT((INDEX(final_df!$B$2:$ZZ$100,,MATCH($C17,final_df!$B$1:$ZZ$1,0))>0)*(final_df!$AM$2:$AM$100=G$1)) -> 2 | H17: =SUMPRODUCT((INDEX(final_df!$B$2:$ZZ$100,,MATCH($C17,final_df!$B$1:$ZZ$1,0))>0)*(final_df!$AM$2:$AM$100=H$1)) -> 1 | I17: =SUMPRODUCT((INDEX(final_df!$B$2:$ZZ$100,,MATCH($C17,final_df!$B$1:$ZZ$1,0))>0)*(final_df!$AM$2:$AM$100=I$1)) -> 1
B18: Jövőre - Utcánál | C18: Önkormányzati szerep - Jövőre - Utcánál | D18: =SUMPRODUCT((INDEX(final_df!$B$2:$ZZ$100,,MATCH(C18,final_df!$B$1:$ZZ$1,0))>0)*1) -> 14 | E18: =SUMPRODUCT((INDEX(final_df!$B$2:$ZZ$100,,MATCH($C18,final_df!$B$1:$ZZ$1,0))>0)*(final_df!$E$2:$E$100=E$1)) -> 7 | F18: =SUMPRODUCT((INDEX(final_df!$B$2:$ZZ$100,,MATCH($C18,final_df!$B$1:$ZZ$1,0))>0)*(final_df!$E$2:$E$100=F$1)) -> 7 | G18: =SUMPRODUCT((INDEX(final_df!$B$2:$ZZ$100,,MATCH($C18,final_df!$B$1:$ZZ$1,0))>0)*(final_df!$AM$2:$AM$100=G$1)) -> 5 | H18: =SUMPRODUCT((INDEX(final_df!$B$2:$ZZ$100,,MATCH($C18,final_df!$B$1:$ZZ$1,0))>0)*(final_df!$AM$2:$AM$100=H$1)) -> 7 | I18: =SUMPRODUCT((INDEX(final_df!$B$2:$ZZ$100,,MATCH($C18,final_df!$B$1:$ZZ$1,0))>0)*(final_df!$AM$2:$AM$100=I$1)) -> 2
A19: Pozitív / Negatív | B19: Negatív | C19: Pozitív / Negatív - Negatív | D19: =SUMPRODUCT((INDEX(final_df!$B$2:$ZZ$100,,MATCH(C19,final_df!$B$1:$ZZ$1,0))>0)*1) -> 53 | E19: =SUMPRODUCT((INDEX(final_df!$B$2:$ZZ$100,,MATCH($C19,final_df!$B$1:$ZZ$1,0))>0)*(final_df!$E$2:$E$100=E$1)) -> 27 | F19: =SUMPRODUCT((INDEX(final_df!$B$2:$ZZ$100,,MATCH($C19,final_df!$B$1:$ZZ$1,0))>0)*(final_df!$E$2:$E$100=F$1)) -> 26 | G19: =SUMPRODUCT((INDEX(final_df!$B$2:$ZZ$100,,MATCH($C19,final_df!$B$1:$ZZ$1,0))>0)*(final_df!$AM$2:$AM$100=G$1)) -> 17 | H19: =SUMPRODUCT((INDEX(final_df!$B$2:$ZZ$100,,MATCH($C19,final_df!$B$1:$ZZ$1,0))>0)*(final_df!$AM$2:$AM$100=H$1)) -> 18 | I19: =SUMPRODUCT((INDEX(final_df!$B$2:$ZZ$100,,MATCH($C19,final_df!$B$1:$ZZ$1,0))>0)*(final_df!$AM$2:$AM$100=I$1)) -> 18
B20: Pozitív | C20: Pozitív / Negatív - Pozitív | D20: =SUMPRODUCT((INDEX(final_df!$B$2:$ZZ$100,,MATCH(C20,final_df!$B$1:$ZZ$1,0))>0)*1) -> 54 | E20: =SUMPRODUCT((INDEX(final_df!$B$2:$ZZ$100,,MATCH($C20,final_df!$B$1:$ZZ$1,0))>0)*(final_df!$E$2:$E$100=E$1)) -> 26 | F20: =SUMPRODUCT((INDEX(final_df!$B$2:$ZZ$100,,MATCH($C20,final_df!$B$1:$ZZ$1,0))>0)*(final_df!$E$2:$E$100=F$1)) -> 28 | G20: =SUMPRODUCT((INDEX(final_df!$B$2:$ZZ$100,,MATCH($C20,final_df!$B$1:$ZZ$1,0))>0)*(final_df!$AM$2:$AM$100=G$1)) -> 18 | H20: =SUMPRODUCT((INDEX(final_df!$B$2:$ZZ$100,,MATCH($C20,final_df!$B$1:$ZZ$1,0))>0)*(final_df!$AM$2:$AM$100=H$1)) -> 18 | I20: =SUMPRODUCT((INDEX(final_df!$B$2:$ZZ$100,,MATCH($C20,final_df!$B$1:$ZZ$1,0))>0)*(final_df!$AM$2:$AM$100=I$1)) -> 18
A21: Társasházak működése (jelenleg) | B21: Biztonság | C21: Társasházak működése (jelenleg) - Biztonság | D21: =SUMPRODUCT((INDEX(final_df!$B$2:$ZZ$100,,MATCH(C21,final_df!$B$1:$ZZ$1,0))>0)*1) -> 25 | E21: =SUMPRODUCT((INDEX(final_df!$B$2:$ZZ$100,,MATCH($C21,final_df!$B$1:$ZZ$1,0))>0)*(final_df!$E$2:$E$100=E$1)) -> 11 | F21: =SUMPRODUCT((INDEX(final_df!$B$2:$ZZ$100,,MATCH($C21,final_df!$B$1:$ZZ$1,0))>0)*(final_df!$E$2:$E$100=F$1)) -> 14 | G21: =SUMPRODUCT((INDEX(final_df!$B$2:$ZZ$100,,MATCH($C21,final_df!$B$1:$ZZ$1,0))>0)*(final_df!$AM$2:$AM$100=G$1)) -> 6 | H21: =SUMPRODUCT((INDEX(final_df!$B$2:$ZZ$100,,MATCH($C21,final_df!$B$1:$ZZ$1,0))>0)*(final_df!$AM$2:$AM$100=H$1)) -> 12 | I21: =SUMPRODUCT((INDEX(final_df!$B$2:$ZZ$100,,MATCH($C21,final_df!$B$1:$ZZ$1,0))>0)*(final_df!$AM$2:$AM$100=I$1)) -> 7
B22: Fizikai állapot / karbantartás | C22: Társasházak működése (jelenleg) - Fizikai állapot / karbantartás | D22: =SUMPRODUCT((INDEX(final_df!$B$2:$ZZ$100,,MATCH(C22,final_df!$B$1:$ZZ$1,0))>0)*1) -> 42 | E22: =SUMPRODUCT((INDEX(final_df!$B$2:$ZZ$100,,MATCH($C22,final_df!$B$1:$ZZ$1,0))>0)*(final_df!$E$2:$E$100=E$1)) -> 21 | F22: =SUMPRODUCT((INDEX(final_df!$B$2:$ZZ$100,,MATCH($C22,final_df!$B$1:$ZZ$1,0))>0)*(final_df!$E$2:$E$100=F$1)) -> 21 | G22: =SUMPRODUCT((INDEX(final_df!$B$2:$ZZ$100,,MATCH($C22,final_df!$B$1:$ZZ$1,0))>0)*(final_df!$AM$2:$AM$100=G$1)) -> 16 | H22: =SUMPRODUCT((INDEX(final_df!$B$2:$ZZ$100,,MATCH($C22,final_df!$B$1:$ZZ$1,0))>0)*(final_df!$AM$2:$AM$100=H$1)) -> 14 | I22: =SUMPRODUCT((INDEX(final_df!$B$2:$ZZ$100,,MATCH($C22,final_df!$B$1:$ZZ$1,0))>0)*(final_df!$AM$2:$AM$100=I$1)) -> 12
B23: Közös képviselet | C23: Társasházak működése (jelenleg) - Közös képviselet | D23: =SUMPRODUCT((INDEX(final_df!$B$2:$ZZ$100,,MATCH(C23,final_df!$B$1:$ZZ$1,0))>0)*1) -> 28 | E23: =SUMPRODUCT((INDEX(final_df!$B$2:$ZZ$100,,MATCH($C23,final_df!$B$1:$ZZ$1,0))>0)*(final_df!$E$2:$E$100=E$1)) -> 13 | F23: =SUMPRODUCT((INDEX(final_df!$B$2:$ZZ$100,,MATCH($C23,final_df!$B$1:$ZZ$1,0))>0)*(final_df!$E$2:$E$100=F$1)) -> 15 | G23: =SUMPRODUCT((INDEX(final_df!$B$2:$ZZ$100,,MATCH($C23,final_df!$B$1:$ZZ$1,0))>0)*(final_df!$AM$2:$AM$100=G$1)) -> 10 | H23: =SUMPRODUCT((INDEX(final_df!$B$2:$ZZ$100,,MATCH($C23,final_df!$B$1:$ZZ$1,0))>0)*(final_df!$AM$2:$AM$100=H$1)) -> 13 | I23: =SUMPRODUCT((INDEX(final_df!$B$2:$ZZ$100,,MATCH($C23,final_df!$B$1:$ZZ$1,0))>0)*(final_df!$AM$2:$AM$100=I$1)) -> 5
B24: Közös terek használata | C24: Társasházak működése (jelenleg) - Közös terek használata | D24: =SUMPRODUCT((INDEX(final_df!$B$2:$ZZ$100,,MATCH(C24,final_df!$B$1:$ZZ$1,0))>0)*1) -> 15 | E24: =SUMPRODUCT((INDEX(final_df!$B$2:$ZZ$100,,MATCH($C24,final_df!$B$1:$ZZ$1,0))>0)*(final_df!$E$2:$E$100=E$1)) -> 10 | F24: =SUMPRODUCT((INDEX(final_df!$B$2:$ZZ$100,,MATCH($C24,final_df!$B$1:$ZZ$1,0))>0)*(final_df!$E$2:$E$100=F$1)) -> 5 | G24: =SUMPRODUCT((INDEX(final_df!$B$2:$ZZ$100,,MATCH($C24,final_df!$B$1:$ZZ$1,0))>0)*(final_df!$AM$2:$AM$100=G$1)) -> 4 | H24: =SUMPRODUCT((INDEX(final_df!$B$2:$ZZ$100,,MATCH($C24,final_df!$B$1:$ZZ$1,0))>0)*(final_df!$AM$2:$AM$100=H$1)) -> 5 | I24: =SUMPRODUCT((INDEX(final_df!$B$2:$ZZ$100,,MATCH($C24,final_df!$B$1:$ZZ$1,0))>0)*(final_df!$AM$2:$AM$100=I$1)) -> 6
B25: Közösségi élet | C25: Társasházak működése (jelenleg) - Közösségi élet | D25: =SUMPRODUCT((INDEX(final_df!$B$2:$ZZ$100,,MATCH(C25,final_df!$B$1:$ZZ$1,0))>0)*1) -> 39 | E25: =SUMPRODUCT((INDEX(final_df!$B$2:$ZZ$100,,MATCH($C25,final_df!$B$1:$ZZ$1,0))>0)*(final_df!$E$2:$E$100=E$1)) -> 16 | F25: =SUMPRODUCT((INDEX(final_df!$B$2:$ZZ$100,,MATCH($C25,final_df!$B$1:$ZZ$1,0))>0)*(final_df!$E$2:$E$100=F$1)) -> 23 | G25: =SUMPRODUCT((INDEX(final_df!$B$2:$ZZ$100,,MATCH($C25,final_df!$B$1:$ZZ$1,0))>0)*(final_df!$AM$2:$AM$100=G$1)) -> 12 | H25: =SUMPRODUCT((INDEX(final_df!$B$2:$ZZ$100,,MATCH($C25,final_df!$B$1:$ZZ$1,0))>0)*(final_df!$AM$2:$AM$100=H$1)) -> 14 | I25: =SUMPRODUCT((INDEX(final_df!$B$2:$ZZ$100,,MATCH($C25,final_df!$B$1:$ZZ$1,0))>0)*(final_df!$AM$2:$AM$100=I$1)) -> 13
B26: Lakóközösség változása | C26: Társasházak működése (jelenleg) - Lakóközösség változása | D26: =SUMPRODUCT((INDEX(final_df!$B$2:$ZZ$100,,MATCH(C26,final_df!$B$1:$ZZ$1,0))>0)*1) -> 32 | E26: =SUMPRODUCT((INDEX(final_df!$B$2:$ZZ$100,,MATCH($C26,final_df!$B$1:$ZZ$1,0))>0)*(final_df!$E$2:$E$100=E$1)) -> 16 | F26: =SUMPRODUCT((INDEX(final_df!$B$2:$ZZ$100,,MATCH($C26,final_df!$B$1:$ZZ$1,0))>0)*(final_df!$E$2:$E$100=F$1)) -> 16 | G26: =SUMPRODUCT((INDEX(final_df!$B$2:$ZZ$100,,MATCH($C26,final_df!$B$1:$ZZ$1,0))>0)*(final_df!$AM$2:$AM$100=G$1)) -> 12 | H26: =SUMPRODUCT((INDEX(final_df!$B$2:$ZZ$100,,MATCH($C26,final_df!$B$1:$ZZ$1,0))>0)*(final_df!$AM$2:$AM$100=H$1)) -> 14 | I26: =SUMPRODUCT((INDEX(final_df!$B$2:$ZZ$100,,MATCH($C26,final_df!$B$1:$ZZ$1,0))>0)*(final_df!$AM$2:$AM$100=I$1)) -> 6
A27: Utca változásai | B27: Fizikai környezet és utcakép változásai | C27: Utca változásai - Fizikai környezet és utcakép változásai | D27: =SUMPRODUCT((INDEX(final_df!$B$2:$ZZ$100,,MATCH(C27,final_df!$B$1:$ZZ$1,0))>0)*1) -> 25 | E27: =SUMPRODUCT((INDEX(final_df!$B$2:$ZZ$100,,MATCH($C27,final_df!$B$1:$ZZ$1,0))>0)*(final_df!$E$2:$E$100=E$1)) -> 13 | F27: =SUMPRODUCT((INDEX(final_df!$B$2:$ZZ$100,,MATCH($C27,final_df!$B$1:$ZZ$1,0))>0)*(final_df!$E$2:$E$100=F$1)) -> 12 | G27: =SUMPRODUCT((INDEX(final_df!$B$2:$ZZ$100,,MATCH($C27,final_df!$B$1:$ZZ$1,0))>0)*(final_df!$AM$2:$AM$100=G$1)) -> 9 | H27: =SUMPRODUCT((INDEX(final_df!$B$2:$ZZ$100,,MATCH($C27,final_df!$B$1:$ZZ$1,0))>0)*(final_df!$AM$2:$AM$100=H$1)) -> 10 | I27: =SUMPRODUCT((INDEX(final_df!$B$2:$ZZ$100,,MATCH($C27,final_df!$B$1:$ZZ$1,0))>0)*(final_df!$AM$2:$AM$100=I$1)) -> 6
B28: Közbiztonság és közterületi viselkedés | C28: Utca változásai - Közbiztonság és közterületi viselkedés | D28: =SUMPRODUCT((INDEX(final_df!$B$2:$ZZ$100,,MATCH(C28,final_df!$B$1:$ZZ$1,0))>0)*1) -> 18 | E28: =SUMPRODUCT((INDEX(final_df!$B$2:$ZZ$100,,MATCH($C28,final_df!$B$1:$ZZ$1,0))>0)*(final_df!$E$2:$E$100=E$1)) -> 8 | F28: =SUMPRODUCT((INDEX(final_df!$B$2:$ZZ$100,,MATCH($C28,final_df!$B$1:$ZZ$1,0))>0)*(final_df!$E$2:$E$100=F$1)) -> 10 | G28: =SUMPRODUCT((INDEX(final_df!$B$2:$ZZ$100,,MATCH($C28,final_df!$B$1:$ZZ$1,0))>0)*(final_df!$AM$2:$AM$100=G$1)) -> 7 | H28: =SUMPRODUCT((INDEX(final_df!$B$2:$ZZ$100,,MATCH($C28,final_df!$B$1:$ZZ$1,0))>0)*(final_df!$AM$2:$AM$100=H$1)) -> 6 | I28: =SUMPRODUCT((INDEX(final_df!$B$2:$ZZ$100,,MATCH($C28,final_df!$B$1:$ZZ$1,0))>0)*(final_df!$AM$2:$AM$100=I$1)) -> 5
B29: Lakossági összetétel / közösségek | C29: Utca változásai - Lakossági összetétel / közösségek | D29: =SUMPRODUCT((INDEX(final_df!$B$2:$ZZ$100,,MATCH(C29,final_df!$B$1:$ZZ$1,0))>0)*1) -> 23 | E29: =SUMPRODUCT((INDEX(final_df!$B$2:$ZZ$100,,MATCH($C29,final_df!$B$1:$ZZ$1,0))>0)*(final_df!$E$2:$E$100=E$1)) -> 8 | F29: =SUMPRODUCT((INDEX(final_df!$B$2:$ZZ$100,,MATCH($C29,final_df!$B$1:$ZZ$1,0))>0)*(final_df!$E$2:$E$100=F$1)) -> 15 | G29: =SUMPRODUCT((INDEX(final_df!$B$2:$ZZ$100,,MATCH($C29,final_df!$B$1:$ZZ$1,0))>0)*(final_df!$AM$2:$AM$100=G$1)) -> 10 | H29: =SUMPRODUCT((INDEX(final_df!$B$2:$ZZ$100,,MATCH($C29,final_df!$B$1:$ZZ$1,0))>0)*(final_df!$AM$2:$AM$100=H$1)) -> 8 | I29: =SUMPRODUCT((INDEX(final_df!$B$2:$ZZ$100,,MATCH($C29,final_df!$B$1:$ZZ$1,0))>0)*(final_df!$AM$2:$AM$100=I$1)) -> 5
B30: Üzletek / szolgáltatások / vendéglátás | C30: Utca változásai - Üzletek / szolgáltatások / vendéglátás | D30: =SUMPRODUCT((INDEX(final_df!$B$2:$ZZ$100,,MATCH(C30,final_df!$B$1:$ZZ$1,0))>0)*1) -> 23 | E30: =SUMPRODUCT((INDEX(final_df!$B$2:$ZZ$100,,MATCH($C30,final_df!$B$1:$ZZ$1,0))>0)*(final_df!$E$2:$E$100=E$1)) -> 9 | F30: =SUMPRODUCT((INDEX(final_df!$B$2:$ZZ$100,,MATCH($C30,final_df!$B$1:$ZZ$1,0))>0)*(final_df!$E$2:$E$100=F$1)) -> 14 | G30: =SUMPRODUCT((INDEX(final_df!$B$2:$ZZ$100,,MATCH($C30,final_df!$B$1:$ZZ$1,0))>0)*(final_df!$AM$2:$AM$100=G$1)) -> 9 | H30: =SUMPRODUCT((INDEX(final_df!$B$2:$ZZ$100,,MATCH($C30,final_df!$B$1:$ZZ$1,0))>0)*(final_df!$AM$2:$AM$100=H$1)) -> 10 | I30: =SUMPRODUCT((INDEX(final_df!$B$2:$ZZ$100,,MATCH($C30,final_df!$B$1:$ZZ$1,0))>0)*(final_df!$AM$2:$AM$100=I$1)) -> 4
A31: Utcahasználat (jelenleg) | B31: Közlekedési élmények | C31: Utcahasználat (jelenleg) - Közlekedési élmények | D31: =SUMPRODUCT((INDEX(final_df!$B$2:$ZZ$100,,MATCH(C31,final_df!$B$1:$ZZ$1,0))>0)*1) -> 29 | E31: =SUMPRODUCT((INDEX(final_df!$B$2:$ZZ$100,,MATCH($C31,final_df!$B$1:$ZZ$1,0))>0)*(final_df!$E$2:$E$100=E$1)) -> 13 | F31: =SUMPRODUCT((INDEX(final_df!$B$2:$ZZ$100,,MATCH($C31,final_df!$B$1:$ZZ$1,0))>0)*(final_df!$E$2:$E$100=F$1)) -> 16 | G31: =SUMPRODUCT((INDEX(final_df!$B$2:$ZZ$100,,MATCH($C31,final_df!$B$1:$ZZ$1,0))>0)*(final_df!$AM$2:$AM$100=G$1)) -> 9 | H31: =SUMPRODUCT((INDEX(final_df!$B$2:$ZZ$100,,MATCH($C31,final_df!$B$1:$ZZ$1,0))>0)*(final_df!$AM$2:$AM$100=H$1)) -> 11 | I31: =SUMPRODUCT((INDEX(final_df!$B$2:$ZZ$100,,MATCH($C31,final_df!$B$1:$ZZ$1,0))>0)*(final_df!$AM$2:$AM$100=I$1)) -> 9
B32: Közösségi interakciók az utcán | C32: Utcahasználat (jelenleg) - Közösségi interakciók az utcán | D32: =SUMPRODUCT((INDEX(final_df!$B$2:$ZZ$100,,MATCH(C32,final_df!$B$1:$ZZ$1,0))>0)*1) -> 12 | E32: =SUMPRODUCT((INDEX(final_df!$B$2:$ZZ$100,,MATCH($C32,final_df!$B$1:$ZZ$1,0))>0)*(final_df!$E$2:$E$100=E$1)) -> 6 | F32: =SUMPRODUCT((INDEX(final_df!$B$2:$ZZ$100,,MATCH($C32,final_df!$B$1:$ZZ$1,0))>0)*(final_df!$E$2:$E$100=F$1)) -> 6 | G32: =SUMPRODUCT((INDEX(final_df!$B$2:$ZZ$100,,MATCH($C32,final_df!$B$1:$ZZ$1,0))>0)*(final_df!$AM$2:$AM$100=G$1)) -> 1 | H32: =SUMPRODUCT((INDEX(final_df!$B$2:$ZZ$100,,MATCH($C32,final_df!$B$1:$ZZ$1,0))>0)*(final_df!$AM$2:$AM$100=H$1)) -> 6 | I32: =SUMPRODUCT((INDEX(final_df!$B$2:$ZZ$100,,MATCH($C32,final_df!$B$1:$ZZ$1,0))>0)*(final_df!$AM$2:$AM$100=I$1)) -> 5
B33: Közterület használata | C33: Utcahasználat (jelenleg) - Közterület használata | D33: =SUMPRODUCT((INDEX(final_df!$B$2:$ZZ$100,,MATCH(C33,final_df!$B$1:$ZZ$1,0))>0)*1) -> 19 | E33: =SUMPRODUCT((INDEX(final_df!$B$2:$ZZ$100,,MATCH($C33,final_df!$B$1:$ZZ$1,0))>0)*(final_df!$E$2:$E$100=E$1)) -> 11 | F33: =SUMPRODUCT((INDEX(final_df!$B$2:$ZZ$100,,MATCH($C33,final_df!$B$1:$ZZ$1,0))>0)*(final_df!$E$2:$E$100=F$1)) -> 8 | G33: =SUMPRODUCT((INDEX(final_df!$B$2:$ZZ$100,,MATCH($C33,final_df!$B$1:$ZZ$1,0))>0)*(final_df!$AM$2:$AM$100=G$1)) -> 7 | H33: =SUMPRODUCT((INDEX(final_df!$B$2:$ZZ$100,,MATCH($C33,final_df!$B$1:$ZZ$1,0))>0)*(final_df!$AM$2:$AM$100=H$1)) -> 4 | I33: =SUMPRODUCT((INDEX(final_df!$B$2:$ZZ$100,,MATCH($C33,final_df!$B$1:$ZZ$1,0))>0)*(final_df!$AM$2:$AM$100=I$1)) -> 8
B34: Szabadidő / szórakozás / vendéglátás | C34: Utcahasználat (jelenleg) - Szabadidő / szórakozás / vendéglátás | D34: =SUMPRODUCT((INDEX(final_df!$B$2:$ZZ$100,,MATCH(C34,final_df!$B$1:$ZZ$1,0))>0)*1) -> 35 | E34: =SUMPRODUCT((INDEX(final_df!$B$2:$ZZ$100,,MATCH($C34,final_df!$B$1:$ZZ$1,0))>0)*(final_df!$E$2:$E$100=E$1)) -> 17 | F34: =SUMPRODUCT((INDEX(final_df!$B$2:$ZZ$100,,MATCH($C34,final_df!$B$1:$ZZ$1,0))>0)*(final_df!$E$2:$E$100=F$1)) -> 18 | G34: =SUMPRODUCT((INDEX(final_df!$B$2:$ZZ$100,,MATCH($C34,final_df!$B$1:$ZZ$1,0))>0)*(final_df!$AM$2:$AM$100=G$1)) -> 7 | H34: =SUMPRODUCT((INDEX(final_df!$B$2:$ZZ$100,,MATCH($C34,final_df!$B$1:$ZZ$1,0))>0)*(final_df!$AM$2:$AM$100=H$1)) -> 12 | I34: =SUMPRODUCT((INDEX(final_df!$B$2:$ZZ$100,,MATCH($C34,final_df!$B$1:$ZZ$1,0))>0)*(final_df!$AM$2:$AM$100=I$1)) -> 16
B35: Vásárlás / boltok / szolgáltatások | C35: Utcahasználat (jelenleg) - Vásárlás / boltok / szolgáltatások | D35: =SUMPRODUCT((INDEX(final_df!$B$2:$ZZ$100,,MATCH(C35,final_df!$B$1:$ZZ$1,0))>0)*1) -> 53 | E35: =SUMPRODUCT((INDEX(final_df!$B$2:$ZZ$100,,MATCH($C35,final_df!$B$1:$ZZ$1,0))>0)*(final_df!$E$2:$E$100=E$1)) -> 25 | F35: =SUMPRODUCT((INDEX(final_df!$B$2:$ZZ$100,,MATCH($C35,final_df!$B$1:$ZZ$1,0))>0)*(final_df!$E$2:$E$100=F$1)) -> 28 | G35: =SUMPRODUCT((INDEX(final_df!$B$2:$ZZ$100,,MATCH($C35,final_df!$B$1:$ZZ$1,0))>0)*(final_df!$AM$2:$AM$100=G$1)) -> 18 | H35: =SUMPRODUCT((INDEX(final_df!$B$2:$ZZ$100,,MATCH($C35,final_df!$B$1:$ZZ$1,0))>0)*(final_df!$AM$2:$AM$100=H$1)) -> 18 | I35: =SUMPRODUCT((INDEX(final_df!$B$2:$ZZ$100,,MATCH($C35,final_df!$B$1:$ZZ$1,0))>0)*(final_df!$AM$2:$AM$100=I$1)) -> 17
A36: Utcai fejlesztések értékelése | B36: Blaha Lujza tér | C36: Utcai fejlesztések értékelése - Blaha Lujza tér | D36: =SUMPRODUCT((INDEX(final_df!$B$2:$ZZ$100,,MATCH(C36,final_df!$B$1:$ZZ$1,0))>0)*1) -> 34 | E36: =SUMPRODUCT((INDEX(final_df!$B$2:$ZZ$100,,MATCH($C36,final_df!$B$1:$ZZ$1,0))>0)*(final_df!$E$2:$E$100=E$1)) -> 19 | F36: =SUMPRODUCT((INDEX(final_df!$B$2:$ZZ$100,,MATCH($C36,final_df!$B$1:$ZZ$1,0))>0)*(final_df!$E$2:$E$100=F$1)) -> 15 | G36: =SUMPRODUCT((INDEX(final_df!$B$2:$ZZ$100,,MATCH($C36,final_df!$B$1:$ZZ$1,0))>0)*(final_df!$AM$2:$AM$100=G$1)) -> 11 | H36: =SUMPRODUCT((INDEX(final_df!$B$2:$ZZ$100,,MATCH($C36,final_df!$B$1:$ZZ$1,0))>0)*(final_df!$AM$2:$AM$100=H$1)) -> 11 | I36: =SUMPRODUCT((INDEX(final_df!$B$2:$ZZ$100,,MATCH($C36,final_df!$B$1:$ZZ$1,0))>0)*(final_df!$AM$2:$AM$100=I$1)) -> 12
B37: Kis zöldítések / torkollatok | C37: Utcai fejlesztések értékelése - II. János Pál pápa tér | D37: =SUMPRODUCT((INDEX(final_df!$B$2:$ZZ$100,,MATCH(C37,final_df!$B$1:$ZZ$1,0))>0)*1) -> 27 | E37: =SUMPRODUCT((INDEX(final_df!$B$2:$ZZ$100,,MATCH($C37,final_df!$B$1:$ZZ$1,0))>0)*(final_df!$E$2:$E$100=E$1)) -> 13 | F37: =SUMPRODUCT((INDEX(final_df!$B$2:$ZZ$100,,MATCH($C37,final_df!$B$1:$ZZ$1,0))>0)*(final_df!$E$2:$E$100=F$1)) -> 14 | G37: =SUMPRODUCT((INDEX(final_df!$B$2:$ZZ$100,,MATCH($C37,final_df!$B$1:$ZZ$1,0))>0)*(final_df!$AM$2:$AM$100=G$1)) -> 10 | H37: =SUMPRODUCT((INDEX(final_df!$B$2:$ZZ$100,,MATCH($C37,final_df!$B$1:$ZZ$1,0))>0)*(final_df!$AM$2:$AM$100=H$1)) -> 10 | I37: =SUMPRODUCT((INDEX(final_df!$B$2:$ZZ$100,,MATCH($C37,final_df!$B$1:$ZZ$1,0))>0)*(final_df!$AM$2:$AM$100=I$1)) -> 7
B38: Négyes metró | C38: Utcai fejlesztések értékelése - Négyes metró | D38: =SUMPRODUCT((INDEX(final_df!$B$2:$ZZ$100,,MATCH(C38,final_df!$B$1:$ZZ$1,0))>0)*1) -> 20 | E38: =SUMPRODUCT((INDEX(final_df!$B$2:$ZZ$100,,MATCH($C38,final_df!$B$1:$ZZ$1,0))>0)*(final_df!$E$2:$E$100=E$1)) -> 9 | F38: =SUMPRODUCT((INDEX(final_df!$B$2:$ZZ$100,,MATCH($C38,final_df!$B$1:$ZZ$1,0))>0)*(final_df!$E$2:$E$100=F$1)) -> 11 | G38: =SUMPRODUCT((INDEX(final_df!$B$2:$ZZ$100,,MATCH($C38,final_df!$B$1:$ZZ$1,0))>0)*(final_df!$AM$2:$AM$100=G$1)) -> 6 | H38: =SUMPRODUCT((INDEX(final_df!$B$2:$ZZ$100,,MATCH($C38,final_df!$B$1:$ZZ$1,0))>0)*(final_df!$AM$2:$AM$100=H$1)) -> 8 | I38: =SUMPRODUCT((INDEX(final_df!$B$2:$ZZ$100,,MATCH($C38,final_df!$B$1:$ZZ$1,0))>0)*(final_df!$AM$2:$AM$100=I$1)) -> 6
B39: Nincs hatása | C39: Utcai fejlesztések értékelése - Nincs hatása | D39: =SUMPRODUCT((INDEX(final_df!$B$2:$ZZ$100,,MATCH(C39,final_df!$B$1:$ZZ$1,0))>0)*1) -> 15 | E39: =SUMPRODUCT((INDEX(final_df!$B$2:$ZZ$100,,MATCH($C39,final_df!$B$1:$ZZ$1,0))>0)*(final_df!$E$2:$E$100=E$1)) -> 8 | F39: =SUMPRODUCT((INDEX(final_df!$B$2:$ZZ$100,,MATCH($C39,final_df!$B$1:$ZZ$1,0))>0)*(final_df!$E$2:$E$100=F$1)) -> 7 | G39: =SUMPRODUCT((INDEX(final_df!$B$2:$ZZ$100,,MATCH($C39,final_df!$B$1:$ZZ$1,0))>0)*(final_df!$AM$2:$AM$100=G$1)) -> 4 | H39: =SUMPRODUCT((INDEX(final_df!$B$2:$ZZ$100,,MATCH($C39,final_df!$B$1:$ZZ$1,0))>0)*(final_df!$AM$2:$AM$100=H$1)) -> 6 | I39: =SUMPRODUCT((INDEX(final_df!$B$2:$ZZ$100,,MATCH($C39,final_df!$B$1:$ZZ$1,0))>0)*(final_df!$AM$2:$AM$100=I$1)) -> 5
B40: Pápa tér | C40: Utcai fejlesztések értékelése - Teleki tér | D40: =SUMPRODUCT((INDEX(final_df!$B$2:$ZZ$100,,MATCH(C40,final_df!$B$1:$ZZ$1,0))>0)*1) -> 20 | E40: =SUMPRODUCT((INDEX(final_df!$B$2:$ZZ$100,,MATCH($C40,final_df!$B$1:$ZZ$1,0))>0)*(final_df!$E$2:$E$100=E$1)) -> 8 | F40: =SUMPRODUCT((INDEX(final_df!$B$2:$ZZ$100,,MATCH($C40,final_df!$B$1:$ZZ$1,0))>0)*(final_df!$E$2:$E$100=F$1)) -> 12 | G40: =SUMPRODUCT((INDEX(final_df!$B$2:$ZZ$100,,MATCH($C40,final_df!$B$1:$ZZ$1,0))>0)*(final_df!$AM$2:$AM$100=G$1)) -> 9 | H40: =SUMPRODUCT((INDEX(final_df!$B$2:$ZZ$100,,MATCH($C40,final_df!$B$1:$ZZ$1,0))>0)*(final_df!$AM$2:$AM$100=H$1)) -> 3 | I40: =SUMPRODUCT((INDEX(final_df!$B$2:$ZZ$100,,MATCH($C40,final_df!$B$1:$ZZ$1,0))>0)*(final_df!$AM$2:$AM$100=I$1)) -> 8
B41: Teleki tér | C41: Utcai fejlesztések értékelése - Utcai zöldítések | D41: =SUMPRODUCT((INDEX(final_df!$B$2:$ZZ$100,,MATCH(C41,final_df!$B$1:$ZZ$1,0))>0)*1) -> 27 | E41: =SUMPRODUCT((INDEX(final_df!$B$2:$ZZ$100,,MATCH($C41,final_df!$B$1:$ZZ$1,0))>0)*(final_df!$E$2:$E$100=E$1)) -> 15 | F41: =SUMPRODUCT((INDEX(final_df!$B$2:$ZZ$100,,MATCH($C41,final_df!$B$1:$ZZ$1,0))>0)*(final_df!$E$2:$E$100=F$1)) -> 12 | G41: =SUMPRODUCT((INDEX(final_df!$B$2:$ZZ$100,,MATCH($C41,final_df!$B$1:$ZZ$1,0))>0)*(final_df!$AM$2:$AM$100=G$1)) -> 9 | H41: =SUMPRODUCT((INDEX(final_df!$B$2:$ZZ$100,,MATCH($C41,final_df!$B$1:$ZZ$1,0))>0)*(final_df!$AM$2:$AM$100=H$1)) -> 10 | I41: =SUMPRODUCT((INDEX(final_df!$B$2:$ZZ$100,,MATCH($C41,final_df!$B$1:$ZZ$1,0))>0)*(final_df!$AM$2:$AM$100=I$1)) -> 8
A42: Utcán mit változtatna | B42: Infrastuktúra | C42: Utcán mit változtatna - Infrastuktúra | D42: =SUMPRODUCT((INDEX(final_df!$B$2:$ZZ$100,,MATCH(C42,final_df!$B$1:$ZZ$1,0))>0)*1) -> 25 | E42: =SUMPRODUCT((INDEX(final_df!$B$2:$ZZ$100,,MATCH($C42,final_df!$B$1:$ZZ$1,0))>0)*(final_df!$E$2:$E$100=E$1)) -> 15 | F42: =SUMPRODUCT((INDEX(final_df!$B$2:$ZZ$100,,MATCH($C42,final_df!$B$1:$ZZ$1,0))>0)*(final_df!$E$2:$E$100=F$1)) -> 10 | G42: =SUMPRODUCT((INDEX(final_df!$B$2:$ZZ$100,,MATCH($C42,final_df!$B$1:$ZZ$1,0))>0)*(final_df!$AM$2:$AM$100=G$1)) -> 8 | H42: =SUMPRODUCT((INDEX(final_df!$B$2:$ZZ$100,,MATCH($C42,final_df!$B$1:$ZZ$1,0))>0)*(final_df!$AM$2:$AM$100=H$1)) -> 9 | I42: =SUMPRODUCT((INDEX(final_df!$B$2:$ZZ$100,,MATCH($C42,final_df!$B$1:$ZZ$1,0))>0)*(final_df!$AM$2:$AM$100=I$1)) -> 8
B43: Közbiztonság javítása | C43: Utcán mit változtatna - Közbiztonság javítása | D43: =SUMPRODUCT((INDEX(final_df!$B$2:$ZZ$100,,MATCH(C43,final_df!$B$1:$ZZ$1,0))>0)*1) -> 13 | E43: =SUMPRODUCT((INDEX(final_df!$B$2:$ZZ$100,,MATCH($C43,final_df!$B$1:$ZZ$1,0))>0)*(final_df!$E$2:$E$100=E$1)) -> 8 | F43: =SUMPRODUCT((INDEX(final_df!$B$2:$ZZ$100,,MATCH($C43,final_df!$B$1:$ZZ$1,0))>0)*(final_df!$E$2:$E$100=F$1)) -> 5 | G43: =SUMPRODUCT((INDEX(final_df!$B$2:$ZZ$100,,MATCH($C43,final_df!$B$1:$ZZ$1,0))>0)*(final_df!$AM$2:$AM$100=G$1)) -> 3 | H43: =SUMPRODUCT((INDEX(final_df!$B$2:$ZZ$100,,MATCH($C43,final_df!$B$1:$ZZ$1,0))>0)*(final_df!$AM$2:$AM$100=H$1)) -> 8 | I43: =SUMPRODUCT((INDEX(final_df!$B$2:$ZZ$100,,MATCH($C43,final_df!$B$1:$ZZ$1,0))>0)*(final_df!$AM$2:$AM$100=I$1)) -> 2
B44: Közlekedés | C44: Utcán mit változtatna - Közlekedés | D44: =SUMPRODUCT((INDEX(final_df!$B$2:$ZZ$100,,MATCH(C44,final_df!$B$1:$ZZ$1,0))>0)*1) -> 23 | E44: =SUMPRODUCT((INDEX(final_df!$B$2:$ZZ$100,,MATCH($C44,final_df!$B$1:$ZZ$1,0))>0)*(final_df!$E$2:$E$100=E$1)) -> 12 | F44: =SUMPRODUCT((INDEX(final_df!$B$2:$ZZ$100,,MATCH($C44,final_df!$B$1:$ZZ$1,0))>0)*(final_df!$E$2:$E$100=F$1)) -> 11 | G44: =SUMPRODUCT((INDEX(final_df!$B$2:$ZZ$100,,MATCH($C44,final_df!$B$1:$ZZ$1,0))>0)*(final_df!$AM$2:$AM$100=G$1)) -> 7 | H44: =SUMPRODUCT((INDEX(final_df!$B$2:$ZZ$100,,MATCH($C44,final_df!$B$1:$ZZ$1,0))>0)*(final_df!$AM$2:$AM$100=H$1)) -> 11 | I44: =SUMPRODUCT((INDEX(final_df!$B$2:$ZZ$100,,MATCH($C44,final_df!$B$1:$ZZ$1,0))>0)*(final_df!$AM$2:$AM$100=I$1)) -> 5
B45: Szabadidő / szórakozás / vendéglátás - változtatna | C45: Utcán mit változtatna - Szabadidő / szórakozás / vendéglátás - változtatna | D45: =SUMPRODUCT((INDEX(final_df!$B$2:$ZZ$100,,MATCH(C45,final_df!$B$1:$ZZ$1,0))>0)*1) -> 13 | E45: =SUMPRODUCT((INDEX(final_df!$B$2:$ZZ$100,,MATCH($C45,final_df!$B$1:$ZZ$1,0))>0)*(final_df!$E$2:$E$100=E$1)) -> 8 | F45: =SUMPRODUCT((INDEX(final_df!$B$2:$ZZ$100,,MATCH($C45,final_df!$B$1:$ZZ$1,0))>0)*(final_df!$E$2:$E$100=F$1)) -> 5 | G45: =SUMPRODUCT((INDEX(final_df!$B$2:$ZZ$100,,MATCH($C45,final_df!$B$1:$ZZ$1,0))>0)*(final_df!$AM$2:$AM$100=G$1)) -> 0 | H45: =SUMPRODUCT((INDEX(final_df!$B$2:$ZZ$100,,MATCH($C45,final_df!$B$1:$ZZ$1,0))>0)*(final_df!$AM$2:$AM$100=H$1)) -> 8 | I45: =SUMPRODUCT((INDEX(final_df!$B$2:$ZZ$100,,MATCH($C45,final_df!$B$1:$ZZ$1,0))>0)*(final_df!$AM$2:$AM$100=I$1)) -> 5
B46: Szociális ellátórendszer | C46: Utcán mit változtatna - Szociális ellátórendszer | D46: =SUMPRODUCT((INDEX(final_df!$B$2:$ZZ$100,,MATCH(C46,final_df!$B$1:$ZZ$1,0))>0)*1) -> 16 | E46: =SUMPRODUCT((INDEX(final_df!$B$2:$ZZ$100,,MATCH($C46,final_df!$B$1:$ZZ$1,0))>0)*(final_df!$E$2:$E$100=E$1)) -> 7 | F46: =SUMPRODUCT((INDEX(final_df!$B$2:$ZZ$100,,MATCH($C46,final_df!$B$1:$ZZ$1,0))>0)*(final_df!$E$2:$E$100=F$1)) -> 9 | G46: =SUMPRODUCT((INDEX(final_df!$B$2:$ZZ$100,,MATCH($C46,final_df!$B$1:$ZZ$1,0))>0)*(final_df!$AM$2:$AM$100=G$1)) -> 5 | H46: =SUMPRODUCT((INDEX(final_df!$B$2:$ZZ$100,,MATCH($C46,final_df!$B$1:$ZZ$1,0))>0)*(final_df!$AM$2:$AM$100=H$1)) -> 7 | I46: =SUMPRODUCT((INDEX(final_df!$B$2:$ZZ$100,,MATCH($C46,final_df!$B$1:$ZZ$1,0))>0)*(final_df!$AM$2:$AM$100=I$1)) -> 4
B47: Tisztaság / rendezettség javítása | C47: Utcán mit változtatna - Tisztaság / rendezettség javítása | D47: =SUMPRODUCT((INDEX(final_df!$B$2:$ZZ$100,,MATCH(C47,final_df!$B$1:$ZZ$1,0))>0)*1) -> 14 | E47: =SUMPRODUCT((INDEX(final_df!$B$2:$ZZ$100,,MATCH($C47,final_df!$B$1:$ZZ$1,0))>0)*(final_df!$E$2:$E$100=E$1)) -> 7 | F47: =SUMPRODUCT((INDEX(final_df!$B$2:$ZZ$100,,MATCH($C47,final_df!$B$1:$ZZ$1,0))>0)*(final_df!$E$2:$E$100=F$1)) -> 7 | G47: =SUMPRODUCT((INDEX(final_df!$B$2:$ZZ$100,,MATCH($C47,final_df!$B$1:$ZZ$1,0))>0)*(final_df!$AM$2:$AM$100=G$1)) -> 5 | H47: =SUMPRODUCT((INDEX(final_df!$B$2:$ZZ$100,,MATCH($C47,final_df!$B$1:$ZZ$1,0))>0)*(final_df!$AM$2:$AM$100=H$1)) -> 5 | I47: =SUMPRODUCT((INDEX(final_df!$B$2:$ZZ$100,,MATCH($C47,final_df!$B$1:$ZZ$1,0))>0)*(final_df!$AM$2:$AM$100=I$1)) -> 4
B48: Vásárlás / boltok / szolgáltatások - változtatna | C48: Utcán mit változtatna - Vásárlás / boltok / szolgáltatások - változtatna | D48: =SUMPRODUCT((INDEX(final_df!$B$2:$ZZ$100,,MATCH(C48,final_df!$B$1:$ZZ$1,0))>0)*1) -> 13 | E48: =SUMPRODUCT((INDEX(final_df!$B$2:$ZZ$100,,MATCH($C48,final_df!$B$1:$ZZ$1,0))>0)*(final_df!$E$2:$E$100=E$1)) -> 8 | F48: =SUMPRODUCT((INDEX(final_df!$B$2:$ZZ$100,,MATCH($C48,final_df!$B$1:$ZZ$1,0))>0)*(final_df!$E$2:$E$100=F$1)) -> 5 | G48: =SUMPRODUCT((INDEX(final_df!$B$2:$ZZ$100,,MATCH($C48,final_df!$B$1:$ZZ$1,0))>0)*(final_df!$AM$2:$AM$100=G$1)) -> 3 | H48: =SUMPRODUCT((INDEX(final_df!$B$2:$ZZ$100,,MATCH($C48,final_df!$B$1:$ZZ$1,0))>0)*(final_df!$AM$2:$AM$100=H$1)) -> 4 | I48: =SUMPRODUCT((INDEX(final_df!$B$2:$ZZ$100,,MATCH($C48,final_df!$B$1:$ZZ$1,0))>0)*(final_df!$AM$2:$AM$100=I$1)) -> 6
B49: Zöldítés | C49: Utcán mit változtatna - Zöldítés | D49: =SUMPRODUCT((INDEX(final_df!$B$2:$ZZ$100,,MATCH(C49,final_df!$B$1:$ZZ$1,0))>0)*1) -> 18 | E49: =SUMPRODUCT((INDEX(final_df!$B$2:$ZZ$100,,MATCH($C49,final_df!$B$1:$ZZ$1,0))>0)*(final_df!$E$2:$E$100=E$1)) -> 10 | F49: =SUMPRODUCT((INDEX(final_df!$B$2:$ZZ$100,,MATCH($C49,final_df!$B$1:$ZZ$1,0))>0)*(final_df!$E$2:$E$100=F$1)) -> 8 | G49: =SUMPRODUCT((INDEX(final_df!$B$2:$ZZ$100,,MATCH($C49,final_df!$B$1:$ZZ$1,0))>0)*(final_df!$AM$2:$AM$100=G$1)) -> 2 | H49: =SUMPRODUCT((INDEX(final_df!$B$2:$ZZ$100,,MATCH($C49,final_df!$B$1:$ZZ$1,0))>0)*(final_df!$AM$2:$AM$100=H$1)) -> 10 | I49: =SUMPRODUCT((INDEX(final_df!$B$2:$ZZ$100,,MATCH($C49,final_df!$B$1:$ZZ$1,0))>0)*(final_df!$AM$2:$AM$100=I$1)) -> 6
A50: Utcával kapcsolatos attitűdök | B50: Biztonságérzet | C50: Utcával kapcsolatos attitűdök - Biztonságérzet | D50: =SUMPRODUCT((INDEX(final_df!$B$2:$ZZ$100,,MATCH(C50,final_df!$B$1:$ZZ$1,0))>0)*1) -> 49 | E50: =SUMPRODUCT((INDEX(final_df!$B$2:$ZZ$100,,MATCH($C50,final_df!$B$1:$ZZ$1,0))>0)*(final_df!$E$2:$E$100=E$1)) -> 22 | F50: =SUMPRODUCT((INDEX(final_df!$B$2:$ZZ$100,,MATCH($C50,final_df!$B$1:$ZZ$1,0))>0)*(final_df!$E$2:$E$100=F$1)) -> 27 | G50: =SUMPRODUCT((INDEX(final_df!$B$2:$ZZ$100,,MATCH($C50,final_df!$B$1:$ZZ$1,0))>0)*(final_df!$AM$2:$AM$100=G$1)) -> 17 | H50: =SUMPRODUCT((INDEX(final_df!$B$2:$ZZ$100,,MATCH($C50,final_df!$B$1:$ZZ$1,0))>0)*(final_df!$AM$2:$AM$100=H$1)) -> 15 | I50: =SUMPRODUCT((INDEX(final_df!$B$2:$ZZ$100,,MATCH($C50,final_df!$B$1:$ZZ$1,0))>0)*(final_df!$AM$2:$AM$100=I$1)) -> 17
B51: Érzelmi kötődés | C51: Utcával kapcsolatos attitűdök - Érzelmi kötődés | D51: =SUMPRODUCT((INDEX(final_df!$B$2:$ZZ$100,,MATCH(C51,final_df!$B$1:$ZZ$1,0))>0)*1) -> 18 | E51: =SUMPRODUCT((INDEX(final_df!$B$2:$ZZ$100,,MATCH($C51,final_df!$B$1:$ZZ$1,0))>0)*(final_df!$E$2:$E$100=E$1)) -> 7 | F51: =SUMPRODUCT((INDEX(final_df!$B$2:$ZZ$100,,MATCH($C51,final_df!$B$1:$ZZ$1,0))>0)*(final_df!$E$2:$E$100=F$1)) -> 11 | G51: =SUMPRODUCT((INDEX(final_df!$B$2:$ZZ$100,,MATCH($C51,final_df!$B$1:$ZZ$1,0))>0)*(final_df!$AM$2:$AM$100=G$1)) -> 5 | H51: =SUMPRODUCT((INDEX(final_df!$B$2:$ZZ$100,,MATCH($C51,final_df!$B$1:$ZZ$1,0))>0)*(final_df!$AM$2:$AM$100=H$1)) -> 7 | I51: =SUMPRODUCT((INDEX(final_df!$B$2:$ZZ$100,,MATCH($C51,final_df!$B$1:$ZZ$1,0))>0)*(final_df!$AM$2:$AM$100=I$1)) -> 6
B52: Környezeti benyomások (zaj / szmog / más) | C52: Utcával kapcsolatos attitűdök - Környezeti benyomások (zaj / szmog / más) | D52: =SUMPRODUCT((INDEX(final_df!$B$2:$ZZ$100,,MATCH(C52,final_df!$B$1:$ZZ$1,0))>0)*1) -> 27 | E52: =SUMPRODUCT((INDEX(final_df!$B$2:$ZZ$100,,MATCH($C52,final_df!$B$1:$ZZ$1,0))>0)*(final_df!$E$2:$E$100=E$1)) -> 13 | F52: =SUMPRODUCT((INDEX(final_df!$B$2:$ZZ$100,,MATCH($C52,final_df!$B$1:$ZZ$1,0))>0)*(final_df!$E$2:$E$100=F$1)) -> 14 | G52: =SUMPRODUCT((INDEX(final_df!$B$2:$ZZ$100,,MATCH($C52,final_df!$B$1:$ZZ$1,0))>0)*(final_df!$AM$2:$AM$100=G$1)) -> 10 | H52: =SUMPRODUCT((INDEX(final_df!$B$2:$ZZ$100,,MATCH($C52,final_df!$B$1:$ZZ$1,0))>0)*(final_df!$AM$2:$AM$100=H$1)) -> 8 | I52: =SUMPRODUCT((INDEX(final_df!$B$2:$ZZ$100,,MATCH($C52,final_df!$B$1:$ZZ$1,0))>0)*(final_df!$AM$2:$AM$100=I$1)) -> 9
B53: Társadalmi sokszínűség (etnikai / osztálybeli / más) | C53: Utcával kapcsolatos attitűdök - Társadalmi sokszínűség (etnikai / osztálybeli / más) | D53: =SUMPRODUCT((INDEX(final_df!$B$2:$ZZ$100,,MATCH(C53,final_df!$B$1:$ZZ$1,0))>0)*1) -> 40 | E53: =SUMPRODUCT((INDEX(final_df!$B$2:$ZZ$100,,MATCH($C53,final_df!$B$1:$ZZ$1,0))>0)*(final_df!$E$2:$E$100=E$1)) -> 18 | F53: =SUMPRODUCT((INDEX(final_df!$B$2:$ZZ$100,,MATCH($C53,final_df!$B$1:$ZZ$1,0))>0)*(final_df!$E$2:$E$100=F$1)) -> 22 | G53: =SUMPRODUCT((INDEX(final_df!$B$2:$ZZ$100,,MATCH($C53,final_df!$B$1:$ZZ$1,0))>0)*(final_df!$AM$2:$AM$100=G$1)) -> 14 | H53: =SUMPRODUCT((INDEX(final_df!$B$2:$ZZ$100,,MATCH($C53,final_df!$B$1:$ZZ$1,0))>0)*(final_df!$AM$2:$AM$100=H$1)) -> 14 | I53: =SUMPRODUCT((INDEX(final_df!$B$2:$ZZ$100,,MATCH($C53,final_df!$B$1:$ZZ$1,0))>0)*(final_df!$AM$2:$AM$100=I$1)) -> 12
B54: Tisztaság / rendezettség | C54: Utcával kapcsolatos attitűdök - Tisztaság / rendezettség | D54: =SUMPRODUCT((INDEX(final_df!$B$2:$ZZ$100,,MATCH(C54,final_df!$B$1:$ZZ$1,0))>0)*1) -> 36 | E54: =SUMPRODUCT((INDEX(final_df!$B$2:$ZZ$100,,MATCH($C54,final_df!$B$1:$ZZ$1,0))>0)*(final_df!$E$2:$E$100=E$1)) -> 13 | F54: =SUMPRODUCT((INDEX(final_df!$B$2:$ZZ$100,,MATCH($C54,final_df!$B$1:$ZZ$1,0))>0)*(final_df!$E$2:$E$100=F$1)) -> 23 | G54: =SUMPRODUCT((INDEX(final_df!$B$2:$ZZ$100,,MATCH($C54,final_df!$B$1:$ZZ$1,0))>0)*(final_df!$AM$2:$AM$100=G$1)) -> 14 | H54: =SUMPRODUCT((INDEX(final_df!$B$2:$ZZ$100,,MATCH($C54,final_df!$B$1:$ZZ$1,0))>0)*(final_df!$AM$2:$AM$100=H$1)) -> 11 | I54: =SUMPRODUCT((INDEX(final_df!$B$2:$ZZ$100,,MATCH($C54,final_df!$B$1:$ZZ$1,0))>0)*(final_df!$AM$2:$AM$100=I$1)) -> 11

Sheet Elemzés - előfordulás aránya
A1: Kódkategória | B1: Kód | C1: Kód konkrétan | D1: Összesen | E1: Férfi | F1: Nő | G1: idős | H1: fiatal tulajdonos | I1: fiatal bérlő
A2: Ideköltözés okai és körülményei | B2: Anyagi | C2: Ideköltözés okai és körülményei - Anyagi | D2: =SUMPRODUCT((INDEX(final_df!$B$2:$ZZ$100,,MATCH(C2,final_df!$B$1:$ZZ$1,0))>0)*1)/56 -> 0.41071429 | E2: =SUMPRODUCT((INDEX(final_df!$B$2:$ZZ$100,,MATCH($C2,final_df!$B$1:$ZZ$1,0))>0)*(final_df!$E$2:$E$100=E$1)) /COUNTIF(final_df!$E$2:$E$100, E$1) -> 0.57142857 | F2: =SUMPRODUCT((INDEX(final_df!$B$2:$ZZ$100,,MATCH($C2,final_df!$B$1:$ZZ$1,0))>0)*(final_df!$E$2:$E$100=F$1)) /COUNTIF(final_df!$E$2:$E$100, F$1) -> 0.25 | G2: =SUMPRODUCT((INDEX(final_df!$B$2:$ZZ$100,,MATCH($C2,final_df!$B$1:$ZZ$1,0))>0)*(final_df!$AM$2:$AM$100=G$1)) /COUNTIF(final_df!$AM$2:$AM$100, G$1) -> 0.16666667 | H2: =SUMPRODUCT((INDEX(final_df!$B$2:$ZZ$100,,MATCH($C2,final_df!$B$1:$ZZ$1,0))>0)*(final_df!$AM$2:$AM$100=H$1)) /COUNTIF(final_df!$AM$2:$AM$100, H$1) -> 0.63157895 | I2: =SUMPRODUCT((INDEX(final_df!$B$2:$ZZ$100,,MATCH($C2,final_df!$B$1:$ZZ$1,0))>0)*(final_df!$AM$2:$AM$100=I$1)) /COUNTIF(final_df!$AM$2:$AM$100, I$1) -> 0.42105263
B3: Családi / személyes okok | C3: Ideköltözés okai és körülményei - Családi / személyes okok | D3: =SUMPRODUCT((INDEX(final_df!$B$2:$ZZ$100,,MATCH(C3,final_df!$B$1:$ZZ$1,0))>0)*1)/56 -> 0.5 | E3: =SUMPRODUCT((INDEX(final_df!$B$2:$ZZ$100,,MATCH($C3,final_df!$B$1:$ZZ$1,0))>0)*(final_df!$E$2:$E$100=E$1)) /COUNTIF(final_df!$E$2:$E$100, E$1) -> 0.28571429 | F3: =SUMPRODUCT((INDEX(final_df!$B$2:$ZZ$100,,MATCH($C3,final_df!$B$1:$ZZ$1,0))>0)*(final_df!$E$2:$E$100=F$1)) /COUNTIF(final_df!$E$2:$E$100, F$1) -> 0.71428571 | G3: =SUMPRODUCT((INDEX(final_df!$B$2:$ZZ$100,,MATCH($C3,final_df!$B$1:$ZZ$1,0))>0)*(final_df!$AM$2:$AM$100=G$1)) /COUNTIF(final_df!$AM$2:$AM$100, G$1) -> 0.61111111 | H3: =SUMPRODUCT((INDEX(final_df!$B$2:$ZZ$100,,MATCH($C3,final_df!$B$1:$ZZ$1,0))>0)*(final_df!$AM$2:$AM$100=H$1)) /COUNTIF(final_df!$AM$2:$AM$100, H$1) -> 0.31578947 | I3: =SUMPRODUCT((INDEX(final_df!$B$2:$ZZ$100,,MATCH($C3,final_df!$B$1:$ZZ$1,0))>0)*(final_df!$AM$2:$AM$100=I$1)) /COUNTIF(final_df!$AM$2:$AM$100, I$1) -> 0.57894737
B4: Kulturális | C4: Ideköltözés okai és körülményei - Kulturális | D4: =SUMPRODUCT((INDEX(final_df!$B$2:$ZZ$100,,MATCH(C4,final_df!$B$1:$ZZ$1,0))>0)*1)/56 -> 0.071428571 | E4: =SUMPRODUCT((INDEX(final_df!$B$2:$ZZ$100,,MATCH($C4,final_df!$B$1:$ZZ$1,0))>0)*(final_df!$E$2:$E$100=E$1)) /COUNTIF(final_df!$E$2:$E$100, E$1) -> 0.071428571 | F4: =SUMPRODUCT((INDEX(final_df!$B$2:$ZZ$100,,MATCH($C4,final_df!$B$1:$ZZ$1,0))>0)*(final_df!$E$2:$E$100=F$1)) /COUNTIF(final_df!$E$2:$E$100, F$1) -> 0.071428571 | G4: =SUMPRODUCT((INDEX(final_df!$B$2:$ZZ$100,,MATCH($C4,final_df!$B$1:$ZZ$1,0))>0)*(final_df!$AM$2:$AM$100=G$1)) /COUNTIF(final_df!$AM$2:$AM$100, G$1) -> 0 | H4: =SUMPRODUCT((INDEX(final_df!$B$2:$ZZ$100,,MATCH($C4,final_df!$B$1:$ZZ$1,0))>0)*(final_df!$AM$2:$AM$100=H$1)) /COUNTIF(final_df!$AM$2:$AM$100, H$1) -> 0.15789474 | I4: =SUMPRODUCT((INDEX(final_df!$B$2:$ZZ$100,,MATCH($C4,final_df!$B$1:$ZZ$1,0))>0)*(final_df!$AM$2:$AM$100=I$1)) /COUNTIF(final_df!$AM$2:$AM$100, I$1) -> 0.052631579
B5: Munka / közlekedés | C5: Ideköltözés okai és körülményei - Munka / közlekedés | D5: =SUMPRODUCT((INDEX(final_df!$B$2:$ZZ$100,,MATCH(C5,final_df!$B$1:$ZZ$1,0))>0)*1)/56 -> 0.26785714 | E5: =SUMPRODUCT((INDEX(final_df!$B$2:$ZZ$100,,MATCH($C5,final_df!$B$1:$ZZ$1,0))>0)*(final_df!$E$2:$E$100=E$1)) /COUNTIF(final_df!$E$2:$E$100, E$1) -> 0.32142857 | F5: =SUMPRODUCT((INDEX(final_df!$B$2:$ZZ$100,,MATCH($C5,final_df!$B$1:$ZZ$1,0))>0)*(final_df!$E$2:$E$100=F$1)) /COUNTIF(final_df!$E$2:$E$100, F$1) -> 0.21428571 | G5: =SUMPRODUCT((INDEX(final_df!$B$2:$ZZ$100,,MATCH($C5,final_df!$B$1:$ZZ$1,0))>0)*(final_df!$AM$2:$AM$100=G$1)) /COUNTIF(final_df!$AM$2:$AM$100, G$1) -> 0.16666667 | H5: =SUMPRODUCT((INDEX(final_df!$B$2:$ZZ$100,,MATCH($C5,final_df!$B$1:$ZZ$1,0))>0)*(final_df!$AM$2:$AM$100=H$1)) /COUNTIF(final_df!$AM$2:$AM$100, H$1) -> 0.36842105 | I5: =SUMPRODUCT((INDEX(final_df!$B$2:$ZZ$100,,MATCH($C5,final_df!$B$1:$ZZ$1,0))>0)*(final_df!$AM$2:$AM$100=I$1)) /COUNTIF(final_df!$AM$2:$AM$100, I$1) -> 0.26315789
A6: Izgalmas idézet | B6: Csak vicces | C6: Izgalmas idézet - Csak vicces | D6: =SUMPRODUCT((INDEX(final_df!$B$2:$ZZ$100,,MATCH(C6,final_df!$B$1:$ZZ$1,0))>0)*1)/56 -> 0.51785714 | E6: =SUMPRODUCT((INDEX(final_df!$B$2:$ZZ$100,,MATCH($C6,final_df!$B$1:$ZZ$1,0))>0)*(final_df!$E$2:$E$100=E$1)) /COUNTIF(final_df!$E$2:$E$100, E$1) -> 0.53571429 | F6: =SUMPRODUCT((INDEX(final_df!$B$2:$ZZ$100,,MATCH($C6,final_df!$B$1:$ZZ$1,0))>0)*(final_df!$E$2:$E$100=F$1)) /COUNTIF(final_df!$E$2:$E$100, F$1) -> 0.5 | G6: =SUMPRODUCT((INDEX(final_df!$B$2:$ZZ$100,,MATCH($C6,final_df!$B$1:$ZZ$1,0))>0)*(final_df!$AM$2:$AM$100=G$1)) /COUNTIF(final_df!$AM$2:$AM$100, G$1) -> 0.5 | H6: =SUMPRODUCT((INDEX(final_df!$B$2:$ZZ$100,,MATCH($C6,final_df!$B$1:$ZZ$1,0))>0)*(final_df!$AM$2:$AM$100=H$1)) /COUNTIF(final_df!$AM$2:$AM$100, H$1) -> 0.63157895 | I6: =SUMPRODUCT((INDEX(final_df!$B$2:$ZZ$100,,MATCH($C6,final_df!$B$1:$ZZ$1,0))>0)*(final_df!$AM$2:$AM$100=I$1)) /COUNTIF(final_df!$AM$2:$AM$100, I$1) -> 0.42105263
B7: Tanulmányba / kiállíásra | C7: Izgalmas idézet - Tanulmányba / kiállíásra | D7: =SUMPRODUCT((INDEX(final_df!$B$2:$ZZ$100,,MATCH(C7,final_df!$B$1:$ZZ$1,0))>0)*1)/56 -> 0.64285714 | E7: =SUMPRODUCT((INDEX(final_df!$B$2:$ZZ$100,,MATCH($C7,final_df!$B$1:$ZZ$1,0))>0)*(final_df!$E$2:$E$100=E$1)) /COUNTIF(final_df!$E$2:$E$100, E$1) -> 0.64285714 | F7: =SUMPRODUCT((INDEX(final_df!$B$2:$ZZ$100,,MATCH($C7,final_df!$B$1:$ZZ$1,0))>0)*(final_df!$E$2:$E$100=F$1)) /COUNTIF(final_df!$E$2:$E$100, F$1) -> 0.64285714 | G7: =SUMPRODUCT((INDEX(final_df!$B$2:$ZZ$100,,MATCH($C7,final_df!$B$1:$ZZ$1,0))>0)*(final_df!$AM$2:$AM$100=G$1)) /COUNTIF(final_df!$AM$2:$AM$100, G$1) -> 0.66666667 | H7: =SUMPRODUCT((INDEX(final_df!$B$2:$ZZ$100,,MATCH($C7,final_df!$B$1:$ZZ$1,0))>0)*(final_df!$AM$2:$AM$100=H$1)) /COUNTIF(final_df!$AM$2:$AM$100, H$1) -> 0.73684211 | I7: =SUMPRODUCT((INDEX(final_df!$B$2:$ZZ$100,,MATCH($C7,final_df!$B$1:$ZZ$1,0))>0)*(final_df!$AM$2:$AM$100=I$1)) /COUNTIF(final_df!$AM$2:$AM$100, I$1) -> 0.52631579
A8: Jövőkép a társasházról | B8: Általános jövőkép | C8: Jövőkép a társasházról - Általános jövőkép | D8: =SUMPRODUCT((INDEX(final_df!$B$2:$ZZ$100,,MATCH(C8,final_df!$B$1:$ZZ$1,0))>0)*1)/56 -> 0.25 | E8: =SUMPRODUCT((INDEX(final_df!$B$2:$ZZ$100,,MATCH($C8,final_df!$B$1:$ZZ$1,0))>0)*(final_df!$E$2:$E$100=E$1)) /COUNTIF(final_df!$E$2:$E$100, E$1) -> 0.25 | F8: =SUMPRODUCT((INDEX(final_df!$B$2:$ZZ$100,,MATCH($C8,final_df!$B$1:$ZZ$1,0))>0)*(final_df!$E$2:$E$100=F$1)) /COUNTIF(final_df!$E$2:$E$100, F$1) -> 0.25 | G8: =SUMPRODUCT((INDEX(final_df!$B$2:$ZZ$100,,MATCH($C8,final_df!$B$1:$ZZ$1,0))>0)*(final_df!$AM$2:$AM$100=G$1)) /COUNTIF(final_df!$AM$2:$AM$100, G$1) -> 0.38888889 | H8: =SUMPRODUCT((INDEX(final_df!$B$2:$ZZ$100,,MATCH($C8,final_df!$B$1:$ZZ$1,0))>0)*(final_df!$AM$2:$AM$100=H$1)) /COUNTIF(final_df!$AM$2:$AM$100, H$1) -> 0.31578947 | I8: =SUMPRODUCT((INDEX(final_df!$B$2:$ZZ$100,,MATCH($C8,final_df!$B$1:$ZZ$1,0))>0)*(final_df!$AM$2:$AM$100=I$1)) /COUNTIF(final_df!$AM$2:$AM$100, I$1) -> 0.052631579
B9: Közös képviselet szerepe | C9: Jövőkép a társasházról - Közös képviselet szerepe | D9: =SUMPRODUCT((INDEX(final_df!$B$2:$ZZ$100,,MATCH(C9,final_df!$B$1:$ZZ$1,0))>0)*1)/56 -> 0.089285714 | E9: =SUMPRODUCT((INDEX(final_df!$B$2:$ZZ$100,,MATCH($C9,final_df!$B$1:$ZZ$1,0))>0)*(final_df!$E$2:$E$100=E$1)) /COUNTIF(final_df!$E$2:$E$100, E$1) -> 0.035714286 | F9: =SUMPRODUCT((INDEX(final_df!$B$2:$ZZ$100,,MATCH($C9,final_df!$B$1:$ZZ$1,0))>0)*(final_df!$E$2:$E$100=F$1)) /COUNTIF(final_df!$E$2:$E$100, F$1) -> 0.14285714 | G9: =SUMPRODUCT((INDEX(final_df!$B$2:$ZZ$100,,MATCH($C9,final_df!$B$1:$ZZ$1,0))>0)*(final_df!$AM$2:$AM$100=G$1)) /COUNTIF(final_df!$AM$2:$AM$100, G$1) -> 0.16666667 | H9: =SUMPRODUCT((INDEX(final_df!$B$2:$ZZ$100,,MATCH($C9,final_df!$B$1:$ZZ$1,0))>0)*(final_df!$AM$2:$AM$100=H$1)) /COUNTIF(final_df!$AM$2:$AM$100, H$1) -> 0.10526316 | I9: =SUMPRODUCT((INDEX(final_df!$B$2:$ZZ$100,,MATCH($C9,final_df!$B$1:$ZZ$1,0))>0)*(final_df!$AM$2:$AM$100=I$1)) /COUNTIF(final_df!$AM$2:$AM$100, I$1) -> 0
B10: Lakóközösség cseréje | C10: Jövőkép a társasházról - Lakóközösség cseréje | D10: =SUMPRODUCT((INDEX(final_df!$B$2:$ZZ$100,,MATCH(C10,final_df!$B$1:$ZZ$1,0))>0)*1)/56 -> 0.26785714 | E10: =SUMPRODUCT((INDEX(final_df!$B$2:$ZZ$100,,MATCH($C10,final_df!$B$1:$ZZ$1,0))>0)*(final_df!$E$2:$E$100=E$1)) /COUNTIF(final_df!$E$2:$E$100, E$1) -> 0.32142857 | F10: =SUMPRODUCT((INDEX(final_df!$B$2:$ZZ$100,,MATCH($C10,final_df!$B$1:$ZZ$1,0))>0)*(final_df!$E$2:$E$100=F$1)) /COUNTIF(final_df!$E$2:$E$100, F$1) -> 0.21428571 | G10: =SUMPRODUCT((INDEX(final_df!$B$2:$ZZ$100,,MATCH($C10,final_df!$B$1:$ZZ$1,0))>0)*(final_df!$AM$2:$AM$100=G$1)) /COUNTIF(final_df!$AM$2:$AM$100, G$1) -> 0.22222222 | H10: =SUMPRODUCT((INDEX(final_df!$B$2:$ZZ$100,,MATCH($C10,final_df!$B$1:$ZZ$1,0))>0)*(final_df!$AM$2:$AM$100=H$1)) /COUNTIF(final_df!$AM$2:$AM$100, H$1) -> 0.36842105 | I10: =SUMPRODUCT((INDEX(final_df!$B$2:$ZZ$100,,MATCH($C10,final_df!$B$1:$ZZ$1,0))>0)*(final_df!$AM$2:$AM$100=I$1)) /COUNTIF(final_df!$AM$2:$AM$100, I$1) -> 0.21052632
B11: Lakóközösség szerepe | C11: Jövőkép a társasházról - Lakóközösség szerepe | D11: =SUMPRODUCT((INDEX(final_df!$B$2:$ZZ$100,,MATCH(C11,final_df!$B$1:$ZZ$1,0))>0)*1)/56 -> 0.14285714 | E11: =SUMPRODUCT((INDEX(final_df!$B$2:$ZZ$100,,MATCH($C11,final_df!$B$1:$ZZ$1,0))>0)*(final_df!$E$2:$E$100=E$1)) /COUNTIF(final_df!$E$2:$E$100, E$1) -> 0.17857143 | F11: =SUMPRODUCT((INDEX(final_df!$B$2:$ZZ$100,,MATCH($C11,final_df!$B$1:$ZZ$1,0))>0)*(final_df!$E$2:$E$100=F$1)) /COUNTIF(final_df!$E$2:$E$100, F$1) -> 0.10714286 | G11: =SUMPRODUCT((INDEX(final_df!$B$2:$ZZ$100,,MATCH($C11,final_df!$B$1:$ZZ$1,0))>0)*(final_df!$AM$2:$AM$100=G$1)) /COUNTIF(final_df!$AM$2:$AM$100, G$1) -> 0.11111111 | H11: =SUMPRODUCT((INDEX(final_df!$B$2:$ZZ$100,,MATCH($C11,final_df!$B$1:$ZZ$1,0))>0)*(final_df!$AM$2:$AM$100=H$1)) /COUNTIF(final_df!$AM$2:$AM$100, H$1) -> 0.10526316 | I11: =SUMPRODUCT((INDEX(final_df!$B$2:$ZZ$100,,MATCH($C11,final_df!$B$1:$ZZ$1,0))>0)*(final_df!$AM$2:$AM$100=I$1)) /COUNTIF(final_df!$AM$2:$AM$100, I$1) -> 0.21052632
B12: Változtatná a társasházon | C12: Jövőkép a társasházról - Változtatná a társasházon | D12: =SUMPRODUCT((INDEX(final_df!$B$2:$ZZ$100,,MATCH(C12,final_df!$B$1:$ZZ$1,0))>0)*1)/56 -> 0.51785714 | E12: =SUMPRODUCT((INDEX(final_df!$B$2:$ZZ$100,,MATCH($C12,final_df!$B$1:$ZZ$1,0))>0)*(final_df!$E$2:$E$100=E$1)) /COUNTIF(final_df!$E$2:$E$100, E$1) -> 0.57142857 | F12: =SUMPRODUCT((INDEX(final_df!$B$2:$ZZ$100,,MATCH($C12,final_df!$B$1:$ZZ$1,0))>0)*(final_df!$E$2:$E$100=F$1)) /COUNTIF(final_df!$E$2:$E$100, F$1) -> 0.46428571 | G12: =SUMPRODUCT((INDEX(final_df!$B$2:$ZZ$100,,MATCH($C12,final_df!$B$1:$ZZ$1,0))>0)*(final_df!$AM$2:$AM$100=G$1)) /COUNTIF(final_df!$AM$2:$AM$100, G$1) -> 0.44444444 | H12: =SUMPRODUCT((INDEX(final_df!$B$2:$ZZ$100,,MATCH($C12,final_df!$B$1:$ZZ$1,0))>0)*(final_df!$AM$2:$AM$100=H$1)) /COUNTIF(final_df!$AM$2:$AM$100, H$1) -> 0.52631579 | I12: =SUMPRODUCT((INDEX(final_df!$B$2:$ZZ$100,,MATCH($C12,final_df!$B$1:$ZZ$1,0))>0)*(final_df!$AM$2:$AM$100=I$1)) /COUNTIF(final_df!$AM$2:$AM$100, I$1) -> 0.57894737
A13: Jövőkép az utcáról | B13: Jövőkép az utcáról | C13: Jövőkép az utcáról - Jövőkép az utcáról | D13: =SUMPRODUCT((INDEX(final_df!$B$2:$ZZ$100,,MATCH(C13,final_df!$B$1:$ZZ$1,0))>0)*1)/56 -> 0.55357143 | E13: =SUMPRODUCT((INDEX(final_df!$B$2:$ZZ$100,,MATCH($C13,final_df!$B$1:$ZZ$1,0))>0)*(final_df!$E$2:$E$100=E$1)) /COUNTIF(final_df!$E$2:$E$100, E$1) -> 0.5 | F13: =SUMPRODUCT((INDEX(final_df!$B$2:$ZZ$100,,MATCH($C13,final_df!$B$1:$ZZ$1,0))>0)*(final_df!$E$2:$E$100=F$1)) /COUNTIF(final_df!$E$2:$E$100, F$1) -> 0.60714286 | G13: =SUMPRODUCT((INDEX(final_df!$B$2:$ZZ$100,,MATCH($C13,final_df!$B$1:$ZZ$1,0))>0)*(final_df!$AM$2:$AM$100=G$1)) /COUNTIF(final_df!$AM$2:$AM$100, G$1) -> 0.27777778 | H13: =SUMPRODUCT((INDEX(final_df!$B$2:$ZZ$100,,MATCH($C13,final_df!$B$1:$ZZ$1,0))>0)*(final_df!$AM$2:$AM$100=H$1)) /COUNTIF(final_df!$AM$2:$AM$100, H$1) -> 0.68421053 | I13: =SUMPRODUCT((INDEX(final_df!$B$2:$ZZ$100,,MATCH($C13,final_df!$B$1:$ZZ$1,0))>0)*(final_df!$AM$2:$AM$100=I$1)) /COUNTIF(final_df!$AM$2:$AM$100, I$1) -> 0.68421053
A14: Lakhatási helyzet | B14: Elhelyezkedés | C14: Lakhatási helyzet - Elhelyezkedés | D14: =SUMPRODUCT((INDEX(final_df!$B$2:$ZZ$100,,MATCH(C14,final_df!$B$1:$ZZ$1,0))>0)*1)/56 -> 0.17857143 | E14: =SUMPRODUCT((INDEX(final_df!$B$2:$ZZ$100,,MATCH($C14,final_df!$B$1:$ZZ$1,0))>0)*(final_df!$E$2:$E$100=E$1)) /COUNTIF(final_df!$E$2:$E$100, E$1) -> 0.14285714 | F14: =SUMPRODUCT((INDEX(final_df!$B$2:$ZZ$100,,MATCH($C14,final_df!$B$1:$ZZ$1,0))>0)*(final_df!$E$2:$E$100=F$1)) /COUNTIF(final_df!$E$2:$E$100, F$1) -> 0.21428571 | G14: =SUMPRODUCT((INDEX(final_df!$B$2:$ZZ$100,,MATCH($C14,final_df!$B$1:$ZZ$1,0))>0)*(final_df!$AM$2:$AM$100=G$1)) /COUNTIF(final_df!$AM$2:$AM$100, G$1) -> 0.11111111 | H14: =SUMPRODUCT((INDEX(final_df!$B$2:$ZZ$100,,MATCH($C14,final_df!$B$1:$ZZ$1,0))>0)*(final_df!$AM$2:$AM$100=H$1)) /COUNTIF(final_df!$AM$2:$AM$100, H$1) -> 0.21052632 | I14: =SUMPRODUCT((INDEX(final_df!$B$2:$ZZ$100,,MATCH($C14,final_df!$B$1:$ZZ$1,0))>0)*(final_df!$AM$2:$AM$100=I$1)) /COUNTIF(final_df!$AM$2:$AM$100, I$1) -> 0.21052632
B15: Komfortszint | C15: Lakhatási helyzet - Komfortszint | D15: =SUMPRODUCT((INDEX(final_df!$B$2:$ZZ$100,,MATCH(C15,final_df!$B$1:$ZZ$1,0))>0)*1)/56 -> 0.33928571 | E15: =SUMPRODUCT((INDEX(final_df!$B$2:$ZZ$100,,MATCH($C15,final_df!$B$1:$ZZ$1,0))>0)*(final_df!$E$2:$E$100=E$1)) /COUNTIF(final_df!$E$2:$E$100, E$1) -> 0.28571429 | F15: =SUMPRODUCT((INDEX(final_df!$B$2:$ZZ$100,,MATCH($C15,final_df!$B$1:$ZZ$1,0))>0)*(final_df!$E$2:$E$100=F$1)) /COUNTIF(final_df!$E$2:$E$100, F$1) -> 0.39285714 | G15: =SUMPRODUCT((INDEX(final_df!$B$2:$ZZ$100,,MATCH($C15,final_df!$B$1:$ZZ$1,0))>0)*(final_df!$AM$2:$AM$100=G$1)) /COUNTIF(final_df!$AM$2:$AM$100, G$1) -> 0.22222222 | H15: =SUMPRODUCT((INDEX(final_df!$B$2:$ZZ$100,,MATCH($C15,final_df!$B$1:$ZZ$1,0))>0)*(final_df!$AM$2:$AM$100=H$1)) /COUNTIF(final_df!$AM$2:$AM$100, H$1) -> 0.31578947 | I15: =SUMPRODUCT((INDEX(final_df!$B$2:$ZZ$100,,MATCH($C15,final_df!$B$1:$ZZ$1,0))>0)*(final_df!$AM$2:$AM$100=I$1)) /COUNTIF(final_df!$AM$2:$AM$100, I$1) -> 0.47368421
A16: Önkormányzati szerep | B16: Jelenleg | C16: Önkormányzati szerep - Jelenleg | D16: =SUMPRODUCT((INDEX(final_df!$B$2:$ZZ$100,,MATCH(C16,final_df!$B$1:$ZZ$1,0))>0)*1)/56 -> 0.375 | E16: =SUMPRODUCT((INDEX(final_df!$B$2:$ZZ$100,,MATCH($C16,final_df!$B$1:$ZZ$1,0))>0)*(final_df!$E$2:$E$100=E$1)) /COUNTIF(final_df!$E$2:$E$100, E$1) -> 0.25 | F16: =SUMPRODUCT((INDEX(final_df!$B$2:$ZZ$100,,MATCH($C16,final_df!$B$1:$ZZ$1,0))>0)*(final_df!$E$2:$E$100=F$1)) /COUNTIF(final_df!$E$2:$E$100, F$1) -> 0.5 | G16: =SUMPRODUCT((INDEX(final_df!$B$2:$ZZ$100,,MATCH($C16,final_df!$B$1:$ZZ$1,0))>0)*(final_df!$AM$2:$AM$100=G$1)) /COUNTIF(final_df!$AM$2:$AM$100, G$1) -> 0.55555556 | H16: =SUMPRODUCT((INDEX(final_df!$B$2:$ZZ$100,,MATCH($C16,final_df!$B$1:$ZZ$1,0))>0)*(final_df!$AM$2:$AM$100=H$1)) /COUNTIF(final_df!$AM$2:$AM$100, H$1) -> 0.36842105 | I16: =SUMPRODUCT((INDEX(final_df!$B$2:$ZZ$100,,MATCH($C16,final_df!$B$1:$ZZ$1,0))>0)*(final_df!$AM$2:$AM$100=I$1)) /COUNTIF(final_df!$AM$2:$AM$100, I$1) -> 0.21052632
B17: Jövőre - Társasháznál | C17: Önkormányzati szerep - Jövőre - Társasháznál | D17: =SUMPRODUCT((INDEX(final_df!$B$2:$ZZ$100,,MATCH(C17,final_df!$B$1:$ZZ$1,0))>0)*1)/56 -> 0.071428571 | E17: =SUMPRODUCT((INDEX(final_df!$B$2:$ZZ$100,,MATCH($C17,final_df!$B$1:$ZZ$1,0))>0)*(final_df!$E$2:$E$100=E$1)) /COUNTIF(final_df!$E$2:$E$100, E$1) -> 0.071428571 | F17: =SUMPRODUCT((INDEX(final_df!$B$2:$ZZ$100,,MATCH($C17,final_df!$B$1:$ZZ$1,0))>0)*(final_df!$E$2:$E$100=F$1)) /COUNTIF(final_df!$E$2:$E$100, F$1) -> 0.071428571 | G17: =SUMPRODUCT((INDEX(final_df!$B$2:$ZZ$100,,MATCH($C17,final_df!$B$1:$ZZ$1,0))>0)*(final_df!$AM$2:$AM$100=G$1)) /COUNTIF(final_df!$AM$2:$AM$100, G$1) -> 0.11111111 | H17: =SUMPRODUCT((INDEX(final_df!$B$2:$ZZ$100,,MATCH($C17,final_df!$B$1:$ZZ$1,0))>0)*(final_df!$AM$2:$AM$100=H$1)) /COUNTIF(final_df!$AM$2:$AM$100, H$1) -> 0.052631579 | I17: =SUMPRODUCT((INDEX(final_df!$B$2:$ZZ$100,,MATCH($C17,final_df!$B$1:$ZZ$1,0))>0)*(final_df!$AM$2:$AM$100=I$1)) /COUNTIF(final_df!$AM$2:$AM$100, I$1) -> 0.052631579
B18: Jövőre - Utcánál | C18: Önkormányzati szerep - Jövőre - Utcánál | D18: =SUMPRODUCT((INDEX(final_df!$B$2:$ZZ$100,,MATCH(C18,final_df!$B$1:$ZZ$1,0))>0)*1)/56 -> 0.25 | E18: =SUMPRODUCT((INDEX(final_df!$B$2:$ZZ$100,,MATCH($C18,final_df!$B$1:$ZZ$1,0))>0)*(final_df!$E$2:$E$100=E$1)) /COUNTIF(final_df!$E$2:$E$100, E$1) -> 0.25 | F18: =SUMPRODUCT((INDEX(final_df!$B$2:$ZZ$100,,MATCH($C18,final_df!$B$1:$ZZ$1,0))>0)*(final_df!$E$2:$E$100=F$1)) /COUNTIF(final_df!$E$2:$E$100, F$1) -> 0.25 | G18: =SUMPRODUCT((INDEX(final_df!$B$2:$ZZ$100,,MATCH($C18,final_df!$B$1:$ZZ$1,0))>0)*(final_df!$AM$2:$AM$100=G$1)) /COUNTIF(final_df!$AM$2:$AM$100, G$1) -> 0.27777778 | H18: =SUMPRODUCT((INDEX(final_df!$B$2:$ZZ$100,,MATCH($C18,final_df!$B$1:$ZZ$1,0))>0)*(final_df!$AM$2:$AM$100=H$1)) /COUNTIF(final_df!$AM$2:$AM$100, H$1) -> 0.36842105 | I18: =SUMPRODUCT((INDEX(final_df!$B$2:$ZZ$100,,MATCH($C18,final_df!$B$1:$ZZ$1,0))>0)*(final_df!$AM$2:$AM$100=I$1)) /COUNTIF(final_df!$AM$2:$AM$100, I$1) -> 0.10526316
A19: Pozitív / Negatív | B19: Negatív | C19: Pozitív / Negatív - Negatív | D19: =SUMPRODUCT((INDEX(final_df!$B$2:$ZZ$100,,MATCH(C19,final_df!$B$1:$ZZ$1,0))>0)*1)/56 -> 0.94642857 | E19: =SUMPRODUCT((INDEX(final_df!$B$2:$ZZ$100,,MATCH($C19,final_df!$B$1:$ZZ$1,0))>0)*(final_df!$E$2:$E$100=E$1)) /COUNTIF(final_df!$E$2:$E$100, E$1) -> 0.96428571 | F19: =SUMPRODUCT((INDEX(final_df!$B$2:$ZZ$100,,MATCH($C19,final_df!$B$1:$ZZ$1,0))>0)*(final_df!$E$2:$E$100=F$1)) /COUNTIF(final_df!$E$2:$E$100, F$1) -> 0.92857143 | G19: =SUMPRODUCT((INDEX(final_df!$B$2:$ZZ$100,,MATCH($C19,final_df!$B$1:$ZZ$1,0))>0)*(final_df!$AM$2:$AM$100=G$1)) /COUNTIF(final_df!$AM$2:$AM$100, G$1) -> 0.94444444 | H19: =SUMPRODUCT((INDEX(final_df!$B$2:$ZZ$100,,MATCH($C19,final_df!$B$1:$ZZ$1,0))>0)*(final_df!$AM$2:$AM$100=H$1)) /COUNTIF(final_df!$AM$2:$AM$100, H$1) -> 0.94736842 | I19: =SUMPRODUCT((INDEX(final_df!$B$2:$ZZ$100,,MATCH($C19,final_df!$B$1:$ZZ$1,0))>0)*(final_df!$AM$2:$AM$100=I$1)) /COUNTIF(final_df!$AM$2:$AM$100, I$1) -> 0.94736842
B20: Pozitív | C20: Pozitív / Negatív - Pozitív | D20: =SUMPRODUCT((INDEX(final_df!$B$2:$ZZ$100,,MATCH(C20,final_df!$B$1:$ZZ$1,0))>0)*1)/56 -> 0.96428571 | E20: =SUMPRODUCT((INDEX(final_df!$B$2:$ZZ$100,,MATCH($C20,final_df!$B$1:$ZZ$1,0))>0)*(final_df!$E$2:$E$100=E$1)) /COUNTIF(final_df!$E$2:$E$100, E$1) -> 0.92857143 | F20: =SUMPRODUCT((INDEX(final_df!$B$2:$ZZ$100,,MATCH($C20,final_df!$B$1:$ZZ$1,0))>0)*(final_df!$E$2:$E$100=F$1)) /COUNTIF(final_df!$E$2:$E$100, F$1) -> 1 | G20: =SUMPRODUCT((INDEX(final_df!$B$2:$ZZ$100,,MATCH($C20,final_df!$B$1:$ZZ$1,0))>0)*(final_df!$AM$2:$AM$100=G$1)) /COUNTIF(final_df!$AM$2:$AM$100, G$1) -> 1 | H20: =SUMPRODUCT((INDEX(final_df!$B$2:$ZZ$100,,MATCH($C20,final_df!$B$1:$ZZ$1,0))>0)*(final_df!$AM$2:$AM$100=H$1)) /COUNTIF(final_df!$AM$2:$AM$100, H$1) -> 0.94736842 | I20: =SUMPRODUCT((INDEX(final_df!$B$2:$ZZ$100,,MATCH($C20,final_df!$B$1:$ZZ$1,0))>0)*(final_df!$AM$2:$AM$100=I$1)) /COUNTIF(final_df!$AM$2:$AM$100, I$1) -> 0.94736842
A21: Társasházak működése (jelenleg) | B21: Biztonság | C21: Társasházak működése (jelenleg) - Biztonság | D21: =SUMPRODUCT((INDEX(final_df!$B$2:$ZZ$100,,MATCH(C21,final_df!$B$1:$ZZ$1,0))>0)*1)/56 -> 0.44642857 | E21: =SUMPRODUCT((INDEX(final_df!$B$2:$ZZ$100,,MATCH($C21,final_df!$B$1:$ZZ$1,0))>0)*(final_df!$E$2:$E$100=E$1)) /COUNTIF(final_df!$E$2:$E$100, E$1) -> 0.39285714 | F21: =SUMPRODUCT((INDEX(final_df!$B$2:$ZZ$100,,MATCH($C21,final_df!$B$1:$ZZ$1,0))>0)*(final_df!$E$2:$E$100=F$1)) /COUNTIF(final_df!$E$2:$E$100, F$1) -> 0.5 | G21: =SUMPRODUCT((INDEX(final_df!$B$2:$ZZ$100,,MATCH($C21,final_df!$B$1:$ZZ$1,0))>0)*(final_df!$AM$2:$AM$100=G$1)) /COUNTIF(final_df!$AM$2:$AM$100, G$1) -> 0.33333333 | H21: =SUMPRODUCT((INDEX(final_df!$B$2:$ZZ$100,,MATCH($C21,final_df!$B$1:$ZZ$1,0))>0)*(final_df!$AM$2:$AM$100=H$1)) /COUNTIF(final_df!$AM$2:$AM$100, H$1) -> 0.63157895 | I21: =SUMPRODUCT((INDEX(final_df!$B$2:$ZZ$100,,MATCH($C21,final_df!$B$1:$ZZ$1,0))>0)*(final_df!$AM$2:$AM$100=I$1)) /COUNTIF(final_df!$AM$2:$AM$100, I$1) -> 0.36842105
B22: Fizikai állapot / karbantartás | C22: Társasházak működése (jelenleg) - Fizikai állapot / karbantartás | D22: =SUMPRODUCT((INDEX(final_df!$B$2:$ZZ$100,,MATCH(C22,final_df!$B$1:$ZZ$1,0))>0)*1)/56 -> 0.75 | E22: =SUMPRODUCT((INDEX(final_df!$B$2:$ZZ$100,,MATCH($C22,final_df!$B$1:$ZZ$1,0))>0)*(final_df!$E$2:$E$100=E$1)) /COUNTIF(final_df!$E$2:$E$100, E$1) -> 0.75 | F22: =SUMPRODUCT((INDEX(final_df!$B$2:$ZZ$100,,MATCH($C22,final_df!$B$1:$ZZ$1,0))>0)*(final_df!$E$2:$E$100=F$1)) /COUNTIF(final_df!$E$2:$E$100, F$1) -> 0.75 | G22: =SUMPRODUCT((INDEX(final_df!$B$2:$ZZ$100,,MATCH($C22,final_df!$B$1:$ZZ$1,0))>0)*(final_df!$AM$2:$AM$100=G$1)) /COUNTIF(final_df!$AM$2:$AM$100, G$1) -> 0.88888889 | H22: =SUMPRODUCT((INDEX(final_df!$B$2:$ZZ$100,,MATCH($C22,final_df!$B$1:$ZZ$1,0))>0)*(final_df!$AM$2:$AM$100=H$1)) /COUNTIF(final_df!$AM$2:$AM$100, H$1) -> 0.73684211 | I22: =SUMPRODUCT((INDEX(final_df!$B$2:$ZZ$100,,MATCH($C22,final_df!$B$1:$ZZ$1,0))>0)*(final_df!$AM$2:$AM$100=I$1)) /COUNTIF(final_df!$AM$2:$AM$100, I$1) -> 0.63157895
B23: Közös képviselet | C23: Társasházak működése (jelenleg) - Közös képviselet | D23: =SUMPRODUCT((INDEX(final_df!$B$2:$ZZ$100,,MATCH(C23,final_df!$B$1:$ZZ$1,0))>0)*1)/56 -> 0.5 | E23: =SUMPRODUCT((INDEX(final_df!$B$2:$ZZ$100,,MATCH($C23,final_df!$B$1:$ZZ$1,0))>0)*(final_df!$E$2:$E$100=E$1)) /COUNTIF(final_df!$E$2:$E$100, E$1) -> 0.46428571 | F23: =SUMPRODUCT((INDEX(final_df!$B$2:$ZZ$100,,MATCH($C23,final_df!$B$1:$ZZ$1,0))>0)*(final_df!$E$2:$E$100=F$1)) /COUNTIF(final_df!$E$2:$E$100, F$1) -> 0.53571429 | G23: =SUMPRODUCT((INDEX(final_df!$B$2:$ZZ$100,,MATCH($C23,final_df!$B$1:$ZZ$1,0))>0)*(final_df!$AM$2:$AM$100=G$1)) /COUNTIF(final_df!$AM$2:$AM$100, G$1) -> 0.55555556 | H23: =SUMPRODUCT((INDEX(final_df!$B$2:$ZZ$100,,MATCH($C23,final_df!$B$1:$ZZ$1,0))>0)*(final_df!$AM$2:$AM$100=H$1)) /COUNTIF(final_df!$AM$2:$AM$100, H$1) -> 0.68421053 | I23: =SUMPRODUCT((INDEX(final_df!$B$2:$ZZ$100,,MATCH($C23,final_df!$B$1:$ZZ$1,0))>0)*(final_df!$AM$2:$AM$100=I$1)) /COUNTIF(final_df!$AM$2:$AM$100, I$1) -> 0.26315789
B24: Közös terek használata | C24: Társasházak működése (jelenleg) - Közös terek használata | D24: =SUMPRODUCT((INDEX(final_df!$B$2:$ZZ$100,,MATCH(C24,final_df!$B$1:$ZZ$1,0))>0)*1)/56 -> 0.26785714 | E24: =SUMPRODUCT((INDEX(final_df!$B$2:$ZZ$100,,MATCH($C24,final_df!$B$1:$ZZ$1,0))>0)*(final_df!$E$2:$E$100=E$1)) /COUNTIF(final_df!$E$2:$E$100, E$1) -> 0.35714286 | F24: =SUMPRODUCT((INDEX(final_df!$B$2:$ZZ$100,,MATCH($C24,final_df!$B$1:$ZZ$1,0))>0)*(final_df!$E$2:$E$100=F$1)) /COUNTIF(final_df!$E$2:$E$100, F$1) -> 0.17857143 | G24: =SUMPRODUCT((INDEX(final_df!$B$2:$ZZ$100,,MATCH($C24,final_df!$B$1:$ZZ$1,0))>0)*(final_df!$AM$2:$AM$100=G$1)) /COUNTIF(final_df!$AM$2:$AM$100, G$1) -> 0.22222222 | H24: =SUMPRODUCT((INDEX(final_df!$B$2:$ZZ$100,,MATCH($C24,final_df!$B$1:$ZZ$1,0))>0)*(final_df!$AM$2:$AM$100=H$1)) /COUNTIF(final_df!$AM$2:$AM$100, H$1) -> 0.26315789 | I24: =SUMPRODUCT((INDEX(final_df!$B$2:$ZZ$100,,MATCH($C24,final_df!$B$1:$ZZ$1,0))>0)*(final_df!$AM$2:$AM$100=I$1)) /COUNTIF(final_df!$AM$2:$AM$100, I$1) -> 0.31578947
B25: Közösségi élet | C25: Társasházak működése (jelenleg) - Közösségi élet | D25: =SUMPRODUCT((INDEX(final_df!$B$2:$ZZ$100,,MATCH(C25,final_df!$B$1:$ZZ$1,0))>0)*1)/56 -> 0.69642857 | E25: =SUMPRODUCT((INDEX(final_df!$B$2:$ZZ$100,,MATCH($C25,final_df!$B$1:$ZZ$1,0))>0)*(final_df!$E$2:$E$100=E$1)) /COUNTIF(final_df!$E$2:$E$100, E$1) -> 0.57142857 | F25: =SUMPRODUCT((INDEX(final_df!$B$2:$ZZ$100,,MATCH($C25,final_df!$B$1:$ZZ$1,0))>0)*(final_df!$E$2:$E$100=F$1)) /COUNTIF(final_df!$E$2:$E$100, F$1) -> 0.82142857 | G25: =SUMPRODUCT((INDEX(final_df!$B$2:$ZZ$100,,MATCH($C25,final_df!$B$1:$ZZ$1,0))>0)*(final_df!$AM$2:$AM$100=G$1)) /COUNTIF(final_df!$AM$2:$AM$100, G$1) -> 0.66666667 | H25: =SUMPRODUCT((INDEX(final_df!$B$2:$ZZ$100,,MATCH($C25,final_df!$B$1:$ZZ$1,0))>0)*(final_df!$AM$2:$AM$100=H$1)) /COUNTIF(final_df!$AM$2:$AM$100, H$1) -> 0.73684211 | I25: =SUMPRODUCT((INDEX(final_df!$B$2:$ZZ$100,,MATCH($C25,final_df!$B$1:$ZZ$1,0))>0)*(final_df!$AM$2:$AM$100=I$1)) /COUNTIF(final_df!$AM$2:$AM$100, I$1) -> 0.68421053
B26: Lakóközösség változása | C26: Társasházak működése (jelenleg) - Lakóközösség változása | D26: =SUMPRODUCT((INDEX(final_df!$B$2:$ZZ$100,,MATCH(C26,final_df!$B$1:$ZZ$1,0))>0)*1)/56 -> 0.57142857 | E26: =SUMPRODUCT((INDEX(final_df!$B$2:$ZZ$100,,MATCH($C26,final_df!$B$1:$ZZ$1,0))>0)*(final_df!$E$2:$E$100=E$1)) /COUNTIF(final_df!$E$2:$E$100, E$1) -> 0.57142857 | F26: =SUMPRODUCT((INDEX(final_df!$B$2:$ZZ$100,,MATCH($C26,final_df!$B$1:$ZZ$1,0))>0)*(final_df!$E$2:$E$100=F$1)) /COUNTIF(final_df!$E$2:$E$100, F$1) -> 0.57142857 | G26: =SUMPRODUCT((INDEX(final_df!$B$2:$ZZ$100,,MATCH($C26,final_df!$B$1:$ZZ$1,0))>0)*(final_df!$AM$2:$AM$100=G$1)) /COUNTIF(final_df!$AM$2:$AM$100, G$1) -> 0.66666667 | H26: =SUMPRODUCT((INDEX(final_df!$B$2:$ZZ$100,,MATCH($C26,final_df!$B$1:$ZZ$1,0))>0)*(final_df!$AM$2:$AM$100=H$1)) /COUNTIF(final_df!$AM$2:$AM$100, H$1) -> 0.73684211 | I26: =SUMPRODUCT((INDEX(final_df!$B$2:$ZZ$100,,MATCH($C26,final_df!$B$1:$ZZ$1,0))>0)*(final_df!$AM$2:$AM$100=I$1)) /COUNTIF(final_df!$AM$2:$AM$100, I$1) -> 0.31578947
A27: Utca változásai | B27: Fizikai környezet és utcakép változásai | C27: Utca változásai - Fizikai környezet és utcakép változásai | D27: =SUMPRODUCT((INDEX(final_df!$B$2:$ZZ$100,,MATCH(C27,final_df!$B$1:$ZZ$1,0))>0)*1)/56 -> 0.44642857 | E27: =SUMPRODUCT((INDEX(final_df!$B$2:$ZZ$100,,MATCH($C27,final_df!$B$1:$ZZ$1,0))>0)*(final_df!$E$2:$E$100=E$1)) /COUNTIF(final_df!$E$2:$E$100, E$1) -> 0.46428571 | F27: =SUMPRODUCT((INDEX(final_df!$B$2:$ZZ$100,,MATCH($C27,final_df!$B$1:$ZZ$1,0))>0)*(final_df!$E$2:$E$100=F$1)) /COUNTIF(final_df!$E$2:$E$100, F$1) -> 0.42857143 | G27: =SUMPRODUCT((INDEX(final_df!$B$2:$ZZ$100,,MATCH($C27,final_df!$B$1:$ZZ$1,0))>0)*(final_df!$AM$2:$AM$100=G$1)) /COUNTIF(final_df!$AM$2:$AM$100, G$1) -> 0.5 | H27: =SUMPRODUCT((INDEX(final_df!$B$2:$ZZ$100,,MATCH($C27,final_df!$B$1:$ZZ$1,0))>0)*(final_df!$AM$2:$AM$100=H$1)) /COUNTIF(final_df!$AM$2:$AM$100, H$1) -> 0.52631579 | I27: =SUMPRODUCT((INDEX(final_df!$B$2:$ZZ$100,,MATCH($C27,final_df!$B$1:$ZZ$1,0))>0)*(final_df!$AM$2:$AM$100=I$1)) /COUNTIF(final_df!$AM$2:$AM$100, I$1) -> 0.31578947
B28: Közbiztonság és közterületi viselkedés | C28: Utca változásai - Közbiztonság és közterületi viselkedés | D28: =SUMPRODUCT((INDEX(final_df!$B$2:$ZZ$100,,MATCH(C28,final_df!$B$1:$ZZ$1,0))>0)*1)/56 -> 0.32142857 | E28: =SUMPRODUCT((INDEX(final_df!$B$2:$ZZ$100,,MATCH($C28,final_df!$B$1:$ZZ$1,0))>0)*(final_df!$E$2:$E$100=E$1)) /COUNTIF(final_df!$E$2:$E$100, E$1) -> 0.28571429 | F28: =SUMPRODUCT((INDEX(final_df!$B$2:$ZZ$100,,MATCH($C28,final_df!$B$1:$ZZ$1,0))>0)*(final_df!$E$2:$E$100=F$1)) /COUNTIF(final_df!$E$2:$E$100, F$1) -> 0.35714286 | G28: =SUMPRODUCT((INDEX(final_df!$B$2:$ZZ$100,,MATCH($C28,final_df!$B$1:$ZZ$1,0))>0)*(final_df!$AM$2:$AM$100=G$1)) /COUNTIF(final_df!$AM$2:$AM$100, G$1) -> 0.38888889 | H28: =SUMPRODUCT((INDEX(final_df!$B$2:$ZZ$100,,MATCH($C28,final_df!$B$1:$ZZ$1,0))>0)*(final_df!$AM$2:$AM$100=H$1)) /COUNTIF(final_df!$AM$2:$AM$100, H$1) -> 0.31578947 | I28: =SUMPRODUCT((INDEX(final_df!$B$2:$ZZ$100,,MATCH($C28,final_df!$B$1:$ZZ$1,0))>0)*(final_df!$AM$2:$AM$100=I$1)) /COUNTIF(final_df!$AM$2:$AM$100, I$1) -> 0.26315789
B29: Lakossági összetétel / közösségek | C29: Utca változásai - Lakossági összetétel / közösségek | D29: =SUMPRODUCT((INDEX(final_df!$B$2:$ZZ$100,,MATCH(C29,final_df!$B$1:$ZZ$1,0))>0)*1)/56 -> 0.41071429 | E29: =SUMPRODUCT((INDEX(final_df!$B$2:$ZZ$100,,MATCH($C29,final_df!$B$1:$ZZ$1,0))>0)*(final_df!$E$2:$E$100=E$1)) /COUNTIF(final_df!$E$2:$E$100, E$1) -> 0.28571429 | F29: =SUMPRODUCT((INDEX(final_df!$B$2:$ZZ$100,,MATCH($C29,final_df!$B$1:$ZZ$1,0))>0)*(final_df!$E$2:$E$100=F$1)) /COUNTIF(final_df!$E$2:$E$100, F$1) -> 0.53571429 | G29: =SUMPRODUCT((INDEX(final_df!$B$2:$ZZ$100,,MATCH($C29,final_df!$B$1:$ZZ$1,0))>0)*(final_df!$AM$2:$AM$100=G$1)) /COUNTIF(final_df!$AM$2:$AM$100, G$1) -> 0.55555556 | H29: =SUMPRODUCT((INDEX(final_df!$B$2:$ZZ$100,,MATCH($C29,final_df!$B$1:$ZZ$1,0))>0)*(final_df!$AM$2:$AM$100=H$1)) /COUNTIF(final_df!$AM$2:$AM$100, H$1) -> 0.42105263 | I29: =SUMPRODUCT((INDEX(final_df!$B$2:$ZZ$100,,MATCH($C29,final_df!$B$1:$ZZ$1,0))>0)*(final_df!$AM$2:$AM$100=I$1)) /COUNTIF(final_df!$AM$2:$AM$100, I$1) -> 0.26315789
B30: Üzletek / szolgáltatások / vendéglátás | C30: Utca változásai - Üzletek / szolgáltatások / vendéglátás | D30: =SUMPRODUCT((INDEX(final_df!$B$2:$ZZ$100,,MATCH(C30,final_df!$B$1:$ZZ$1,0))>0)*1)/56 -> 0.41071429 | E30: =SUMPRODUCT((INDEX(final_df!$B$2:$ZZ$100,,MATCH($C30,final_df!$B$1:$ZZ$1,0))>0)*(final_df!$E$2:$E$100=E$1)) /COUNTIF(final_df!$E$2:$E$100, E$1) -> 0.32142857 | F30: =SUMPRODUCT((INDEX(final_df!$B$2:$ZZ$100,,MATCH($C30,final_df!$B$1:$ZZ$1,0))>0)*(final_df!$E$2:$E$100=F$1)) /COUNTIF(final_df!$E$2:$E$100, F$1) -> 0.5 | G30: =SUMPRODUCT((INDEX(final_df!$B$2:$ZZ$100,,MATCH($C30,final_df!$B$1:$ZZ$1,0))>0)*(final_df!$AM$2:$AM$100=G$1)) /COUNTIF(final_df!$AM$2:$AM$100, G$1) -> 0.5 | H30: =SUMPRODUCT((INDEX(final_df!$B$2:$ZZ$100,,MATCH($C30,final_df!$B$1:$ZZ$1,0))>0)*(final_df!$AM$2:$AM$100=H$1)) /COUNTIF(final_df!$AM$2:$AM$100, H$1) -> 0.52631579 | I30: =SUMPRODUCT((INDEX(final_df!$B$2:$ZZ$100,,MATCH($C30,final_df!$B$1:$ZZ$1,0))>0)*(final_df!$AM$2:$AM$100=I$1)) /COUNTIF(final_df!$AM$2:$AM$100, I$1) -> 0.21052632
A31: Utcahasználat (jelenleg) | B31: Közlekedési élmények | C31: Utcahasználat (jelenleg) - Közlekedési élmények | D31: =SUMPRODUCT((INDEX(final_df!$B$2:$ZZ$100,,MATCH(C31,final_df!$B$1:$ZZ$1,0))>0)*1)/56 -> 0.51785714 | E31: =SUMPRODUCT((INDEX(final_df!$B$2:$ZZ$100,,MATCH($C31,final_df!$B$1:$ZZ$1,0))>0)*(final_df!$E$2:$E$100=E$1)) /COUNTIF(final_df!$E$2:$E$100, E$1) -> 0.46428571 | F31: =SUMPRODUCT((INDEX(final_df!$B$2:$ZZ$100,,MATCH($C31,final_df!$B$1:$ZZ$1,0))>0)*(final_df!$E$2:$E$100=F$1)) /COUNTIF(final_df!$E$2:$E$100, F$1) -> 0.57142857 | G31: =SUMPRODUCT((INDEX(final_df!$B$2:$ZZ$100,,MATCH($C31,final_df!$B$1:$ZZ$1,0))>0)*(final_df!$AM$2:$AM$100=G$1)) /COUNTIF(final_df!$AM$2:$AM$100, G$1) -> 0.5 | H31: =SUMPRODUCT((INDEX(final_df!$B$2:$ZZ$100,,MATCH($C31,final_df!$B$1:$ZZ$1,0))>0)*(final_df!$AM$2:$AM$100=H$1)) /COUNTIF(final_df!$AM$2:$AM$100, H$1) -> 0.57894737 | I31: =SUMPRODUCT((INDEX(final_df!$B$2:$ZZ$100,,MATCH($C31,final_df!$B$1:$ZZ$1,0))>0)*(final_df!$AM$2:$AM$100=I$1)) /COUNTIF(final_df!$AM$2:$AM$100, I$1) -> 0.47368421
B32: Közösségi interakciók az utcán | C32: Utcahasználat (jelenleg) - Közösségi interakciók az utcán | D32: =SUMPRODUCT((INDEX(final_df!$B$2:$ZZ$100,,MATCH(C32,final_df!$B$1:$ZZ$1,0))>0)*1)/56 -> 0.21428571 | E32: =SUMPRODUCT((INDEX(final_df!$B$2:$ZZ$100,,MATCH($C32,final_df!$B$1:$ZZ$1,0))>0)*(final_df!$E$2:$E$100=E$1)) /COUNTIF(final_df!$E$2:$E$100, E$1) -> 0.21428571 | F32: =SUMPRODUCT((INDEX(final_df!$B$2:$ZZ$100,,MATCH($C32,final_df!$B$1:$ZZ$1,0))>0)*(final_df!$E$2:$E$100=F$1)) /COUNTIF(final_df!$E$2:$E$100, F$1) -> 0.21428571 | G32: =SUMPRODUCT((INDEX(final_df!$B$2:$ZZ$100,,MATCH($C32,final_df!$B$1:$ZZ$1,0))>0)*(final_df!$AM$2:$AM$100=G$1)) /COUNTIF(final_df!$AM$2:$AM$100, G$1) -> 0.055555556 | H32: =SUMPRODUCT((INDEX(final_df!$B$2:$ZZ$100,,MATCH($C32,final_df!$B$1:$ZZ$1,0))>0)*(final_df!$AM$2:$AM$100=H$1)) /COUNTIF(final_df!$AM$2:$AM$100, H$1) -> 0.31578947 | I32: =SUMPRODUCT((INDEX(final_df!$B$2:$ZZ$100,,MATCH($C32,final_df!$B$1:$ZZ$1,0))>0)*(final_df!$AM$2:$AM$100=I$1)) /COUNTIF(final_df!$AM$2:$AM$100, I$1) -> 0.26315789
B33: Közterület használata | C33: Utcahasználat (jelenleg) - Közterület használata | D33: =SUMPRODUCT((INDEX(final_df!$B$2:$ZZ$100,,MATCH(C33,final_df!$B$1:$ZZ$1,0))>0)*1)/56 -> 0.33928571 | E33: =SUMPRODUCT((INDEX(final_df!$B$2:$ZZ$100,,MATCH($C33,final_df!$B$1:$ZZ$1,0))>0)*(final_df!$E$2:$E$100=E$1)) /COUNTIF(final_df!$E$2:$E$100, E$1) -> 0.39285714 | F33: =SUMPRODUCT((INDEX(final_df!$B$2:$ZZ$100,,MATCH($C33,final_df!$B$1:$ZZ$1,0))>0)*(final_df!$E$2:$E$100=F$1)) /COUNTIF(final_df!$E$2:$E$100, F$1) -> 0.28571429 | G33: =SUMPRODUCT((INDEX(final_df!$B$2:$ZZ$100,,MATCH($C33,final_df!$B$1:$ZZ$1,0))>0)*(final_df!$AM$2:$AM$100=G$1)) /COUNTIF(final_df!$AM$2:$AM$100, G$1) -> 0.38888889 | H33: =SUMPRODUCT((INDEX(final_df!$B$2:$ZZ$100,,MATCH($C33,final_df!$B$1:$ZZ$1,0))>0)*(final_df!$AM$2:$AM$100=H$1)) /COUNTIF(final_df!$AM$2:$AM$100, H$1) -> 0.21052632 | I33: =SUMPRODUCT((INDEX(final_df!$B$2:$ZZ$100,,MATCH($C33,final_df!$B$1:$ZZ$1,0))>0)*(final_df!$AM$2:$AM$100=I$1)) /COUNTIF(final_df!$AM$2:$AM$100, I$1) -> 0.42105263
B34: Szabadidő / szórakozás / vendéglátás | C34: Utcahasználat (jelenleg) - Szabadidő / szórakozás / vendéglátás | D34: =SUMPRODUCT((INDEX(final_df!$B$2:$ZZ$100,,MATCH(C34,final_df!$B$1:$ZZ$1,0))>0)*1)/56 -> 0.625 | E34: =SUMPRODUCT((INDEX(final_df!$B$2:$ZZ$100,,MATCH($C34,final_df!$B$1:$ZZ$1,0))>0)*(final_df!$E$2:$E$100=E$1)) /COUNTIF(final_df!$E$2:$E$100, E$1) -> 0.60714286 | F34: =SUMPRODUCT((INDEX(final_df!$B$2:$ZZ$100,,MATCH($C34,final_df!$B$1:$ZZ$1,0))>0)*(final_df!$E$2:$E$100=F$1)) /COUNTIF(final_df!$E$2:$E$100, F$1) -> 0.64285714 | G34: =SUMPRODUCT((INDEX(final_df!$B$2:$ZZ$100,,MATCH($C34,final_df!$B$1:$ZZ$1,0))>0)*(final_df!$AM$2:$AM$100=G$1)) /COUNTIF(final_df!$AM$2:$AM$100, G$1) -> 0.38888889 | H34: =SUMPRODUCT((INDEX(final_df!$B$2:$ZZ$100,,MATCH($C34,final_df!$B$1:$ZZ$1,0))>0)*(final_df!$AM$2:$AM$100=H$1)) /COUNTIF(final_df!$AM$2:$AM$100, H$1) -> 0.63157895 | I34: =SUMPRODUCT((INDEX(final_df!$B$2:$ZZ$100,,MATCH($C34,final_df!$B$1:$ZZ$1,0))>0)*(final_df!$AM$2:$AM$100=I$1)) /COUNTIF(final_df!$AM$2:$AM$100, I$1) -> 0.84210526
B35: Vásárlás / boltok / szolgáltatások | C35: Utcahasználat (jelenleg) - Vásárlás / boltok / szolgáltatások | D35: =SUMPRODUCT((INDEX(final_df!$B$2:$ZZ$100,,MATCH(C35,final_df!$B$1:$ZZ$1,0))>0)*1)/56 -> 0.94642857 | E35: =SUMPRODUCT((INDEX(final_df!$B$2:$ZZ$100,,MATCH($C35,final_df!$B$1:$ZZ$1,0))>0)*(final_df!$E$2:$E$100=E$1)) /COUNTIF(final_df!$E$2:$E$100, E$1) -> 0.89285714 | F35: =SUMPRODUCT((INDEX(final_df!$B$2:$ZZ$100,,MATCH($C35,final_df!$B$1:$ZZ$1,0))>0)*(final_df!$E$2:$E$100=F$1)) /COUNTIF(final_df!$E$2:$E$100, F$1) -> 1 | G35: =SUMPRODUCT((INDEX(final_df!$B$2:$ZZ$100,,MATCH($C35,final_df!$B$1:$ZZ$1,0))>0)*(final_df!$AM$2:$AM$100=G$1)) /COUNTIF(final_df!$AM$2:$AM$100, G$1) -> 1 | H35: =SUMPRODUCT((INDEX(final_df!$B$2:$ZZ$100,,MATCH($C35,final_df!$B$1:$ZZ$1,0))>0)*(final_df!$AM$2:$AM$100=H$1)) /COUNTIF(final_df!$AM$2:$AM$100, H$1) -> 0.94736842 | I35: =SUMPRODUCT((INDEX(final_df!$B$2:$ZZ$100,,MATCH($C35,final_df!$B$1:$ZZ$1,0))>0)*(final_df!$AM$2:$AM$100=I$1)) /COUNTIF(final_df!$AM$2:$AM$100, I$1) -> 0.89473684
